Workbook
Name Embark: dEmbarks[Embark]
Name ListaClientes: dClientes[Client]
Name ListaRigs: dRig[Rig]
Name SegmentaçãodeDados_Client: #N/A
Name SegmentaçãodeDados_Rig: #N/A
Name SoW: dSoWDetail[SoW]
Name WO: dWOs[WO]

Sheet Planilha3
A5: Soma de Total | B5: Rótulos de Coluna
A6: Rótulos de Linha | B6: (vazio) | C6: 45658 | D6: 45689 | E6: 45717 | F6: Total Geral
A7: (vazio) | B7: 172843.88 | C7: 8162857.9 | D7: 11040023 | E7: 4327137.4 | F7: 23702862
A8: 1328 | B8: 172843.88 | C8: 8162857.9 | D8: 11040023 | E8: 4327137.4 | F8: 23702862
A9: 1641 | B9: 172843.88 | C9: 8162857.9 | D9: 11040023 | E9: 4327137.4 | F9: 23702862
A10: 1656 | B10: 172843.88 | C10: 8162857.9 | D10: 11040023 | E10: 4327137.4 | F10: 23702862
A11: 1671 | B11: 172843.88 | C11: 8162857.9 | D11: 11040023 | E11: 4327137.4 | F11: 23702862
A12: 1713 | B12: 172843.88 | C12: 8162857.9 | D12: 11040023 | E12: 4327137.4 | F12: 23702862
A13: 1729 | B13: 172843.88 | C13: 8162857.9 | D13: 11040023 | E13: 4327137.4 | F13: 23702862
A14: 1730 | B14: 172843.88 | C14: 8162857.9 | D14: 11040023 | E14: 4327137.4 | F14: 23702862
A15: 1737 | B15: 172843.88 | C15: 8162857.9 | D15: 11040023 | E15: 4327137.4 | F15: 23702862
A16: 1739 | B16: 172843.88 | C16: 8162857.9 | D16: 11040023 | E16: 4327137.4 | F16: 23702862
A17: 1742 | B17: 172843.88 | C17: 8162857.9 | D17: 11040023 | E17: 4327137.4 | F17: 23702862
A18: 1746 | B18: 172843.88 | C18: 8162857.9 | D18: 11040023 | E18: 4327137.4 | F18: 23702862
A19: 1754 | B19: 172843.88 | C19: 8162857.9 | D19: 11040023 | E19: 4327137.4 | F19: 23702862
... A1035: 3360 | B1035: 172843.88 | C1035: 8162857.9 | D1035: 11040023 | E1035: 4327137.4 | F1035: 23702862
A1036: Total Geral | B1036: 172843.88 | C1036: 8162857.9 | D1036: 11040023 | E1036: 4327137.4 | F1036: 23702862

Sheet Input
A1: Month | B1: E/F | C1: Embark | D1: WO | E1: Contract Category | F1: Cliente | G1: Rig | H1: Quote | I1: Start Date | J1: End Date | K1: Amount Charged | L1: Value | M1: Pending Amount | N1: DI | O1: DI Date | P1: Number of Invoice | Q1: InvoiceTotal Value | R1: Invoice Date | S1: Days NF-Des | T1: Rental Equipment Invoice (REI) | U1: Rental Equipment Invoice Value | V1: REI Date | W1: Days FL-Des | X1: WIP | Y1: Daily | Z1: Stand-by | AA1: Total Daily | AB1: Personal | AC1: Stand-by $ | AD1: Personel Logistics | AE1: Hotel / Meal | AF1: Equipment In Transit | AG1: Material | AH1: Log de Materials | AI1: Exchange rate variation | AJ1: LOP | AK1: Tags & Slings | AL1: Extra Time | AM1: Others | AN1: ART (Technical Responsibility) | AO1: Engineering | AP1: Total | AQ1: Ticket Médio
A2: 46054 | B2: F | D2: 3344 | E2: Inspection Contract - Variable | F2: Modec | G2: MV-24 | H2: 4711 | I2: 45858 | J2: 45897 | K2: 47.14 | L2: =SUM(TabProd[[#This Row],[Personal]:[Engineering]]) -> 47.14 | M2: =IF(TabProd[[#This Row],[Amount Charged]]<>TabProd[[#This Row],[Value]],TabProd[[#This Row],[Amount Charged]]-TabProd[[#This Row],[Value]],"") | N2: 4914 | O2: 46010 | P2: 1721 | Q2: 47.14 | R2: 46066 | S2: =IF(R2="","",R2-J2) -> 169 | W2: =IF(V2="","",V2-J2) | X2: =TabProd[[#This Row],[Value]]-TabProd[[#This Row],[InvoiceTotal Value]]-TabProd[[#This Row],[Rental Equipment Invoice Value]]+AR1 -> 0 | Y2: 11 | AA2: =SUM(Y2:Z2) -> 11 | AB2: 47.14 | AP2: =SUM(AB2:AO2) -> 47.14 | AQ2: =IF(TabProd[[#This Row],[Total Daily]]=0,"",TabProd[[#This Row],[Total]]/TabProd[[#This Row],[Total Daily]]) -> 4.2854545
A3: 46023 | B3: F | D3: 3445 | E3: Engineering | F3: Helix | G3: SH2 | H3: 4912 | I3: 45901 | J3: 45930 | K3: -22800 | L3: =SUM(TabProd[[#This Row],[Personal]:[Engineering]]) -> -22800 | M3: =IF(TabProd[[#This Row],[Amount Charged]]<>TabProd[[#This Row],[Value]],TabProd[[#This Row],[Amount Charged]]-TabProd[[#This Row],[Value]],"") | N3: 5089 | O3: 45932 | P3: 0 | Q3: -22800 | S3: =IF(R3="","",R3-J3) | W3: =IF(V3="","",V3-J3) | X3: =TabProd[[#This Row],[Value]]-TabProd[[#This Row],[InvoiceTotal Value]]-TabProd[[#This Row],[Rental Equipment Invoice Value]]+AR3 -> 0 | AA3: =SUM(Y3:Z3) -> 0 | AO3: -22800 | AP3: =SUM(AB3:AO3) -> -22800 | AQ3: =IF(TabProd[[#This Row],[Total Daily]]=0,"",TabProd[[#This Row],[Total]]/TabProd[[#This Row],[Total Daily]])
A4: 46023 | B4: F | D4: 3573 | E4: Inspection Spot | F4: Oceaneering | G4: PBS | H4: 5136 | I4: 45918 | J4: 45921 | K4: -13814.4 | L4: =SUM(TabProd[[#This Row],[Personal]:[Engineering]]) -> -13814.4 | M4: =IF(TabProd[[#This Row],[Amount Charged]]<>TabProd[[#This Row],[Value]],TabProd[[#This Row],[Amount Charged]]-TabProd[[#This Row],[Value]],"") | N4: 5085 | O4: 45930 | P4: 3912 | Q4: -13814.4 | R4: 45968 | S4: =IF(R4="","",R4-J4) -> 47 | W4: =IF(V4="","",V4-J4) | X4: =TabProd[[#This Row],[Value]]-TabProd[[#This Row],[InvoiceTotal Value]]-TabProd[[#This Row],[Rental Equipment Invoice Value]]+AR3 -> 1.8189894e-12 | Y4: -6 | AA4: =SUM(Y4:Z4) -> -6 | AB4: -12614.4 | AG4: -1200 | AP4: =SUM(AB4:AO4) -> -13814.4 | AQ4: =IF(TabProd[[#This Row],[Total Daily]]=0,"",TabProd[[#This Row],[Total]]/TabProd[[#This Row],[Total Daily]]) -> 2302.4
A5: 46023 | B5: F | D5: 3475 | E5: Inspection Contract - Variable | F5: Transocean | G5: Corcovado | H5: 4881 | I5: 45929 | J5: 45933 | K5: -148800.8 | L5: =SUM(TabProd[[#This Row],[Personal]:[Engineering]]) -> -148800.8 | M5: =IF(TabProd[[#This Row],[Amount Charged]]<>TabProd[[#This Row],[Value]],TabProd[[#This Row],[Amount Charged]]-TabProd[[#This Row],[Value]],"") | N5: 5189 | P5: 1445 | Q5: 506.6 | R5: 45974 | S5: =IF(R5="","",R5-J5) -> 41 | T5: 903 | U5: -149307.4 | V5: 46339 | W5: =IF(V5="","",V5-J5) -> 406 | X5: =TabProd[[#This Row],[Value]]-TabProd[[#This Row],[InvoiceTotal Value]]-TabProd[[#This Row],[Rental Equipment Invoice Value]]+AR4 -> 0 | AA5: =SUM(Y5:Z5) -> 0 | AD5: 164.81 | AE5: 341.79 | AG5: -149307.4 | AP5: =SUM(AB5:AO5) -> -148800.8 | AQ5: =IF(TabProd[[#This Row],[Total Daily]]=0,"",TabProd[[#This Row],[Total]]/TabProd[[#This Row],[Total Daily]])
A6: 46023 | B6: F | D6: 3445 | E6: Engineering | F6: Helix | G6: SH2 | H6: 4912 | I6: 45931 | J6: 45961 | K6: -22800 | L6: =SUM(TabProd[[#This Row],[Personal]:[Engineering]]) -> -22800 | M6: =IF(TabProd[[#This Row],[Amount Charged]]<>TabProd[[#This Row],[Value]],TabProd[[#This Row],[Amount Charged]]-TabProd[[#This Row],[Value]],"") | N6: 5154 | P6: 0 | Q6: -22800 | S6: =IF(R6="","",R6-J6) | W6: =IF(V6="","",V6-J6) | X6: =TabProd[[#This Row],[Value]]-TabProd[[#This Row],[InvoiceTotal Value]]-TabProd[[#This Row],[Rental Equipment Invoice Value]]+AR6 -> 0 | AA6: =SUM(Y6:Z6) -> 0 | AO6: -22800 | AP6: =SUM(AB6:AO6) -> -22800 | AQ6: =IF(TabProd[[#This Row],[Total Daily]]=0,"",TabProd[[#This Row],[Total]]/TabProd[[#This Row],[Total Daily]])
A7: 46023 | B7: F | D7: 3292 | E7: Inspection Contract - Fixed Team | F7: Helix | G7: SH1 | H7: 3970 | I7: 45933 | J7: 45961 | K7: 30438.26 | L7: =SUM(TabProd[[#This Row],[Personal]:[Engineering]]) -> 30438.26 | M7: =IF(TabProd[[#This Row],[Amount Charged]]<>TabProd[[#This Row],[Value]],TabProd[[#This Row],[Amount Charged]]-TabProd[[#This Row],[Value]],"") | N7: 5177 | P7: 1448 | Q7: 30438.26 | R7: 45974 | S7: =IF(R7="","",R7-J7) -> 13 | T7: 905 | U7: 0 | V7: 45974 | W7: =IF(V7="","",V7-J7) -> 13 | X7: =TabProd[[#This Row],[Value]]-TabProd[[#This Row],[InvoiceTotal Value]]-TabProd[[#This Row],[Rental Equipment Invoice Value]]+AR7 -> 0 | AA7: =SUM(Y7:Z7) -> 0 | AB7: 23768.52 | AE7: 538.2 | AL7: 6131.54 | AP7: =SUM(AB7:AO7) -> 30438.26 | AQ7: =IF(TabProd[[#This Row],[Total Daily]]=0,"",TabProd[[#This Row],[Total]]/TabProd[[#This Row],[Total Daily]])
A8: 46023 | B8: F | D8: 3045 | E8: Maintenance Contract - Variable | F8: Helix | G8: SH1 | H8: 3983 | I8: 45940 | J8: 45954 | K8: 864 | L8: =SUM(TabProd[[#This Row],[Personal]:[Engineering]]) -> 864 | M8: =IF(TabProd[[#This Row],[Amount Charged]]<>TabProd[[#This Row],[Value]],TabProd[[#This Row],[Amount Charged]]-TabProd[[#This Row],[Value]],"") | N8: 5204 | O8: 45965 | P8: 1447 | Q8: 864 | R8: 45974 | S8: =IF(R8="","",R8-J8) -> 20 | T8: 904 | U8: 0 | V8: 45974 | W8: =IF(V8="","",V8-J8) -> 20 | X8: =TabProd[[#This Row],[Value]]-TabProd[[#This Row],[InvoiceTotal Value]]-TabProd[[#This Row],[Rental Equipment Invoice Value]]+AR8 -> 0 | AA8: =SUM(Y8:Z8) -> 0 | AD8: 864 | AP8: =SUM(AB8:AO8) -> 864 | AQ8: =IF(TabProd[[#This Row],[Total Daily]]=0,"",TabProd[[#This Row],[Total]]/TabProd[[#This Row],[Total Daily]])
A9: 46023 | B9: F | D9: 3380 | E9: Inspection Contract - Variable | F9: Modec | G9: MV-20 | H9: 4784 | I9: 45943 | J9: 45953 | K9: -4977.39 | L9: =SUM(TabProd[[#This Row],[Personal]:[Engineering]]) -> -4977.39 | M9: =IF(TabProd[[#This Row],[Amount Charged]]<>TabProd[[#This Row],[Value]],TabProd[[#This Row],[Amount Charged]]-TabProd[[#This Row],[Value]],"") | N9: 5183 | O9: 46028 | P9: 1620 | Q9: -4977.39 | R9: 46041 | S9: =IF(R9="","",R9-J9) -> 88 | W9: =IF(V9="","",V9-J9) | X9: =TabProd[[#This Row],[Value]]-TabProd[[#This Row],[InvoiceTotal Value]]-TabProd[[#This Row],[Rental Equipment Invoice Value]]+AR9 -> 0 | Y9: -1 | AA9: =SUM(Y9:Z9) -> -1 | AB9: -4977.39 | AP9: =SUM(AB9:AO9) -> -4977.39 | AQ9: =IF(TabProd[[#This Row],[Total Daily]]=0,"",TabProd[[#This Row],[Total]]/TabProd[[#This Row],[Total Daily]]) -> 4977.39
A10: 46023 | B10: F | D10: 3580 | E10: Inspection Contract - Variable | F10: SEA1 | G10: SH1 | H10: 5158 | I10: 45943 | J10: 45954 | K10: -78483.6 | L10: =SUM(TabProd[[#This Row],[Personal]:[Engineering]]) -> -78483.6 | M10: =IF(TabProd[[#This Row],[Amount Charged]]<>TabProd[[#This Row],[Value]],TabProd[[#This Row],[Amount Charged]]-TabProd[[#This Row],[Value]],"") | N10: 5172 | P10: 0 | Q10: -78483.6 | S10: =IF(R10="","",R10-J10) | W10: =IF(V10="","",V10-J10) | X10: =TabProd[[#This Row],[Value]]-TabProd[[#This Row],[InvoiceTotal Value]]-TabProd[[#This Row],[Rental Equipment Invoice Value]]+AR9 -> 0 | Y10: -30 | AA10: =SUM(Y10:Z10) -> -30 | AB10: -62856 | AD10: -2160 | AG10: -10281.6 | AH10: -3186 | AP10: =SUM(AB10:AO10) -> -78483.6 | AQ10: =IF(TabProd[[#This Row],[Total Daily]]=0,"",TabProd[[#This Row],[Total]]/TabProd[[#This Row],[Total Daily]]) -> 2616.12
A11: 46023 | B11: F | D11: 3606 | E11: Equipment Rental | F11: Helix | G11: SH1 | H11: 5228 | I11: 45960 | J11: 45969 | K11: 27319.68 | L11: =SUM(TabProd[[#This Row],[Personal]:[Engineering]]) -> 27319.68 | M11: =IF(TabProd[[#This Row],[Amount Charged]]<>TabProd[[#This Row],[Value]],TabProd[[#This Row],[Amount Charged]]-TabProd[[#This Row],[Value]],"") | N11: 5237 | O11: 46079 | S11: =IF(R11="","",R11-J11) | T11: 1109 | U11: 27319.68 | V11: 46099 | W11: =IF(V11="","",V11-J11) -> 130 | X11: =TabProd[[#This Row],[Value]]-TabProd[[#This Row],[InvoiceTotal Value]]-TabProd[[#This Row],[Rental Equipment Invoice Value]]+AR8 -> -3.6379788e-12 | AA11: =SUM(Y11:Z11) -> 0 | AG11: 27319.68 | AP11: =SUM(AB11:AO11) -> 27319.68 | AQ11: =IF(TabProd[[#This Row],[Total Daily]]=0,"",TabProd[[#This Row],[Total]]/TabProd[[#This Row],[Total Daily]])
A12: 46054 | B12: F | D12: 3608 | E12: Inspection Contract - Variable | F12: Helix | G12: SH1 | H12: 5202 | I12: 45960 | J12: 46054 | K12: 43152 | L12: =SUM(TabProd[[#This Row],[Personal]:[Engineering]]) -> 43152 | M12: =IF(TabProd[[#This Row],[Amount Charged]]<>TabProd[[#This Row],[Value]],TabProd[[#This Row],[Amount Charged]]-TabProd[[#This Row],[Value]],"") | N12: 5299 | O12: 46066 | P12: 1743 | Q12: 43152 | R12: 46084 | S12: =IF(R12="","",R12-J12) -> 30 | W12: =IF(V12="","",V12-J12) | X12: =TabProd[[#This Row],[Value]]-TabProd[[#This Row],[InvoiceTotal Value]]-TabProd[[#This Row],[Rental Equipment Invoice Value]]+AR11 -> 0 | AA12: =SUM(Y12:Z12) -> 0 | AN12: 405 | AO12: 42747 | AP12: =SUM(AB12:AO12) -> 43152 | AQ12: =IF(TabProd[[#This Row],[Total Daily]]=0,"",TabProd[[#This Row],[Total]]/TabProd[[#This Row],[Total Daily]])
A13: 46082 | B13: F | D13: 3606 | E13: Equipment Rental | F13: Helix | G13: SH1 | H13: 5228 | I13: 45960 | J13: 45969 | K13: -33827.76 | L13: =SUM(TabProd[[#This Row],[Personal]:[Engineering]]) -> -33827.76 | M13: =IF(TabProd[[#This Row],[Amount Charged]]<>TabProd[[#This Row],[Value]],TabProd[[#This Row],[Amount Charged]]-TabProd[[#This Row],[Value]],"") | N13: 5237 | O13: 46079 | S13: =IF(R13="","",R13-J13) | T13: 1109 | U13: -33827.76 | V13: 46099 | W13: =IF(V13="","",V13-J13) -> 130 | X13: =TabProd[[#This Row],[Value]]-TabProd[[#This Row],[InvoiceTotal Value]]-TabProd[[#This Row],[Rental Equipment Invoice Value]]+AR13 -> 0 | AA13: =SUM(Y13:Z13) -> 0 | AG13: -33827.76 | AP13: =SUM(AB13:AO13) -> -33827.76 | AQ13: =IF(TabProd[[#This Row],[Total Daily]]=0,"",TabProd[[#This Row],[Total]]/TabProd[[#This Row],[Total Daily]])
A14: 46054 | B14: F | D14: 3359 | E14: Inspection Spot | F14: Seadrill | G14: West Jupiter | H14: 4730 | I14: 45962 | J14: 45991 | K14: -83864 | L14: =SUM(TabProd[[#This Row],[Personal]:[Engineering]]) -> -83864 | M14: =IF(TabProd[[#This Row],[Amount Charged]]<>TabProd[[#This Row],[Value]],TabProd[[#This Row],[Amount Charged]]-TabProd[[#This Row],[Value]],"") | N14: 5244 | O14: 45992 | P14: 19 | Q14: -83864 | R14: 46078 | S14: =IF(R14="","",R14-J14) -> 87 | T14: 2556 | V14: 46078 | W14: =IF(V14="","",V14-J14) -> 87 | X14: =TabProd[[#This Row],[Value]]-TabProd[[#This Row],[InvoiceTotal Value]]-TabProd[[#This Row],[Rental Equipment Invoice Value]]+AR14 -> 0 | AA14: =SUM(Y14:Z14) -> 0 | AM14: -83864 | AP14: =SUM(AB14:AO14) -> -83864 | AQ14: =IF(TabProd[[#This Row],[Total Daily]]=0,"",TabProd[[#This Row],[Total]]/TabProd[[#This Row],[Total Daily]])
A15: 46023 | B15: F | D15: 3292 | E15: Inspection Contract - Fixed Team | F15: Helix | G15: SH1 | H15: 3970 | I15: 45969 | J15: 45975 | K15: -45179.75 | L15: =SUM(TabProd[[#This Row],[Personal]:[Engineering]]) -> -45179.75 | M15: =IF(TabProd[[#This Row],[Amount Charged]]<>TabProd[[#This Row],[Value]],TabProd[[#This Row],[Amount Charged]]-TabProd[[#This Row],[Value]],"") | N15: 5256 | O15: 46001 | P15: 1623 | Q15: -27107.85 | R15: 46041 | S15: =IF(R15="","",R15-J15) -> 66 | T15: 1004 | U15: -18071.9 | V15: 46041 | W15: =IF(V15="","",V15-J15) -> 66 | X15: =TabProd[[#This Row],[Value]]-TabProd[[#This Row],[InvoiceTotal Value]]-TabProd[[#This Row],[Rental Equipment Invoice Value]]+AR15 -> 0 | Y15: -6 | AA15: =SUM(Y15:Z15) -> -6 | AB15: -27107.85 | AG15: -18071.9 | AP15: =SUM(AB15:AO15) -> -45179.75 | AQ15: =IF(TabProd[[#This Row],[Total Daily]]=0,"",TabProd[[#This Row],[Total]]/TabProd[[#This Row],[Total Daily]]) -> 7529.9583
A16: 46082 | B16: F | D16: 3572 | E16: Maintenance Spot | F16: Archer | G16: Peregrino Alpha | H16: 5145 | I16: 45973 | J16: 45991 | K16: 870.16 | L16: =SUM(TabProd[[#This Row],[Personal]:[Engineering]]) -> 870.16 | M16: =IF(TabProd[[#This Row],[Amount Charged]]<>TabProd[[#This Row],[Value]],TabProd[[#This Row],[Amount Charged]]-TabProd[[#This Row],[Value]],"") | N16: 5249 | O16: 46021 | P16: 1781 | Q16: 870.16 | R16: 46091 | S16: =IF(R16="","",R16-J16) -> 100 | W16: =IF(V16="","",V16-J16) | X16: =TabProd[[#This Row],[Value]]-TabProd[[#This Row],[InvoiceTotal Value]]-TabProd[[#This Row],[Rental Equipment Invoice Value]]+AR16 -> -1.1368684e-13 | Y16: -7 | AA16: =SUM(Y16:Z16) -> -7 | AB16: -1881.08 | AD16: 2751.24 | AP16: =SUM(AB16:AO16) -> 870.16 | AQ16: =IF(TabProd[[#This Row],[Total Daily]]=0,"",TabProd[[#This Row],[Total]]/TabProd[[#This Row],[Total Daily]]) -> -124.30857
A17: 46054 | B17: F | D17: 3593 | E17: Inspection Spot | F17: Modec | G17: MV-18 | H17: 5154 | I17: 45977 | J17: 45983 | K17: -4996.4 | L17: =SUM(TabProd[[#This Row],[Personal]:[Engineering]]) -> -4996.4 | M17: =IF(TabProd[[#This Row],[Amount Charged]]<>TabProd[[#This Row],[Value]],TabProd[[#This Row],[Amount Charged]]-TabProd[[#This Row],[Value]],"") | N17: 5270 | O17: 46020 | P17: 2 | Q17: -4996.4 | R17: 46028 | S17: =IF(R17="","",R17-J17) -> 45 | W17: =IF(V17="","",V17-J17) | X17: =TabProd[[#This Row],[Value]]-TabProd[[#This Row],[InvoiceTotal Value]]-TabProd[[#This Row],[Rental Equipment Invoice Value]]+AR16 -> 0 | AA17: =SUM(Y17:Z17) -> 0 | AG17: -12726 | AH17: 7729.6 | AP17: =SUM(AB17:AO17) -> -4996.4 | AQ17: =IF(TabProd[[#This Row],[Total Daily]]=0,"",TabProd[[#This Row],[Total]]/TabProd[[#This Row],[Total Daily]])
A18: 46023 | B18: F | D18: 3616 | E18: Inspection Spot | F18: Modec | G18: MV-18 | H18: 5233 | I18: 45980 | J18: 46355 | K18: -11538.3 | L18: =SUM(TabProd[[#This Row],[Personal]:[Engineering]]) -> -11538.3 | M18: =IF(TabProd[[#This Row],[Amount Charged]]<>TabProd[[#This Row],[Value]],TabProd[[#This Row],[Amount Charged]]-TabProd[[#This Row],[Value]],"") | N18: 5268 | O18: 46020 | P18: 1579 | Q18: -10581.5 | R18: 46034 | S18: =IF(R18="","",R18-J18) -> -321 | T18: 988 | U18: -956.8 | V18: 46034 | W18: =IF(V18="","",V18-J18) -> -321 | X18: =TabProd[[#This Row],[Value]]-TabProd[[#This Row],[InvoiceTotal Value]]-TabProd[[#This Row],[Rental Equipment Invoice Value]]+AR17 -> -1.8189894e-12 | Y18: -4 | Z18: -2 | AA18: =SUM(Y18:Z18) -> -6 | AB18: -8574.4 | AC18: -2005.6 | AE18: -1.5 | AG18: -956.8 | AP18: =SUM(AB18:AO18) -> -11538.3 | AQ18: =IF(TabProd[[#This Row],[Total Daily]]=0,"",TabProd[[#This Row],[Total]]/TabProd[[#This Row],[Total Daily]]) -> 1923.05
A19: 46023 | B19: F | D19: 3427 | E19: Maintenance Contract - Variable | F19: Foresea | G19: ODN I | H19: 4892 | I19: 45984 | J19: 46005 | K19: -3775.38 | L19: =SUM(TabProd[[#This Row],[Personal]:[Engineering]]) -> -3775.38 | M19: =IF(TabProd[[#This Row],[Amount Charged]]<>TabProd[[#This Row],[Value]],TabProd[[#This Row],[Amount Charged]]-TabProd[[#This Row],[Value]],"") | N19: 5272-5361 | O19: 46028 | P19: 1574 | Q19: 0 | R19: 46031 | S19: =IF(R19="","",R19-J19) -> 26 | T19: 983-984 | U19: -3775.38 | V19: 46031 | W19: =IF(V19="","",V19-J19) -> 26 | X19: =TabProd[[#This Row],[Value]]-TabProd[[#This Row],[InvoiceTotal Value]]-TabProd[[#This Row],[Rental Equipment Invoice Value]]+AR19 -> 0 | AA19: =SUM(Y19:Z19) -> 0 | AG19: -3775.38 | AP19: =SUM(AB19:AO19) -> -3775.38 | AQ19: =IF(TabProd[[#This Row],[Total Daily]]=0,"",TabProd[[#This Row],[Total]]/TabProd[[#This Row],[Total Daily]])
A20: 46023 | B20: F | D20: 3545 | E20: Inspection Contract - Variable | F20: Constellation | G20: Gold Star | H20: 5088 | I20: 45985 | J20: 46034 | K20: 50168 | L20: =SUM(TabProd[[#This Row],[Personal]:[Engineering]]) -> 50168 | M20: =IF(TabProd[[#This Row],[Amount Charged]]<>TabProd[[#This Row],[Value]],TabProd[[#This Row],[Amount Charged]]-TabProd[[#This Row],[Value]],"") | N20: 5388-5513-5514 | O20: 46035 | S20: =IF(R20="","",R20-J20) | T20: 1059-1060-1066 | U20: 50168 | V20: 46072 | W20: =IF(V20="","",V20-J20) -> 38 | X20: =TabProd[[#This Row],[Value]]-TabProd[[#This Row],[InvoiceTotal Value]]-TabProd[[#This Row],[Rental Equipment Invoice Value]]+AR19 -> 0 | AA20: =SUM(Y20:Z20) -> 0 | AG20: 49000 | AH20: 1168 | AP20: =SUM(AB20:AO20) -> 50168 | AQ20: =IF(TabProd[[#This Row],[Total Daily]]=0,"",TabProd[[#This Row],[Total]]/TabProd[[#This Row],[Total Daily]])
A21: 46023 | B21: F | D21: 3563 | E21: Inspection Spot | F21: Technip | G21: Skandi Vitoria | H21: 5031 | I21: 45986 | J21: 46031 | K21: 25322.08 | L21: =SUM(TabProd[[#This Row],[Personal]:[Engineering]]) -> 25322.08 | M21: =IF(TabProd[[#This Row],[Amount Charged]]<>TabProd[[#This Row],[Value]],TabProd[[#This Row],[Amount Charged]]-TabProd[[#This Row],[Value]],"") | N21: 5434 | O21: 46043 | S21: =IF(R21="","",R21-J21) | T21: 2555 | U21: 25322.08 | V21: 46076 | W21: =IF(V21="","",V21-J21) -> 45 | X21: =TabProd[[#This Row],[Value]]-TabProd[[#This Row],[InvoiceTotal Value]]-TabProd[[#This Row],[Rental Equipment Invoice Value]]+AR20 -> 0 | AA21: =SUM(Y21:Z21) -> 0 | AG21: 25322.08 | AP21: =SUM(AB21:AO21) -> 25322.08 | AQ21: =IF(TabProd[[#This Row],[Total Daily]]=0,"",TabProd[[#This Row],[Total]]/TabProd[[#This Row],[Total Daily]])
A22: 46082 | B22: F | D22: 3535 | E22: Inspection Spot | F22: Trident | G22: P-65 | H22: 5008 | I22: 45988 | J22: 46001 | K22: 1094.8 | L22: =SUM(TabProd[[#This Row],[Personal]:[Engineering]]) -> 1094.8 | M22: =IF(TabProd[[#This Row],[Amount Charged]]<>TabProd[[#This Row],[Value]],TabProd[[#This Row],[Amount Charged]]-TabProd[[#This Row],[Value]],"") | N22: 5276-5560 | O22: 46385 | P22: 1818-1823 | Q22: 1094.8 | R22: 46104 | S22: =IF(R22="","",R22-J22) -> 103 | W22: =IF(V22="","",V22-J22) | X22: =TabProd[[#This Row],[Value]]-TabProd[[#This Row],[InvoiceTotal Value]]-TabProd[[#This Row],[Rental Equipment Invoice Value]]+AR22 -> 0 | AA22: =SUM(Y22:Z22) -> 0 | AM22: 1094.8 | AP22: =SUM(AB22:AO22) -> 1094.8 | AQ22: =IF(TabProd[[#This Row],[Total Daily]]=0,"",TabProd[[#This Row],[Total]]/TabProd[[#This Row],[Total Daily]])
A23: 46054 | B23: F | D23: 3563 | E23: Inspection Spot | F23: Technip | G23: Skandi Vitoria | H23: 5031 | I23: 45990 | J23: 46004 | K23: -25697.08 | L23: =SUM(TabProd[[#This Row],[Personal]:[Engineering]]) -> -25697.08 | M23: =IF(TabProd[[#This Row],[Amount Charged]]<>TabProd[[#This Row],[Value]],TabProd[[#This Row],[Amount Charged]]-TabProd[[#This Row],[Value]],"") | N23: 5281-5559 | O23: 46034 | P23: 23-28 | Q23: -2092.5 | R23: 46104 | S23: =IF(R23="","",R23-J23) -> 100 | T23: 2559 | U23: -23604.58 | V23: 46179 | W23: =IF(V23="","",V23-J23) -> 175 | X23: =TabProd[[#This Row],[Value]]-TabProd[[#This Row],[InvoiceTotal Value]]-TabProd[[#This Row],[Rental Equipment Invoice Value]]+AR23 -> 0 | AA23: =SUM(Y23:Z23) -> 0 | AG23: -25322.08 | AN23: -375 | AP23: =SUM(AB23:AO23) -> -25697.08 | AQ23: =IF(TabProd[[#This Row],[Total Daily]]=0,"",TabProd[[#This Row],[Total]]/TabProd[[#This Row],[Total Daily]])
A24: 46023 | B24: F | D24: 3341 | E24: Inspection Spot | F24: Seadrill | G24: West Tellus | H24: 4693 | I24: 45992 | J24: 46022 | K24: -9000 | L24: =SUM(TabProd[[#This Row],[Personal]:[Engineering]]) -> -9000 | M24: =IF(TabProd[[#This Row],[Amount Charged]]<>TabProd[[#This Row],[Value]],TabProd[[#This Row],[Amount Charged]]-TabProd[[#This Row],[Value]],"") | N24: 5312 | O24: 46024 | P24: 1655 | Q24: -9000 | R24: 46048 | S24: =IF(R24="","",R24-J24) -> 26 | T24: 1017 | U24: 0 | V24: 46048 | W24: =IF(V24="","",V24-J24) -> 26 | X24: =TabProd[[#This Row],[Value]]-TabProd[[#This Row],[InvoiceTotal Value]]-TabProd[[#This Row],[Rental Equipment Invoice Value]]+AR24 -> 0 | AA24: =SUM(Y24:Z24) -> 0 | AM24: -9000 | AP24: =SUM(AB24:AO24) -> -9000 | AQ24: =IF(TabProd[[#This Row],[Total Daily]]=0,"",TabProd[[#This Row],[Total]]/TabProd[[#This Row],[Total Daily]])
A25: 46023 | B25: F | D25: 3300 | E25: Inspection Contract - Fixed Team | F25: Transocean | G25: Corcovado | H25: 1877 | I25: 45992 | J25: 46022 | K25: 525.5 | L25: =SUM(TabProd[[#This Row],[Personal]:[Engineering]]) -> 525.5 | M25: =IF(TabProd[[#This Row],[Amount Charged]]<>TabProd[[#This Row],[Value]],TabProd[[#This Row],[Amount Charged]]-TabProd[[#This Row],[Value]],"") | N25: 5403 | O25: 46036 | P25: 1614 | Q25: 525.5 | R25: 46038 | S25: =IF(R25="","",R25-J25) -> 16 | W25: =IF(V25="","",V25-J25) | X25: =TabProd[[#This Row],[Value]]-TabProd[[#This Row],[InvoiceTotal Value]]-TabProd[[#This Row],[Rental Equipment Invoice Value]]+AR25 -> 0 | AA25: =SUM(Y25:Z25) -> 0 | AL25: 525.5 | AP25: =SUM(AB25:AO25) -> 525.5 | AQ25: =IF(TabProd[[#This Row],[Total Daily]]=0,"",TabProd[[#This Row],[Total]]/TabProd[[#This Row],[Total Daily]])
A26: 46023 | B26: F | D26: 3627 | E26: Inspection Contract - Variable | F26: Transocean | G26: KG2 | H26: 5249 | I26: 45996 | J26: 46011 | K26: 3079.23 | L26: =SUM(TabProd[[#This Row],[Personal]:[Engineering]]) -> 3079.23 | M26: =IF(TabProd[[#This Row],[Amount Charged]]<>TabProd[[#This Row],[Value]],TabProd[[#This Row],[Amount Charged]]-TabProd[[#This Row],[Value]],"") | N26: 5320 | O26: 46036 | P26: 1628 | Q26: 967.7 | R26: 46041 | S26: =IF(R26="","",R26-J26) -> 30 | T26: 1006 | U26: 2111.53 | V26: 46041 | W26: =IF(V26="","",V26-J26) -> 30 | X26: =TabProd[[#This Row],[Value]]-TabProd[[#This Row],[InvoiceTotal Value]]-TabProd[[#This Row],[Rental Equipment Invoice Value]]+AR25 -> 4.5474735e-13 | AA26: =SUM(Y26:Z26) -> 0 | AB26: 967.7 | AG26: 682.08 | AH26: 1429.45 | AP26: =SUM(AB26:AO26) -> 3079.23 | AQ26: =IF(TabProd[[#This Row],[Total Daily]]=0,"",TabProd[[#This Row],[Total]]/TabProd[[#This Row],[Total Daily]])
A27: 46023 | B27: F | D27: 3583 | E27: Inspection Contract - Variable | F27: Ventura | G27: DS Carolina | H27: 5137 | I27: 45999 | J27: 46013 | K27: 12008 | L27: =SUM(TabProd[[#This Row],[Personal]:[Engineering]]) -> 12008 | M27: =IF(TabProd[[#This Row],[Amount Charged]]<>TabProd[[#This Row],[Value]],TabProd[[#This Row],[Amount Charged]]-TabProd[[#This Row],[Value]],"") | N27: 5343-5384 | O27: 46030 | P27: 1581-1604 | Q27: 12608 | R27: 46037 | S27: =IF(R27="","",R27-J27) -> 24 | T27: 991 | U27: -600 | V27: 46034 | W27: =IF(V27="","",V27-J27) -> 21 | X27: =TabProd[[#This Row],[Value]]-TabProd[[#This Row],[InvoiceTotal Value]]-TabProd[[#This Row],[Rental Equipment Invoice Value]]+AR26 -> 0 | Y27: 6 | AA27: =SUM(Y27:Z27) -> 6 | AB27: 19820 | AD27: 1160 | AG27: -600 | AM27: -8372 | AP27: =SUM(AB27:AO27) -> 12008 | AQ27: =IF(TabProd[[#This Row],[Total Daily]]=0,"",TabProd[[#This Row],[Total]]/TabProd[[#This Row],[Total Daily]]) -> 2001.3333
A28: 46054 | B28: F | D28: 3607 | E28: Inspection Spot | F28: Technip | G28: Skandi Buzios | H28: 5031 | I28: 45999 | J28: 46010 | K28: -9439.83 | L28: =SUM(TabProd[[#This Row],[Personal]:[Engineering]]) -> -9439.83 | M28: =IF(TabProd[[#This Row],[Amount Charged]]<>TabProd[[#This Row],[Value]],TabProd[[#This Row],[Amount Charged]]-TabProd[[#This Row],[Value]],"") | N28: 5282 | O28: 46021 | P28: 1732 | Q28: -9439.83 | R28: 46073 | S28: =IF(R28="","",R28-J28) -> 63 | T28: 1068 | U28: 0 | V28: 46073 | W28: =IF(V28="","",V28-J28) -> 63 | X28: =TabProd[[#This Row],[Value]]-TabProd[[#This Row],[InvoiceTotal Value]]-TabProd[[#This Row],[Rental Equipment Invoice Value]]+AR27 -> 0 | AA28: =SUM(Y28:Z28) -> 0 | AB28: -4087.27 | AD28: 400 | AE28: -5752.56 | AP28: =SUM(AB28:AO28) -> -9439.83 | AQ28: =IF(TabProd[[#This Row],[Total Daily]]=0,"",TabProd[[#This Row],[Total]]/TabProd[[#This Row],[Total Daily]])
A29: 46023 | B29: F | D29: 3611 | E29: Inspection Contract - Variable | F29: Ventura | G29: DS Carolina | I29: 46002 | J29: 46005 | K29: 10320 | L29: =SUM(TabProd[[#This Row],[Personal]:[Engineering]]) -> 10320 | M29: =IF(TabProd[[#This Row],[Amount Charged]]<>TabProd[[#This Row],[Value]],TabProd[[#This Row],[Amount Charged]]-TabProd[[#This Row],[Value]],"") | N29: 5383 | O29: 46038 | P29: 1645 | Q29: 8720 | R29: 46044 | S29: =IF(R29="","",R29-J29) -> 39 | T29: 1015 | U29: 1600 | V29: 46044 | W29: =IF(V29="","",V29-J29) -> 39 | X29: =TabProd[[#This Row],[Value]]-TabProd[[#This Row],[InvoiceTotal Value]]-TabProd[[#This Row],[Rental Equipment Invoice Value]]+AR28 -> 0 | Y29: 4 | AA29: =SUM(Y29:Z29) -> 4 | AB29: 8720 | AG29: 1600 | AP29: =SUM(AB29:AO29) -> 10320 | AQ29: =IF(TabProd[[#This Row],[Total Daily]]=0,"",TabProd[[#This Row],[Total]]/TabProd[[#This Row],[Total Daily]]) -> 2580
A30: 46113 | D30: 3478 | E30: Maintenance Contract - Variable | F30: Foresea | G30: Norbe 9 | H30: 4984 | I30: 46002 | J30: 46031 | K30: 282203.41 | L30: =SUM(TabProd[[#This Row],[Personal]:[Engineering]]) -> 282203.41 | M30: =IF(TabProd[[#This Row],[Amount Charged]]<>TabProd[[#This Row],[Value]],TabProd[[#This Row],[Amount Charged]]-TabProd[[#This Row],[Value]],"") | N30: 5300 | O30: 46183 | P30: 2045 | Q30: 102100.81 | R30: 46192 | S30: =IF(R30="","",R30-J30) -> 161 | T30: 1261 | U30: 180102.6 | V30: 46192 | W30: =IF(V30="","",V30-J30) -> 161 | X30: =TabProd[[#This Row],[Value]]-TabProd[[#This Row],[InvoiceTotal Value]]-TabProd[[#This Row],[Rental Equipment Invoice Value]]+AR29 -> 2.910383e-11 | Y30: 1 | AA30: =SUM(Y30:Z30) -> 1 | AB30: 79712.78 | AC30: 22388.03 | AG30: 180102.6 | AP30: =SUM(AB30:AO30) -> 282203.41 | AQ30: =IF(TabProd[[#This Row],[Total Daily]]=0,"",TabProd[[#This Row],[Total]]/TabProd[[#This Row],[Total Daily]]) -> 282203.41
A31: 46174 | D31: 3478 | E31: Maintenance Contract - Variable | F31: Foresea | G31: Norbe 9 | H31: 4984 | I31: 46002 | J31: 46031 | K31: 14274.08 | L31: =SUM(TabProd[[#This Row],[Personal]:[Engineering]]) -> 14274.08 | M31: =IF(TabProd[[#This Row],[Amount Charged]]<>TabProd[[#This Row],[Value]],TabProd[[#This Row],[Amount Charged]]-TabProd[[#This Row],[Value]],"") | N31: 5300 | O31: 46183 | P31: 2045 | Q31: 5163.98 | R31: 46192 | S31: =IF(R31="","",R31-J31) -> 161 | T31: 1261 | U31: 9110.1 | V31: 46192 | W31: =IF(V31="","",V31-J31) -> 161 | X31: =TabProd[[#This Row],[Value]]-TabProd[[#This Row],[InvoiceTotal Value]]-TabProd[[#This Row],[Rental Equipment Invoice Value]]+AR31 -> 7.2759576e-12 | Y31: 30 | Z31: 17 | AA31: =SUM(Y31:Z31) -> 47 | AB31: 4031.63 | AC31: 1132.35 | AG31: 9110.1 | AP31: =SUM(AB31:AO31) -> 14274.08 | AQ31: =IF(TabProd[[#This Row],[Total Daily]]=0,"",TabProd[[#This Row],[Total]]/TabProd[[#This Row],[Total Daily]]) -> 303.70383
A32: 46023 | B32: F | D32: 3619 | E32: Inspection Contract - Variable | F32: Transocean | G32: Orion | H32: 5243 | I32: 46002 | J32: 46011 | K32: 1068.14 | L32: =SUM(TabProd[[#This Row],[Personal]:[Engineering]]) -> 1068.14 | M32: =IF(TabProd[[#This Row],[Amount Charged]]<>TabProd[[#This Row],[Value]],TabProd[[#This Row],[Amount Charged]]-TabProd[[#This Row],[Value]],"") | N32: 5347 | O32: 46035 | P32: 1611 | Q32: 1068.14 | R32: 46037 | S32: =IF(R32="","",R32-J32) -> 26 | T32: 1001 | U32: 0 | V32: 46037 | W32: =IF(V32="","",V32-J32) -> 26 | X32: =TabProd[[#This Row],[Value]]-TabProd[[#This Row],[InvoiceTotal Value]]-TabProd[[#This Row],[Rental Equipment Invoice Value]]+AR31 -> -4.5474735e-12 | AA32: =SUM(Y32:Z32) -> 0 | AB32: 1068.13 | AE32: 0.01 | AP32: =SUM(AB32:AO32) -> 1068.14 | AQ32: =IF(TabProd[[#This Row],[Total Daily]]=0,"",TabProd[[#This Row],[Total]]/TabProd[[#This Row],[Total Daily]])
A33: 46023 | B33: F | D33: 3541 | E33: Inspection Contract - Variable | F33: Transocean | G33: Corcovado | H33: 4931 | I33: 46008 | J33: 46021 | K33: -12789 | L33: =SUM(TabProd[[#This Row],[Personal]:[Engineering]]) -> -12789 | M33: =IF(TabProd[[#This Row],[Amount Charged]]<>TabProd[[#This Row],[Value]],TabProd[[#This Row],[Amount Charged]]-TabProd[[#This Row],[Value]],"") | N33: 5377 | O33: 46030 | S33: =IF(R33="","",R33-J33) | T33: 1007 | U33: -12789 | V33: 46041 | W33: =IF(V33="","",V33-J33) -> 20 | X33: =TabProd[[#This Row],[Value]]-TabProd[[#This Row],[InvoiceTotal Value]]-TabProd[[#This Row],[Rental Equipment Invoice Value]]+AR32 -> 0 | AA33: =SUM(Y33:Z33) -> 0 | AG33: -12789 | AP33: =SUM(AB33:AO33) -> -12789 | AQ33: =IF(TabProd[[#This Row],[Total Daily]]=0,"",TabProd[[#This Row],[Total]]/TabProd[[#This Row],[Total Daily]])
A34: 46082 | B34: F | D34: 3599 | E34: Inspection Contract - Variable | F34: Constellation | G34: Amaralina Star | H34: 4854 | I34: 46010 | J34: 46074 | K34: 173163.8 | L34: =SUM(TabProd[[#This Row],[Personal]:[Engineering]]) -> 173163.8 | M34: =IF(TabProd[[#This Row],[Amount Charged]]<>TabProd[[#This Row],[Value]],TabProd[[#This Row],[Amount Charged]]-TabProd[[#This Row],[Value]],"") | N34: 5572 | S34: =IF(R34="","",R34-J34) | T34: 1115 | U34: 173163.8 | V34: 46101 | W34: =IF(V34="","",V34-J34) -> 27 | X34: =TabProd[[#This Row],[Value]]-TabProd[[#This Row],[InvoiceTotal Value]]-TabProd[[#This Row],[Rental Equipment Invoice Value]]+AR34 -> 0 | AA34: =SUM(Y34:Z34) -> 0 | AG34: 169943.8 | AH34: 3220 | AP34: =SUM(AB34:AO34) -> 173163.8 | AQ34: =IF(TabProd[[#This Row],[Total Daily]]=0,"",TabProd[[#This Row],[Total]]/TabProd[[#This Row],[Total Daily]])
A35: 46023 | B35: F | D35: 3415 | E35: Inspection Contract - Variable | F35: Modec | G35: FPSO Bacalhau | H35: 4874 | I35: 46011 | J35: 46024 | K35: 7822.04 | L35: =SUM(TabProd[[#This Row],[Personal]:[Engineering]]) -> 7822.04 | M35: =IF(TabProd[[#This Row],[Amount Charged]]<>TabProd[[#This Row],[Value]],TabProd[[#This Row],[Amount Charged]]-TabProd[[#This Row],[Value]],"") | N35: 5364 | O35: 46029 | P35: 1653 | Q35: 7822.04 | R35: 46045 | S35: =IF(R35="","",R35-J35) -> 21 | W35: =IF(V35="","",V35-J35) | X35: =TabProd[[#This Row],[Value]]-TabProd[[#This Row],[InvoiceTotal Value]]-TabProd[[#This Row],[Rental Equipment Invoice Value]]+AR35 -> 9.094947e-13 | Y35: 6 | AA35: =SUM(Y35:Z35) -> 6 | AB35: 7822.04 | AP35: =SUM(AB35:AO35) -> 7822.04 | AQ35: =IF(TabProd[[#This Row],[Total Daily]]=0,"",TabProd[[#This Row],[Total]]/TabProd[[#This Row],[Total Daily]]) -> 1303.6733
A36: 46082 | B36: F | D36: 3572 | E36: Maintenance Spot | F36: Archer | G36: Peregrino Alpha | H36: 5145 | I36: 46011 | J36: 46022 | K36: 219668.66 | L36: =SUM(TabProd[[#This Row],[Personal]:[Engineering]]) -> 219668.66 | M36: =IF(TabProd[[#This Row],[Amount Charged]]<>TabProd[[#This Row],[Value]],TabProd[[#This Row],[Amount Charged]]-TabProd[[#This Row],[Value]],"") | N36: 5351 | O36: 46021 | P36: 1782 | Q36: 219668.66 | R36: 46091 | S36: =IF(R36="","",R36-J36) -> 69 | W36: =IF(V36="","",V36-J36) | X36: =TabProd[[#This Row],[Value]]-TabProd[[#This Row],[InvoiceTotal Value]]-TabProd[[#This Row],[Rental Equipment Invoice Value]]+AR36 -> -2.910383e-11 | AA36: =SUM(Y36:Z36) -> 0 | AB36: 72340 | AD36: 1834.16 | AG36: 119525.7 | AH36: 3864.8 | AJ36: 22104 | AP36: =SUM(AB36:AO36) -> 219668.66 | AQ36: =IF(TabProd[[#This Row],[Total Daily]]=0,"",TabProd[[#This Row],[Total]]/TabProd[[#This Row],[Total Daily]])
A37: 46082 | B37: F | D37: 3636 | E37: Maintenance Spot | F37: Archer | G37: Peregrino Alpha | H37: 5278 | I37: 46011 | J37: 46022 | K37: -219668.66 | L37: =SUM(TabProd[[#This Row],[Personal]:[Engineering]]) -> -219668.66 | M37: =IF(TabProd[[#This Row],[Amount Charged]]<>TabProd[[#This Row],[Value]],TabProd[[#This Row],[Amount Charged]]-TabProd[[#This Row],[Value]],"") | N37: 5350 | O37: 46021 | P37: 1782 | Q37: -219668.66 | R37: 46091 | S37: =IF(R37="","",R37-J37) -> 69 | W37: =IF(V37="","",V37-J37) | X37: =TabProd[[#This Row],[Value]]-TabProd[[#This Row],[InvoiceTotal Value]]-TabProd[[#This Row],[Rental Equipment Invoice Value]]+AR37 -> 2.910383e-11 | AA37: =SUM(Y37:Z37) -> 0 | AB37: -72340 | AD37: -1834.16 | AG37: -119525.7 | AH37: -3864.8 | AJ37: -22104 | AP37: =SUM(AB37:AO37) -> -219668.66 | AQ37: =IF(TabProd[[#This Row],[Total Daily]]=0,"",TabProd[[#This Row],[Total]]/TabProd[[#This Row],[Total Daily]])
A38: 46023 | B38: F | D38: 3809 | E38: Inspection Contract - Fixed Team | F38: Constellation | G38: Admarine | H38: 5115 | I38: 46012 | J38: 46022 | K38: -0.16 | L38: =SUM(TabProd[[#This Row],[Personal]:[Engineering]]) -> -0.16 | M38: =IF(TabProd[[#This Row],[Amount Charged]]<>TabProd[[#This Row],[Value]],TabProd[[#This Row],[Amount Charged]]-TabProd[[#This Row],[Value]],"") | N38: 5376 | O38: 46029 | P38: 1616 | Q38: -0.16 | R38: 46038 | S38: =IF(R38="","",R38-J38) -> 16 | W38: =IF(V38="","",V38-J38) | X38: =TabProd[[#This Row],[Value]]-TabProd[[#This Row],[InvoiceTotal Value]]-TabProd[[#This Row],[Rental Equipment Invoice Value]]+AR35 -> 0 | AA38: =SUM(Y38:Z38) -> 0 | AM38: -0.16 | AP38: =SUM(AB38:AO38) -> -0.16 | AQ38: =IF(TabProd[[#This Row],[Total Daily]]=0,"",TabProd[[#This Row],[Total]]/TabProd[[#This Row],[Total Daily]])
A39: 46023 | B39: F | D39: 3500 | E39: Inspection Contract - Variable | F39: Modec | G39: MV-22 | H39: 5016 | I39: 46012 | J39: 46026 | K39: 14957.54 | L39: =SUM(TabProd[[#This Row],[Personal]:[Engineering]]) -> 14957.54 | M39: =IF(TabProd[[#This Row],[Amount Charged]]<>TabProd[[#This Row],[Value]],TabProd[[#This Row],[Amount Charged]]-TabProd[[#This Row],[Value]],"") | N39: 5367 | O39: 46029 | P39: 1590 | Q39: 14957.54 | R39: 46034 | S39: =IF(R39="","",R39-J39) -> 8 | W39: =IF(V39="","",V39-J39) | X39: =TabProd[[#This Row],[Value]]-TabProd[[#This Row],[InvoiceTotal Value]]-TabProd[[#This Row],[Rental Equipment Invoice Value]]+AR38 -> -5.4569682e-12 | Y39: 9 | AA39: =SUM(Y39:Z39) -> 9 | AB39: 15055.3 | AM39: -97.76 | AP39: =SUM(AB39:AO39) -> 14957.54 | AQ39: =IF(TabProd[[#This Row],[Total Daily]]=0,"",TabProd[[#This Row],[Total]]/TabProd[[#This Row],[Total Daily]]) -> 1661.9489
A40: 46023 | B40: F | D40: 3619 | E40: Inspection Contract - Variable | F40: Transocean | G40: Orion | H40: 5243 | I40: 46012 | J40: 46038 | K40: 41135.34 | L40: =SUM(TabProd[[#This Row],[Personal]:[Engineering]]) -> 41135.34 | M40: =IF(TabProd[[#This Row],[Amount Charged]]<>TabProd[[#This Row],[Value]],TabProd[[#This Row],[Amount Charged]]-TabProd[[#This Row],[Value]],"") | N40: 5416 | O40: 46049 | S40: =IF(R40="","",R40-J40) | T40: 1023 | U40: 41135.34 | V40: 46056 | W40: =IF(V40="","",V40-J40) -> 18 | X40: =TabProd[[#This Row],[Value]]-TabProd[[#This Row],[InvoiceTotal Value]]-TabProd[[#This Row],[Rental Equipment Invoice Value]]+AR39 -> 0 | AA40: =SUM(Y40:Z40) -> 0 | AG40: 39134.34 | AH40: 2001 | AP40: =SUM(AB40:AO40) -> 41135.34 | AQ40: =IF(TabProd[[#This Row],[Total Daily]]=0,"",TabProd[[#This Row],[Total]]/TabProd[[#This Row],[Total Daily]])
A41: 46023 | B41: F | D41: 3031 | E41: Maintenance Contract - Variable | F41: Foresea | G41: ODN I | H41: 4120 | I41: 46013 | J41: 46026 | K41: 7011.15 | L41: =SUM(TabProd[[#This Row],[Personal]:[Engineering]]) -> 7011.15 | M41: =IF(TabProd[[#This Row],[Amount Charged]]<>TabProd[[#This Row],[Value]],TabProd[[#This Row],[Amount Charged]]-TabProd[[#This Row],[Value]],"") | N41: 5341 | O41: 46030 | P41: 1577 | Q41: 6741.48 | R41: 46031 | S41: =IF(R41="","",R41-J41) -> 5 | T41: 987 | U41: 269.67 | V41: 46031 | W41: =IF(V41="","",V41-J41) -> 5 | X41: =TabProd[[#This Row],[Value]]-TabProd[[#This Row],[InvoiceTotal Value]]-TabProd[[#This Row],[Rental Equipment Invoice Value]]+AR41 -> 1.1368684e-13 | Y41: 3 | AA41: =SUM(Y41:Z41) -> 3 | AB41: 6741.48 | AG41: 269.67 | AP41: =SUM(AB41:AO41) -> 7011.15 | AQ41: =IF(TabProd[[#This Row],[Total Daily]]=0,"",TabProd[[#This Row],[Total]]/TabProd[[#This Row],[Total Daily]]) -> 2337.05
A42: 46023 | B42: F | D42: 3427 | E42: Maintenance Contract - Variable | F42: Foresea | G42: ODN I | H42: 4892 | I42: 46014 | J42: 46026 | K42: 25048.47 | L42: =SUM(TabProd[[#This Row],[Personal]:[Engineering]]) -> 25048.47 | M42: =IF(TabProd[[#This Row],[Amount Charged]]<>TabProd[[#This Row],[Value]],TabProd[[#This Row],[Amount Charged]]-TabProd[[#This Row],[Value]],"") | N42: 5362 | O42: 46028 | P42: 1586 | Q42: 20374.26 | R42: 46034 | S42: =IF(R42="","",R42-J42) -> 8 | T42: 985 | U42: 4674.21 | V42: 46031 | W42: =IF(V42="","",V42-J42) -> 5 | X42: =TabProd[[#This Row],[Value]]-TabProd[[#This Row],[InvoiceTotal Value]]-TabProd[[#This Row],[Rental Equipment Invoice Value]]+AR42 -> -9.094947e-13 | Y42: 10 | AA42: =SUM(Y42:Z42) -> 10 | AB42: 20374.26 | AG42: 4674.21 | AP42: =SUM(AB42:AO42) -> 25048.47 | AQ42: =IF(TabProd[[#This Row],[Total Daily]]=0,"",TabProd[[#This Row],[Total]]/TabProd[[#This Row],[Total Daily]]) -> 2504.847
D43: 3597 | E43: Inspection Contract - Variable | F43: Constellation | G43: Amaralina Star | I43: 46015 | J43: 46029 | L43: =SUM(TabProd[[#This Row],[Personal]:[Engineering]]) -> 359604.9 | M43: =IF(TabProd[[#This Row],[Amount Charged]]<>TabProd[[#This Row],[Value]],TabProd[[#This Row],[Amount Charged]]-TabProd[[#This Row],[Value]],"") -> -359604.9 | N43: 5429 | S43: =IF(R43="","",R43-J43) | W43: =IF(V43="","",V43-J43) | X43: =TabProd[[#This Row],[Value]]-TabProd[[#This Row],[InvoiceTotal Value]]-TabProd[[#This Row],[Rental Equipment Invoice Value]]+AR41 -> 359604.9 | Z43: 375 | AA43: =SUM(Y43:Z43) -> 375 | AC43: 359604.9 | AP43: =SUM(AB43:AO43) -> 359604.9 | AQ43: =IF(TabProd[[#This Row],[Total Daily]]=0,"",TabProd[[#This Row],[Total]]/TabProd[[#This Row],[Total Daily]]) -> 958.9464
A44: 46023 | B44: F | D44: 3617 | E44: Maintenance Contract - Variable | F44: Transocean | G44: Corcovado | H44: 5165 | I44: 46016 | J44: 46038 | K44: 59523.54 | L44: =SUM(TabProd[[#This Row],[Personal]:[Engineering]]) -> 59523.54 | M44: =IF(TabProd[[#This Row],[Amount Charged]]<>TabProd[[#This Row],[Value]],TabProd[[#This Row],[Amount Charged]]-TabProd[[#This Row],[Value]],"") | N44: 5415 | O44: 46049 | S44: =IF(R44="","",R44-J44) | T44: 1056 | U44: 59523.54 | V44: 46066 | W44: =IF(V44="","",V44-J44) -> 28 | X44: =TabProd[[#This Row],[Value]]-TabProd[[#This Row],[InvoiceTotal Value]]-TabProd[[#This Row],[Rental Equipment Invoice Value]]+AR42 -> 0 | AA44: =SUM(Y44:Z44) -> 0 | AG44: 55682.54 | AH44: 3841 | AP44: =SUM(AB44:AO44) -> 59523.54 | AQ44: =IF(TabProd[[#This Row],[Total Daily]]=0,"",TabProd[[#This Row],[Total]]/TabProd[[#This Row],[Total Daily]])
A45: 46023 | D45: 3380 | E45: Inspection Contract - Variable | F45: Modec | G45: MV-20 | H45: 4784 | I45: 46017 | J45: 46024 | K45: 5360 | L45: =SUM(TabProd[[#This Row],[Personal]:[Engineering]]) -> 5360 | M45: =IF(TabProd[[#This Row],[Amount Charged]]<>TabProd[[#This Row],[Value]],TabProd[[#This Row],[Amount Charged]]-TabProd[[#This Row],[Value]],"") | N45: 5288 | S45: =IF(R45="","",R45-J45) | W45: =IF(V45="","",V45-J45) | X45: =TabProd[[#This Row],[Value]]-TabProd[[#This Row],[InvoiceTotal Value]]-TabProd[[#This Row],[Rental Equipment Invoice Value]]+AR45 -> 5360 | Y45: 3 | AA45: =SUM(Y45:Z45) -> 3 | AB45: 5360 | AP45: =SUM(AB45:AO45) -> 5360 | AQ45: =IF(TabProd[[#This Row],[Total Daily]]=0,"",TabProd[[#This Row],[Total]]/TabProd[[#This Row],[Total Daily]]) -> 1786.6667
A46: 46023 | B46: F | D46: 3415 | E46: Inspection Contract - Variable | F46: Modec | G46: FPSO Bacalhau | H46: 4874 | I46: 46017 | J46: 46032 | K46: 36361.68 | L46: =SUM(TabProd[[#This Row],[Personal]:[Engineering]]) -> 36361.68 | M46: =IF(TabProd[[#This Row],[Amount Charged]]<>TabProd[[#This Row],[Value]],TabProd[[#This Row],[Amount Charged]]-TabProd[[#This Row],[Value]],"") | N46: 5365 | O46: 46035 | P46: 1654 | Q46: 36361.68 | R46: 46045 | S46: =IF(R46="","",R46-J46) -> 13 | W46: =IF(V46="","",V46-J46) | X46: =TabProd[[#This Row],[Value]]-TabProd[[#This Row],[InvoiceTotal Value]]-TabProd[[#This Row],[Rental Equipment Invoice Value]]+AR46 -> 0 | Y46: 26 | AA46: =SUM(Y46:Z46) -> 26 | AB46: 36361.68 | AP46: =SUM(AB46:AO46) -> 36361.68 | AQ46: =IF(TabProd[[#This Row],[Total Daily]]=0,"",TabProd[[#This Row],[Total]]/TabProd[[#This Row],[Total Daily]]) -> 1398.5262
A47: 46023 | B47: F | D47: 3289 | E47: Inspection Contract - Fixed Team | F47: Constellation | G47: Laguna Star | H47: 3380 | I47: 46018 | J47: 46032 | K47: 56012.41 | L47: =SUM(TabProd[[#This Row],[Personal]:[Engineering]]) -> 56012.41 | M47: =IF(TabProd[[#This Row],[Amount Charged]]<>TabProd[[#This Row],[Value]],TabProd[[#This Row],[Amount Charged]]-TabProd[[#This Row],[Value]],"") | N47: 5373 | O47: 46035 | P47: 1617 | Q47: 56012.41 | R47: 46041 | S47: =IF(R47="","",R47-J47) -> 9 | W47: =IF(V47="","",V47-J47) | X47: =TabProd[[#This Row],[Value]]-TabProd[[#This Row],[InvoiceTotal Value]]-TabProd[[#This Row],[Rental Equipment Invoice Value]]+AR47 -> 0 | Y47: 27 | AA47: =SUM(Y47:Z47) -> 27 | AB47: 54179.47 | AD47: 1832.94 | AP47: =SUM(AB47:AO47) -> 56012.41 | AQ47: =IF(TabProd[[#This Row],[Total Daily]]=0,"",TabProd[[#This Row],[Total]]/TabProd[[#This Row],[Total Daily]]) -> 2074.5337
A48: 46023 | B48: F | D48: 3292 | E48: Inspection Contract - Fixed Team | F48: Helix | G48: SH1 | H48: 3970 | I48: 46018 | J48: 46032 | K48: 58088.25 | L48: =SUM(TabProd[[#This Row],[Personal]:[Engineering]]) -> 58088.25 | M48: =IF(TabProd[[#This Row],[Amount Charged]]<>TabProd[[#This Row],[Value]],TabProd[[#This Row],[Amount Charged]]-TabProd[[#This Row],[Value]],"") | N48: 5374 | O48: 46035 | P48: 1597 | Q48: 34852.95 | R48: 46037 | S48: =IF(R48="","",R48-J48) -> 5 | T48: 997 | U48: 23235.3 | V48: 46037 | W48: =IF(V48="","",V48-J48) -> 5 | X48: =TabProd[[#This Row],[Value]]-TabProd[[#This Row],[InvoiceTotal Value]]-TabProd[[#This Row],[Rental Equipment Invoice Value]]+AR48 -> 0 | Y48: 27 | AA48: =SUM(Y48:Z48) -> 27 | AB48: 34852.95 | AG48: 23235.3 | AP48: =SUM(AB48:AO48) -> 58088.25 | AQ48: =IF(TabProd[[#This Row],[Total Daily]]=0,"",TabProd[[#This Row],[Total]]/TabProd[[#This Row],[Total Daily]]) -> 2151.4167
A49: 46023 | B49: F | D49: 3810 | E49: Inspection Contract - Fixed Team | F49: Etesco | G49: Takatsugu J | H49: 3701 | I49: 46019 | J49: 46033 | K49: 68915.44 | L49: =SUM(TabProd[[#This Row],[Personal]:[Engineering]]) -> 68915.44 | M49: =IF(TabProd[[#This Row],[Amount Charged]]<>TabProd[[#This Row],[Value]],TabProd[[#This Row],[Amount Charged]]-TabProd[[#This Row],[Value]],"") | N49: 5358 | O49: 46035 | P49: 1598 | Q49: 41349.26 | R49: 46037 | S49: =IF(R49="","",R49-J49) -> 4 | T49: 998 | U49: 27566.18 | V49: 46037 | W49: =IF(V49="","",V49-J49) -> 4 | X49: =TabProd[[#This Row],[Value]]-TabProd[[#This Row],[InvoiceTotal Value]]-TabProd[[#This Row],[Rental Equipment Invoice Value]]+AR48 -> 0 | Y49: 33 | AA49: =SUM(Y49:Z49) -> 33 | AB49: 41349.26 | AG49: 27566.18 | AP49: =SUM(AB49:AO49) -> 68915.44 | AQ49: =IF(TabProd[[#This Row],[Total Daily]]=0,"",TabProd[[#This Row],[Total]]/TabProd[[#This Row],[Total Daily]]) -> 2088.3467
A50: 46023 | B50: F | D50: 3293 | E50: Inspection Contract - Fixed Team | F50: Helix | G50: SH2 | H50: 3970 | I50: 46019 | J50: 46033 | K50: 64542.5 | L50: =SUM(TabProd[[#This Row],[Personal]:[Engineering]]) -> 64542.5 | M50: =IF(TabProd[[#This Row],[Amount Charged]]<>TabProd[[#This Row],[Value]],TabProd[[#This Row],[Amount Charged]]-TabProd[[#This Row],[Value]],"") | N50: 5375 | O50: 46035 | P50: 1640 | Q50: 38725.5 | R50: 46043 | S50: =IF(R50="","",R50-J50) -> 10 | T50: 1014 | U50: 25817 | V50: 46043 | W50: =IF(V50="","",V50-J50) -> 10 | X50: =TabProd[[#This Row],[Value]]-TabProd[[#This Row],[InvoiceTotal Value]]-TabProd[[#This Row],[Rental Equipment Invoice Value]]+AR50 -> -3.6379788e-12 | Y50: 30 | AA50: =SUM(Y50:Z50) -> 30 | AB50: 38725.5 | AG50: 25817 | AP50: =SUM(AB50:AO50) -> 64542.5 | AQ50: =IF(TabProd[[#This Row],[Total Daily]]=0,"",TabProd[[#This Row],[Total]]/TabProd[[#This Row],[Total Daily]]) -> 2151.4167
A51: 46023 | B51: F | D51: 3561 | E51: Inspection Spot | F51: Modec | G51: MV-33 | H51: 5121 | I51: 46020 | J51: 46034 | K51: 44118.96 | L51: =SUM(TabProd[[#This Row],[Personal]:[Engineering]]) -> 44118.96 | M51: =IF(TabProd[[#This Row],[Amount Charged]]<>TabProd[[#This Row],[Value]],TabProd[[#This Row],[Amount Charged]]-TabProd[[#This Row],[Value]],"") | N51: 5368 | O51: 46035 | P51: 1625 | Q51: 44118.96 | R51: 46041 | S51: =IF(R51="","",R51-J51) -> 7 | W51: =IF(V51="","",V51-J51) | X51: =TabProd[[#This Row],[Value]]-TabProd[[#This Row],[InvoiceTotal Value]]-TabProd[[#This Row],[Rental Equipment Invoice Value]]+AR50 -> 0 | Y51: 39 | AA51: =SUM(Y51:Z51) -> 39 | AB51: 44305.76 | AM51: -186.8 | AP51: =SUM(AB51:AO51) -> 44118.96 | AQ51: =IF(TabProd[[#This Row],[Total Daily]]=0,"",TabProd[[#This Row],[Total]]/TabProd[[#This Row],[Total Daily]]) -> 1131.2554
A52: 46023 | B52: F | D52: 3487 | E52: Inspection Contract - Variable | F52: Transocean | G52: Aquila | H52: 4964 | I52: 46023 | J52: 46053 | K52: 182282.24 | L52: =SUM(TabProd[[#This Row],[Personal]:[Engineering]]) -> 182282.24 | M52: =IF(TabProd[[#This Row],[Amount Charged]]<>TabProd[[#This Row],[Value]],TabProd[[#This Row],[Amount Charged]]-TabProd[[#This Row],[Value]],"") | N52: 5405 | O52: 46056 | P52: 1713 | Q52: 160022.43 | R52: 46066 | S52: =IF(R52="","",R52-J52) -> 13 | T52: 1052 | U52: 22259.81 | V52: 46066 | W52: =IF(V52="","",V52-J52) -> 13 | X52: =TabProd[[#This Row],[Value]]-TabProd[[#This Row],[InvoiceTotal Value]]-TabProd[[#This Row],[Rental Equipment Invoice Value]]+AR51 -> 2.5465852e-11 | Y52: 51 | AA52: =SUM(Y52:Z52) -> 51 | AB52: 115834.44 | AD52: 11187.99 | AG52: 22259.81 | AO52: 33000 | AP52: =SUM(AB52:AO52) -> 182282.24 | AQ52: =IF(TabProd[[#This Row],[Total Daily]]=0,"",TabProd[[#This Row],[Total]]/TabProd[[#This Row],[Total Daily]]) -> 3574.1616
A53: 46023 | B53: F | D53: 3359 | E53: Inspection Spot | F53: Seadrill | G53: West Jupiter | H53: 4730 | I53: 46023 | J53: 46053 | K53: 203709.75 | L53: =SUM(TabProd[[#This Row],[Personal]:[Engineering]]) -> 203709.75 | M53: =IF(TabProd[[#This Row],[Amount Charged]]<>TabProd[[#This Row],[Value]],TabProd[[#This Row],[Amount Charged]]-TabProd[[#This Row],[Value]],"") | N53: 5378 | O53: 46055 | P53: 25 | Q53: 153496 | R53: 46099 | S53: =IF(R53="","",R53-J53) -> 46 | T53: 2561 | U53: 50213.75 | V53: 46104 | W53: =IF(V53="","",V53-J53) -> 51 | X53: =TabProd[[#This Row],[Value]]-TabProd[[#This Row],[InvoiceTotal Value]]-TabProd[[#This Row],[Rental Equipment Invoice Value]]+AR53 -> 0 | Y53: 63 | AA53: =SUM(Y53:Z53) -> 63 | AB53: 144856 | AD53: 8640 | AG53: 46920 | AH53: 3293.75 | AP53: =SUM(AB53:AO53) -> 203709.75 | AQ53: =IF(TabProd[[#This Row],[Total Daily]]=0,"",TabProd[[#This Row],[Total]]/TabProd[[#This Row],[Total Daily]]) -> 3233.4881
A54: 46023 | B54: F | D54: 3324 | E54: Inspection Spot | F54: Seadrill | G54: West Carina | H54: 4662 | I54: 46023 | J54: 46053 | K54: 547877 | L54: =SUM(TabProd[[#This Row],[Personal]:[Engineering]]) -> 547877 | M54: =IF(TabProd[[#This Row],[Amount Charged]]<>TabProd[[#This Row],[Value]],TabProd[[#This Row],[Amount Charged]]-TabProd[[#This Row],[Value]],"") | N54: 5379 | O54: 46055 | P54: 15 | Q54: 496309.62 | R54: 46066 | S54: =IF(R54="","",R54-J54) -> 13 | T54: 2554 | U54: 51567.38 | V54: 46072 | W54: =IF(V54="","",V54-J54) -> 19 | X54: =TabProd[[#This Row],[Value]]-TabProd[[#This Row],[InvoiceTotal Value]]-TabProd[[#This Row],[Rental Equipment Invoice Value]]+AR54 -> 7.2759576e-12 | Y54: 186 | Z54: 3 | AA54: =SUM(Y54:Z54) -> 189 | AB54: 476500 | AC54: 3812 | AD54: 14400 | AE54: 1597.62 | AG54: 50840 | AH54: 727.38 | AP54: =SUM(AB54:AO54) -> 547877 | AQ54: =IF(TabProd[[#This Row],[Total Daily]]=0,"",TabProd[[#This Row],[Total]]/TabProd[[#This Row],[Total Daily]]) -> 2898.8201
A55: 46023 | B55: F | D55: 3341 | E55: Inspection Spot | F55: Seadrill | G55: West Tellus | H55: 4693 | I55: 46023 | J55: 46053 | K55: 274828 | L55: =SUM(TabProd[[#This Row],[Personal]:[Engineering]]) -> 274828 | M55: =IF(TabProd[[#This Row],[Amount Charged]]<>TabProd[[#This Row],[Value]],TabProd[[#This Row],[Amount Charged]]-TabProd[[#This Row],[Value]],"") | N55: 5380 | O55: 46055 | P55: 1885 | Q55: 211588 | R55: 46129 | S55: =IF(R55="","",R55-J55) -> 76 | T55: 1163 | U55: 63240 | V55: 46129 | W55: =IF(V55="","",V55-J55) -> 76 | X55: =TabProd[[#This Row],[Value]]-TabProd[[#This Row],[InvoiceTotal Value]]-TabProd[[#This Row],[Rental Equipment Invoice Value]]+AR55 -> 0 | Y55: 81 | AA55: =SUM(Y55:Z55) -> 81 | AB55: 205828 | AD55: 5760 | AG55: 63240 | AP55: =SUM(AB55:AO55) -> 274828 | AQ55: =IF(TabProd[[#This Row],[Total Daily]]=0,"",TabProd[[#This Row],[Total]]/TabProd[[#This Row],[Total Daily]]) -> 3392.9383
A56: 46023 | B56: F | D56: 3572 | E56: Maintenance Spot | F56: PRIO | G56: PGA (Peregrino Alfa) | H56: 5145 | I56: 46023 | J56: 46053 | K56: 909860.49 | L56: =SUM(TabProd[[#This Row],[Personal]:[Engineering]]) -> 909860.49 | M56: =IF(TabProd[[#This Row],[Amount Charged]]<>TabProd[[#This Row],[Value]],TabProd[[#This Row],[Amount Charged]]-TabProd[[#This Row],[Value]],"") | N56: 5393 | O56: 46077 | P56: 1820 | Q56: 909860.49 | R56: 46101 | S56: =IF(R56="","",R56-J56) -> 48 | W56: =IF(V56="","",V56-J56) | X56: =TabProd[[#This Row],[Value]]-TabProd[[#This Row],[InvoiceTotal Value]]-TabProd[[#This Row],[Rental Equipment Invoice Value]]+AR55 -> 0 | Y56: 202 | AA56: =SUM(Y56:Z56) -> 202 | AB56: 500736.8 | AD56: 15590.36 | AG56: 377944.87 | AH56: 15588.46 | AP56: =SUM(AB56:AO56) -> 909860.49 | AQ56: =IF(TabProd[[#This Row],[Total Daily]]=0,"",TabProd[[#This Row],[Total]]/TabProd[[#This Row],[Total Daily]]) -> 4504.2599
A57: 46082 | B57: F | D57: 3572 | E57: Maintenance Spot | F57: PRIO | G57: PGA (Peregrino Alfa) | H57: 5145 | I57: 46023 | J57: 46053 | K57: 236027.95 | L57: =SUM(TabProd[[#This Row],[Personal]:[Engineering]]) -> 236027.95 | M57: =IF(TabProd[[#This Row],[Amount Charged]]<>TabProd[[#This Row],[Value]],TabProd[[#This Row],[Amount Charged]]-TabProd[[#This Row],[Value]],"") | N57: 5393 | O57: 46077 | P57: 1820 | Q57: 236027.95 | R57: 46101 | S57: =IF(R57="","",R57-J57) -> 48 | W57: =IF(V57="","",V57-J57) | X57: =TabProd[[#This Row],[Value]]-TabProd[[#This Row],[InvoiceTotal Value]]-TabProd[[#This Row],[Rental Equipment Invoice Value]]+AR57 -> 0 | Y57: -5 | AA57: =SUM(Y57:Z57) -> -5 | AB57: 186513.89 | AD57: 4126.86 | AJ57: 44208 | AL57: 1179.2 | AP57: =SUM(AB57:AO57) -> 236027.95 | AQ57: =IF(TabProd[[#This Row],[Total Daily]]=0,"",TabProd[[#This Row],[Total]]/TabProd[[#This Row],[Total Daily]]) -> -47205.59
A58: 46023 | B58: F | D58: 3437 | E58: Engineering | F58: Ventura | G58: Victoria | H58: 4751 | I58: 46023 | J58: 46053 | K58: 39520 | L58: =SUM(TabProd[[#This Row],[Personal]:[Engineering]]) -> 39520 | M58: =IF(TabProd[[#This Row],[Amount Charged]]<>TabProd[[#This Row],[Value]],TabProd[[#This Row],[Amount Charged]]-TabProd[[#This Row],[Value]],"") | N58: 5398 | O58: 46056 | P58: 1679 | Q58: 39520 | R58: 46058 | S58: =IF(R58="","",R58-J58) -> 5 | W58: =IF(V58="","",V58-J58) | X58: =TabProd[[#This Row],[Value]]-TabProd[[#This Row],[InvoiceTotal Value]]-TabProd[[#This Row],[Rental Equipment Invoice Value]]+AR58 -> 0 | AA58: =SUM(Y58:Z58) -> 0 | AO58: 39520 | AP58: =SUM(AB58:AO58) -> 39520 | AQ58: =IF(TabProd[[#This Row],[Total Daily]]=0,"",TabProd[[#This Row],[Total]]/TabProd[[#This Row],[Total Daily]])
A59: 46023 | B59: F | D59: 3436 | E59: Engineering | F59: Ventura | G59: DS Carolina | H59: 4750 | I59: 46023 | J59: 46053 | K59: 39520 | L59: =SUM(TabProd[[#This Row],[Personal]:[Engineering]]) -> 39520 | M59: =IF(TabProd[[#This Row],[Amount Charged]]<>TabProd[[#This Row],[Value]],TabProd[[#This Row],[Amount Charged]]-TabProd[[#This Row],[Value]],"") | N59: 5399 | O59: 46056 | P59: 1687 | Q59: 39520 | R59: 46059 | S59: =IF(R59="","",R59-J59) -> 6 | W59: =IF(V59="","",V59-J59) | X59: =TabProd[[#This Row],[Value]]-TabProd[[#This Row],[InvoiceTotal Value]]-TabProd[[#This Row],[Rental Equipment Invoice Value]]+AR59 -> 0 | AA59: =SUM(Y59:Z59) -> 0 | AO59: 39520 | AP59: =SUM(AB59:AO59) -> 39520 | AQ59: =IF(TabProd[[#This Row],[Total Daily]]=0,"",TabProd[[#This Row],[Total]]/TabProd[[#This Row],[Total Daily]])
A60: 46023 | B60: F | D60: 3543 | E60: Engineering | F60: Helix | G60: SH1 | H60: 5109 | I60: 46023 | J60: 46053 | K60: 22800 | L60: =SUM(TabProd[[#This Row],[Personal]:[Engineering]]) -> 22800 | M60: =IF(TabProd[[#This Row],[Amount Charged]]<>TabProd[[#This Row],[Value]],TabProd[[#This Row],[Amount Charged]]-TabProd[[#This Row],[Value]],"") | N60: 5400 | O60: 46064 | P60: 1731 | Q60: 22800 | R60: 46073 | S60: =IF(R60="","",R60-J60) -> 20 | W60: =IF(V60="","",V60-J60) | X60: =TabProd[[#This Row],[Value]]-TabProd[[#This Row],[InvoiceTotal Value]]-TabProd[[#This Row],[Rental Equipment Invoice Value]]+AR58 -> 0 | AA60: =SUM(Y60:Z60) -> 0 | AO60: 22800 | AP60: =SUM(AB60:AO60) -> 22800 | AQ60: =IF(TabProd[[#This Row],[Total Daily]]=0,"",TabProd[[#This Row],[Total]]/TabProd[[#This Row],[Total Daily]])
A61: 46023 | B61: F | D61: 3445 | E61: Engineering | F61: Helix | G61: SH2 | H61: 4912 | I61: 46023 | J61: 46052 | K61: 22800 | L61: =SUM(TabProd[[#This Row],[Personal]:[Engineering]]) -> 22800 | M61: =IF(TabProd[[#This Row],[Amount Charged]]<>TabProd[[#This Row],[Value]],TabProd[[#This Row],[Amount Charged]]-TabProd[[#This Row],[Value]],"") | N61: 5401 | O61: 46057 | P61: 1726 | Q61: 22800 | R61: 46072 | S61: =IF(R61="","",R61-J61) -> 20 | W61: =IF(V61="","",V61-J61) | X61: =TabProd[[#This Row],[Value]]-TabProd[[#This Row],[InvoiceTotal Value]]-TabProd[[#This Row],[Rental Equipment Invoice Value]]+AR61 -> 0 | AA61: =SUM(Y61:Z61) -> 0 | AO61: 22800 | AP61: =SUM(AB61:AO61) -> 22800 | AQ61: =IF(TabProd[[#This Row],[Total Daily]]=0,"",TabProd[[#This Row],[Total]]/TabProd[[#This Row],[Total Daily]])
A62: 46023 | B62: F | D62: 3577 | E62: Engineering | F62: Constellation | G62: Base Cliente | H62: 5080 | I62: 46023 | J62: 46053 | K62: 38220 | L62: =SUM(TabProd[[#This Row],[Personal]:[Engineering]]) -> 38220 | M62: =IF(TabProd[[#This Row],[Amount Charged]]<>TabProd[[#This Row],[Value]],TabProd[[#This Row],[Amount Charged]]-TabProd[[#This Row],[Value]],"") | N62: 5402 | O62: 46055 | P62: 1722 | Q62: 38220 | R62: 46066 | S62: =IF(R62="","",R62-J62) -> 13 | W62: =IF(V62="","",V62-J62) | X62: =TabProd[[#This Row],[Value]]-TabProd[[#This Row],[InvoiceTotal Value]]-TabProd[[#This Row],[Rental Equipment Invoice Value]]+AR60 -> 0 | AA62: =SUM(Y62:Z62) -> 0 | AB62: 38220 | AP62: =SUM(AB62:AO62) -> 38220 | AQ62: =IF(TabProd[[#This Row],[Total Daily]]=0,"",TabProd[[#This Row],[Total]]/TabProd[[#This Row],[Total Daily]])
A63: 46023 | B63: F | D63: 3800 | E63: Inspection Contract - Fixed Team | F63: Transocean | G63: Corcovado | H63: 1877 | I63: 46023 | J63: 46053 | K63: 196340.46 | L63: =SUM(TabProd[[#This Row],[Personal]:[Engineering]]) -> 196340.46 | M63: =IF(TabProd[[#This Row],[Amount Charged]]<>TabProd[[#This Row],[Value]],TabProd[[#This Row],[Amount Charged]]-TabProd[[#This Row],[Value]],"") | N63: 5409 | O63: 46056 | P63: 1675 | Q63: 172448.95 | R63: 46057 | S63: =IF(R63="","",R63-J63) -> 4 | T63: 1029 | U63: 23891.51 | V63: 46057 | W63: =IF(V63="","",V63-J63) -> 4 | X63: =TabProd[[#This Row],[Value]]-TabProd[[#This Row],[InvoiceTotal Value]]-TabProd[[#This Row],[Rental Equipment Invoice Value]]+AR62 -> 1.0913936e-11 | Y63: 90 | AA63: =SUM(Y63:Z63) -> 90 | AB63: 172448.95 | AG63: 23891.51 | AP63: =SUM(AB63:AO63) -> 196340.46 | AQ63: =IF(TabProd[[#This Row],[Total Daily]]=0,"",TabProd[[#This Row],[Total]]/TabProd[[#This Row],[Total Daily]]) -> 2181.5607
A64: 46023 | B64: F | D64: 3801 | E64: Inspection Contract - Fixed Team | F64: Transocean | G64: Mykonos | H64: 1877 | I64: 46023 | J64: 46053 | K64: 196340.46 | L64: =SUM(TabProd[[#This Row],[Personal]:[Engineering]]) -> 196340.46 | M64: =IF(TabProd[[#This Row],[Amount Charged]]<>TabProd[[#This Row],[Value]],TabProd[[#This Row],[Amount Charged]]-TabProd[[#This Row],[Value]],"") | N64: 5410 | O64: 46055 | P64: 1696 | Q64: 172448.95 | R64: 46065 | S64: =IF(R64="","",R64-J64) -> 12 | T64: 1042 | U64: 23891.51 | V64: 46065 | W64: =IF(V64="","",V64-J64) -> 12 | X64: =TabProd[[#This Row],[Value]]-TabProd[[#This Row],[InvoiceTotal Value]]-TabProd[[#This Row],[Rental Equipment Invoice Value]]+AR63 -> 1.0913936e-11 | Y64: 91 | AA64: =SUM(Y64:Z64) -> 91 | AB64: 172448.95 | AG64: 23891.51 | AP64: =SUM(AB64:AO64) -> 196340.46 | AQ64: =IF(TabProd[[#This Row],[Total Daily]]=0,"",TabProd[[#This Row],[Total]]/TabProd[[#This Row],[Total Daily]]) -> 2157.5875
A65: 46023 | B65: F | D65: 3802 | E65: Inspection Contract - Fixed Team | F65: Transocean | G65: PBS | H65: 1877 | I65: 46023 | J65: 46053 | K65: 200590.87 | L65: =SUM(TabProd[[#This Row],[Personal]:[Engineering]]) -> 200590.87 | M65: =IF(TabProd[[#This Row],[Amount Charged]]<>TabProd[[#This Row],[Value]],TabProd[[#This Row],[Amount Charged]]-TabProd[[#This Row],[Value]],"") | N65: 5411 | O65: 46056 | P65: 1676 | Q65: 176699.36 | R65: 46057 | S65: =IF(R65="","",R65-J65) -> 4 | T65: 1031 | U65: 23891.51 | V65: 46057 | W65: =IF(V65="","",V65-J65) -> 4 | X65: =TabProd[[#This Row],[Value]]-TabProd[[#This Row],[InvoiceTotal Value]]-TabProd[[#This Row],[Rental Equipment Invoice Value]]+AR64 -> 4.0017767e-11 | Y65: 87 | AA65: =SUM(Y65:Z65) -> 87 | AB65: 172448.95 | AG65: 23891.51 | AL65: 4250.41 | AP65: =SUM(AB65:AO65) -> 200590.87 | AQ65: =IF(TabProd[[#This Row],[Total Daily]]=0,"",TabProd[[#This Row],[Total]]/TabProd[[#This Row],[Total Daily]]) -> 2305.6422
A66: 46023 | B66: F | D66: 3803 | E66: Inspection Contract - Fixed Team | F66: Transocean | G66: KG2 | H66: 1877 | I66: 46023 | J66: 46053 | K66: 196340.46 | L66: =SUM(TabProd[[#This Row],[Personal]:[Engineering]]) -> 196340.46 | M66: =IF(TabProd[[#This Row],[Amount Charged]]<>TabProd[[#This Row],[Value]],TabProd[[#This Row],[Amount Charged]]-TabProd[[#This Row],[Value]],"") | N66: 5412 | O66: 46056 | P66: 1664 | Q66: 172448.95 | R66: 46056 | S66: =IF(R66="","",R66-J66) -> 3 | T66: 1025 | U66: 23891.51 | V66: 46056 | W66: =IF(V66="","",V66-J66) -> 3 | X66: =TabProd[[#This Row],[Value]]-TabProd[[#This Row],[InvoiceTotal Value]]-TabProd[[#This Row],[Rental Equipment Invoice Value]]+AR65 -> 1.0913936e-11 | Y66: 78 | AA66: =SUM(Y66:Z66) -> 78 | AB66: 172448.95 | AG66: 23891.51 | AP66: =SUM(AB66:AO66) -> 196340.46 | AQ66: =IF(TabProd[[#This Row],[Total Daily]]=0,"",TabProd[[#This Row],[Total]]/TabProd[[#This Row],[Total Daily]]) -> 2517.1854
A67: 46023 | B67: F | D67: 3804 | E67: Inspection Contract - Fixed Team | F67: Transocean | G67: Orion | H67: 1877 | I67: 46023 | J67: 46053 | K67: 196340.46 | L67: =SUM(TabProd[[#This Row],[Personal]:[Engineering]]) -> 196340.46 | M67: =IF(TabProd[[#This Row],[Amount Charged]]<>TabProd[[#This Row],[Value]],TabProd[[#This Row],[Amount Charged]]-TabProd[[#This Row],[Value]],"") | N67: 5413 | O67: 46055 | P67: 1663 | Q67: 172448.95 | R67: 46056 | S67: =IF(R67="","",R67-J67) -> 3 | T67: 1023 | U67: 23891.51 | V67: 46056 | W67: =IF(V67="","",V67-J67) -> 3 | X67: =TabProd[[#This Row],[Value]]-TabProd[[#This Row],[InvoiceTotal Value]]-TabProd[[#This Row],[Rental Equipment Invoice Value]]+AR66 -> 1.0913936e-11 | Y67: 93 | AA67: =SUM(Y67:Z67) -> 93 | AB67: 172448.95 | AG67: 23891.51 | AP67: =SUM(AB67:AO67) -> 196340.46 | AQ67: =IF(TabProd[[#This Row],[Total Daily]]=0,"",TabProd[[#This Row],[Total]]/TabProd[[#This Row],[Total Daily]]) -> 2111.1877
A68: 46023 | B68: F | D68: 3805 | E68: Inspection Contract - Fixed Team | F68: Transocean | G68: Aquila | H68: 4191 | I68: 46023 | J68: 46053 | K68: 196340.46 | L68: =SUM(TabProd[[#This Row],[Personal]:[Engineering]]) -> 196340.46 | M68: =IF(TabProd[[#This Row],[Amount Charged]]<>TabProd[[#This Row],[Value]],TabProd[[#This Row],[Amount Charged]]-TabProd[[#This Row],[Value]],"") | N68: 5414 | O68: 46056 | P68: 1677 | Q68: 172448.95 | R68: 46058 | S68: =IF(R68="","",R68-J68) -> 5 | T68: 1032 | U68: 23891.51 | V68: 46058 | W68: =IF(V68="","",V68-J68) -> 5 | X68: =TabProd[[#This Row],[Value]]-TabProd[[#This Row],[InvoiceTotal Value]]-TabProd[[#This Row],[Rental Equipment Invoice Value]]+AR67 -> 1.0913936e-11 | Y68: 93 | AA68: =SUM(Y68:Z68) -> 93 | AB68: 172448.95 | AG68: 23891.51 | AP68: =SUM(AB68:AO68) -> 196340.46 | AQ68: =IF(TabProd[[#This Row],[Total Daily]]=0,"",TabProd[[#This Row],[Total]]/TabProd[[#This Row],[Total Daily]]) -> 2111.1877
A69: 46023 | B69: F | D69: 3807 | E69: Inspection Contract - Fixed Team | F69: Constellation | G69: Amaralina Star | H69: 3380 | I69: 46023 | J69: 46053 | K69: 160184.99 | L69: =SUM(TabProd[[#This Row],[Personal]:[Engineering]]) -> 160184.99 | M69: =IF(TabProd[[#This Row],[Amount Charged]]<>TabProd[[#This Row],[Value]],TabProd[[#This Row],[Amount Charged]]-TabProd[[#This Row],[Value]],"") | N69: 5439 | O69: 46055 | P69: 1666 | Q69: 160184.99 | R69: 46056 | S69: =IF(R69="","",R69-J69) -> 3 | W69: =IF(V69="","",V69-J69) | X69: =TabProd[[#This Row],[Value]]-TabProd[[#This Row],[InvoiceTotal Value]]-TabProd[[#This Row],[Rental Equipment Invoice Value]]+AR67 -> 0 | Y69: 85 | AA69: =SUM(Y69:Z69) -> 85 | AB69: 156439.19 | AD69: 2485.8 | AH69: 1260 | AP69: =SUM(AB69:AO69) -> 160184.99 | AQ69: =IF(TabProd[[#This Row],[Total Daily]]=0,"",TabProd[[#This Row],[Total]]/TabProd[[#This Row],[Total Daily]]) -> 1884.5293
A70: 46023 | B70: F | D70: 3809 | E70: Inspection Contract - Fixed Team | F70: Constellation | G70: Admarine | H70: 5115 | I70: 46023 | J70: 46053 | K70: 187766.25 | L70: =SUM(TabProd[[#This Row],[Personal]:[Engineering]]) -> 187766.25 | M70: =IF(TabProd[[#This Row],[Amount Charged]]<>TabProd[[#This Row],[Value]],TabProd[[#This Row],[Amount Charged]]-TabProd[[#This Row],[Value]],"") | N70: 5442 | O70: 46055 | P70: 1697 | Q70: 187766.25 | R70: 46065 | S70: =IF(R70="","",R70-J70) -> 12 | W70: =IF(V70="","",V70-J70) | X70: =TabProd[[#This Row],[Value]]-TabProd[[#This Row],[InvoiceTotal Value]]-TabProd[[#This Row],[Rental Equipment Invoice Value]]+AR69 -> 0 | Y70: 93 | AA70: =SUM(Y70:Z70) -> 93 | AB70: 156394.35 | AD70: 31371.9 | AP70: =SUM(AB70:AO70) -> 187766.25 | AQ70: =IF(TabProd[[#This Row],[Total Daily]]=0,"",TabProd[[#This Row],[Total]]/TabProd[[#This Row],[Total Daily]]) -> 2018.9919
A71: 46023 | B71: F | D71: 3813 | E71: Inspection Contract - Fixed Team | F71: Foresea | G71: ODN I | H71: 2016 | I71: 46023 | J71: 46053 | K71: 173780.72 | L71: =SUM(TabProd[[#This Row],[Personal]:[Engineering]]) -> 173780.72 | M71: =IF(TabProd[[#This Row],[Amount Charged]]<>TabProd[[#This Row],[Value]],TabProd[[#This Row],[Amount Charged]]-TabProd[[#This Row],[Value]],"") | N71: 5446 | O71: 46055 | P71: 1674 | Q71: 173780.72 | R71: 46057 | S71: =IF(R71="","",R71-J71) -> 4 | W71: =IF(V71="","",V71-J71) | X71: =TabProd[[#This Row],[Value]]-TabProd[[#This Row],[InvoiceTotal Value]]-TabProd[[#This Row],[Rental Equipment Invoice Value]]+AR70 -> 0 | Y71: 92 | AA71: =SUM(Y71:Z71) -> 92 | AB71: 173780.72 | AP71: =SUM(AB71:AO71) -> 173780.72 | AQ71: =IF(TabProd[[#This Row],[Total Daily]]=0,"",TabProd[[#This Row],[Total]]/TabProd[[#This Row],[Total Daily]]) -> 1888.9209
A72: 46023 | B72: F | D72: 3814 | E72: Inspection Contract - Fixed Team | F72: Ventura | G72: Victoria | H72: 3610 | I72: 46023 | J72: 46053 | K72: 162420 | L72: =SUM(TabProd[[#This Row],[Personal]:[Engineering]]) -> 162420 | M72: =IF(TabProd[[#This Row],[Amount Charged]]<>TabProd[[#This Row],[Value]],TabProd[[#This Row],[Amount Charged]]-TabProd[[#This Row],[Value]],"") | N72: 5451 | O72: 46057 | P72: 1680 | Q72: 162420 | R72: 46058 | S72: =IF(R72="","",R72-J72) -> 5 | W72: =IF(V72="","",V72-J72) | X72: =TabProd[[#This Row],[Value]]-TabProd[[#This Row],[InvoiceTotal Value]]-TabProd[[#This Row],[Rental Equipment Invoice Value]]+AR71 -> 0 | Y72: 93 | AA72: =SUM(Y72:Z72) -> 93 | AB72: 162420 | AP72: =SUM(AB72:AO72) -> 162420 | AQ72: =IF(TabProd[[#This Row],[Total Daily]]=0,"",TabProd[[#This Row],[Total]]/TabProd[[#This Row],[Total Daily]]) -> 1746.4516
A73: 46023 | B73: F | D73: 3815 | E73: Inspection Contract - Fixed Team | F73: Ventura | G73: DS Carolina | H73: 3610 | I73: 46023 | J73: 46053 | K73: 162420 | L73: =SUM(TabProd[[#This Row],[Personal]:[Engineering]]) -> 162420 | M73: =IF(TabProd[[#This Row],[Amount Charged]]<>TabProd[[#This Row],[Value]],TabProd[[#This Row],[Amount Charged]]-TabProd[[#This Row],[Value]],"") | N73: 5452 | O73: 46055 | P73: 1690 | Q73: 162420 | R73: 46062 | S73: =IF(R73="","",R73-J73) -> 9 | W73: =IF(V73="","",V73-J73) | X73: =TabProd[[#This Row],[Value]]-TabProd[[#This Row],[InvoiceTotal Value]]-TabProd[[#This Row],[Rental Equipment Invoice Value]]+AR72 -> 0 | Y73: 93 | AA73: =SUM(Y73:Z73) -> 93 | AB73: 162420 | AP73: =SUM(AB73:AO73) -> 162420 | AQ73: =IF(TabProd[[#This Row],[Total Daily]]=0,"",TabProd[[#This Row],[Total]]/TabProd[[#This Row],[Total Daily]]) -> 1746.4516
A74: 46023 | B74: F | D74: 3436 | E74: Inspection Contract - Variable | F74: Ventura | G74: DS Carolina | H74: 4750 | I74: 46023 | J74: 46053 | K74: 208724.85 | L74: =SUM(TabProd[[#This Row],[Personal]:[Engineering]]) -> 208724.85 | M74: =IF(TabProd[[#This Row],[Amount Charged]]<>TabProd[[#This Row],[Value]],TabProd[[#This Row],[Amount Charged]]-TabProd[[#This Row],[Value]],"") | N74: 5453 | O74: 46056 | P74: 1686 | Q74: 190347.6 | R74: 46059 | S74: =IF(R74="","",R74-J74) -> 6 | T74: 1039 | U74: 18377.25 | V74: 46062 | W74: =IF(V74="","",V74-J74) -> 9 | X74: =TabProd[[#This Row],[Value]]-TabProd[[#This Row],[InvoiceTotal Value]]-TabProd[[#This Row],[Rental Equipment Invoice Value]]+AR74 -> 0 | Y74: 93 | AA74: =SUM(Y74:Z74) -> 93 | AB74: 181647.6 | AD74: 8700 | AG74: 17670 | AH74: 707.25 | AP74: =SUM(AB74:AO74) -> 208724.85 | AQ74: =IF(TabProd[[#This Row],[Total Daily]]=0,"",TabProd[[#This Row],[Total]]/TabProd[[#This Row],[Total Daily]]) -> 2244.3532
A75: 46023 | B75: F | D75: 3437 | E75: Inspection Contract - Variable | F75: Ventura | G75: Victoria | H75: 4751 | I75: 46023 | J75: 46053 | K75: 197142 | L75: =SUM(TabProd[[#This Row],[Personal]:[Engineering]]) -> 197142 | M75: =IF(TabProd[[#This Row],[Amount Charged]]<>TabProd[[#This Row],[Value]],TabProd[[#This Row],[Amount Charged]]-TabProd[[#This Row],[Value]],"") | N75: 5454 | O75: 46055 | P75: 1681 | Q75: 179472 | R75: 46058 | S75: =IF(R75="","",R75-J75) -> 5 | T75: 1033 | U75: 17670 | V75: 46058 | W75: =IF(V75="","",V75-J75) -> 5 | X75: =TabProd[[#This Row],[Value]]-TabProd[[#This Row],[InvoiceTotal Value]]-TabProd[[#This Row],[Rental Equipment Invoice Value]]+AR75 -> 0 | Y75: 87 | AA75: =SUM(Y75:Z75) -> 87 | AB75: 170772 | AD75: 8700 | AG75: 17670 | AP75: =SUM(AB75:AO75) -> 197142 | AQ75: =IF(TabProd[[#This Row],[Total Daily]]=0,"",TabProd[[#This Row],[Total]]/TabProd[[#This Row],[Total Daily]]) -> 2266
A76: 46023 | B76: F | D76: 3406 | E76: Engineering | F76: Seadrill | G76: West Carina | H76: 4779 | I76: 46023 | J76: 46053 | K76: 16250 | L76: =SUM(TabProd[[#This Row],[Personal]:[Engineering]]) -> 16250 | M76: =IF(TabProd[[#This Row],[Amount Charged]]<>TabProd[[#This Row],[Value]],TabProd[[#This Row],[Amount Charged]]-TabProd[[#This Row],[Value]],"") | N76: 5456 | O76: 46147 | P76: 1927 | Q76: 16250 | R76: 46148 | S76: =IF(R76="","",R76-J76) -> 95 | W76: =IF(V76="","",V76-J76) | X76: =TabProd[[#This Row],[Value]]-TabProd[[#This Row],[InvoiceTotal Value]]-TabProd[[#This Row],[Rental Equipment Invoice Value]]+AR76 -> 0 | AA76: =SUM(Y76:Z76) -> 0 | AO76: 16250 | AP76: =SUM(AB76:AO76) -> 16250 | AQ76: =IF(TabProd[[#This Row],[Total Daily]]=0,"",TabProd[[#This Row],[Total]]/TabProd[[#This Row],[Total Daily]])
A77: 46023 | B77: F | D77: 3480 | E77: Engineering | F77: Seadrill | G77: West Jupiter | H77: 4857 | I77: 46023 | J77: 46053 | K77: 16250 | L77: =SUM(TabProd[[#This Row],[Personal]:[Engineering]]) -> 16250 | M77: =IF(TabProd[[#This Row],[Amount Charged]]<>TabProd[[#This Row],[Value]],TabProd[[#This Row],[Amount Charged]]-TabProd[[#This Row],[Value]],"") | N77: 5457 | O77: 46064 | P77: 18 | Q77: 16250 | R77: 46072 | S77: =IF(R77="","",R77-J77) -> 19 | W77: =IF(V77="","",V77-J77) | X77: =TabProd[[#This Row],[Value]]-TabProd[[#This Row],[InvoiceTotal Value]]-TabProd[[#This Row],[Rental Equipment Invoice Value]]+AR74 -> 0 | AA77: =SUM(Y77:Z77) -> 0 | AO77: 16250 | AP77: =SUM(AB77:AO77) -> 16250 | AQ77: =IF(TabProd[[#This Row],[Total Daily]]=0,"",TabProd[[#This Row],[Total]]/TabProd[[#This Row],[Total Daily]])
A78: 46023 | B78: F | D78: 3481 | E78: Engineering | F78: Seadrill | G78: West Tellus | H78: 4858 | I78: 46023 | J78: 46053 | K78: 16250 | L78: =SUM(TabProd[[#This Row],[Personal]:[Engineering]]) -> 16250 | M78: =IF(TabProd[[#This Row],[Amount Charged]]<>TabProd[[#This Row],[Value]],TabProd[[#This Row],[Amount Charged]]-TabProd[[#This Row],[Value]],"") | N78: 5458 | O78: 46064 | P78: 1720 | Q78: 16250 | R78: 46066 | S78: =IF(R78="","",R78-J78) -> 13 | W78: =IF(V78="","",V78-J78) | X78: =TabProd[[#This Row],[Value]]-TabProd[[#This Row],[InvoiceTotal Value]]-TabProd[[#This Row],[Rental Equipment Invoice Value]]+AR77 -> 0 | AA78: =SUM(Y78:Z78) -> 0 | AO78: 16250 | AP78: =SUM(AB78:AO78) -> 16250 | AQ78: =IF(TabProd[[#This Row],[Total Daily]]=0,"",TabProd[[#This Row],[Total]]/TabProd[[#This Row],[Total Daily]])
A79: 46023 | B79: F | D79: 3528 | E79: Engineering | F79: Transocean | G79: Mykonos | H79: 4669 | I79: 46023 | J79: 46053 | K79: 33000 | L79: =SUM(TabProd[[#This Row],[Personal]:[Engineering]]) -> 33000 | M79: =IF(TabProd[[#This Row],[Amount Charged]]<>TabProd[[#This Row],[Value]],TabProd[[#This Row],[Amount Charged]]-TabProd[[#This Row],[Value]],"") | N79: 5459 | O79: 46063 | P79: 1698 | Q79: 33000 | R79: 46065 | S79: =IF(R79="","",R79-J79) -> 12 | W79: =IF(V79="","",V79-J79) | X79: =TabProd[[#This Row],[Value]]-TabProd[[#This Row],[InvoiceTotal Value]]-TabProd[[#This Row],[Rental Equipment Invoice Value]]+AR77 -> 0 | AA79: =SUM(Y79:Z79) -> 0 | AO79: 33000 | AP79: =SUM(AB79:AO79) -> 33000 | AQ79: =IF(TabProd[[#This Row],[Total Daily]]=0,"",TabProd[[#This Row],[Total]]/TabProd[[#This Row],[Total Daily]])
A80: 46023 | B80: F | D80: 3530 | E80: Engineering | F80: Transocean | G80: KG2 | H80: 4669 | I80: 46023 | J80: 46053 | K80: 33000 | L80: =SUM(TabProd[[#This Row],[Personal]:[Engineering]]) -> 33000 | M80: =IF(TabProd[[#This Row],[Amount Charged]]<>TabProd[[#This Row],[Value]],TabProd[[#This Row],[Amount Charged]]-TabProd[[#This Row],[Value]],"") | N80: 5460 | P80: 1706 | Q80: 33000 | R80: 46066 | S80: =IF(R80="","",R80-J80) -> 13 | W80: =IF(V80="","",V80-J80) | X80: =TabProd[[#This Row],[Value]]-TabProd[[#This Row],[InvoiceTotal Value]]-TabProd[[#This Row],[Rental Equipment Invoice Value]]+AR79 -> 0 | AA80: =SUM(Y80:Z80) -> 0 | AO80: 33000 | AP80: =SUM(AB80:AO80) -> 33000 | AQ80: =IF(TabProd[[#This Row],[Total Daily]]=0,"",TabProd[[#This Row],[Total]]/TabProd[[#This Row],[Total Daily]])
A81: 46023 | B81: F | D81: 3801 | E81: Inspection Contract - Fixed Team | F81: Transocean | G81: Mykonos | H81: 1877 | I81: 46023 | J81: 46053 | K81: 1636.17 | L81: =SUM(TabProd[[#This Row],[Personal]:[Engineering]]) -> 1636.17 | M81: =IF(TabProd[[#This Row],[Amount Charged]]<>TabProd[[#This Row],[Value]],TabProd[[#This Row],[Amount Charged]]-TabProd[[#This Row],[Value]],"") | N81: 5468 | O81: 46055 | P81: 1718 | Q81: 1636.17 | R81: 46066 | S81: =IF(R81="","",R81-J81) -> 13 | W81: =IF(V81="","",V81-J81) | X81: =TabProd[[#This Row],[Value]]-TabProd[[#This Row],[InvoiceTotal Value]]-TabProd[[#This Row],[Rental Equipment Invoice Value]]+AR80 -> 0 | AA81: =SUM(Y81:Z81) -> 0 | AL81: 1636.17 | AP81: =SUM(AB81:AO81) -> 1636.17 | AQ81: =IF(TabProd[[#This Row],[Total Daily]]=0,"",TabProd[[#This Row],[Total]]/TabProd[[#This Row],[Total Daily]])
A82: 46023 | B82: F | D82: 3801 | E82: Inspection Contract - Fixed Team | F82: Transocean | G82: Mykonos | H82: 1877 | I82: 46023 | J82: 46053 | K82: 1505.65 | L82: =SUM(TabProd[[#This Row],[Personal]:[Engineering]]) -> 1505.65 | M82: =IF(TabProd[[#This Row],[Amount Charged]]<>TabProd[[#This Row],[Value]],TabProd[[#This Row],[Amount Charged]]-TabProd[[#This Row],[Value]],"") | N82: 5476 | O82: 46055 | P82: 1719 | Q82: 1505.65 | R82: 46066 | S82: =IF(R82="","",R82-J82) -> 13 | W82: =IF(V82="","",V82-J82) | X82: =TabProd[[#This Row],[Value]]-TabProd[[#This Row],[InvoiceTotal Value]]-TabProd[[#This Row],[Rental Equipment Invoice Value]]+AR81 -> -2.2737368e-13 | Z82: 1 | AA82: =SUM(Y82:Z82) -> 1 | AC82: 1004.31 | AD82: 92 | AE82: 409.34 | AP82: =SUM(AB82:AO82) -> 1505.65 | AQ82: =IF(TabProd[[#This Row],[Total Daily]]=0,"",TabProd[[#This Row],[Total]]/TabProd[[#This Row],[Total Daily]]) -> 1505.65
A83: 46023 | B83: F | D83: 3807 | E83: Inspection Contract - Fixed Team | F83: Constellation | G83: Amaralina Star | H83: 3380 | I83: 46023 | J83: 46053 | K83: 37084 | L83: =SUM(TabProd[[#This Row],[Personal]:[Engineering]]) -> 37084 | M83: =IF(TabProd[[#This Row],[Amount Charged]]<>TabProd[[#This Row],[Value]],TabProd[[#This Row],[Amount Charged]]-TabProd[[#This Row],[Value]],"") | N83: 5477 | P83: 1700 | Q83: 37084 | R83: 46065 | S83: =IF(R83="","",R83-J83) -> 12 | W83: =IF(V83="","",V83-J83) | X83: =TabProd[[#This Row],[Value]]-TabProd[[#This Row],[InvoiceTotal Value]]-TabProd[[#This Row],[Rental Equipment Invoice Value]]+AR82 -> 0 | AA83: =SUM(Y83:Z83) -> 0 | AE83: 37084 | AP83: =SUM(AB83:AO83) -> 37084 | AQ83: =IF(TabProd[[#This Row],[Total Daily]]=0,"",TabProd[[#This Row],[Total]]/TabProd[[#This Row],[Total Daily]])
A84: 46023 | B84: F | D84: 3800 | E84: Inspection Contract - Fixed Team | F84: Transocean | G84: Corcovado | H84: 1877 | I84: 46023 | J84: 46053 | K84: 1636.17 | L84: =SUM(TabProd[[#This Row],[Personal]:[Engineering]]) -> 1636.17 | M84: =IF(TabProd[[#This Row],[Amount Charged]]<>TabProd[[#This Row],[Value]],TabProd[[#This Row],[Amount Charged]]-TabProd[[#This Row],[Value]],"") | N84: 5479 | O84: 46056 | P84: 1678 | Q84: 1636.17 | R84: 46058 | S84: =IF(R84="","",R84-J84) -> 5 | W84: =IF(V84="","",V84-J84) | X84: =TabProd[[#This Row],[Value]]-TabProd[[#This Row],[InvoiceTotal Value]]-TabProd[[#This Row],[Rental Equipment Invoice Value]]+AR83 -> 0 | AA84: =SUM(Y84:Z84) -> 0 | AL84: 1636.17 | AP84: =SUM(AB84:AO84) -> 1636.17 | AQ84: =IF(TabProd[[#This Row],[Total Daily]]=0,"",TabProd[[#This Row],[Total]]/TabProd[[#This Row],[Total Daily]])
A85: 46023 | B85: F | D85: 3491 | E85: Inspection Contract - Variable | F85: Transocean | G85: Corcovado | H85: 4964 | I85: 46023 | J85: 46053 | K85: 262427.09 | L85: =SUM(TabProd[[#This Row],[Personal]:[Engineering]]) -> 262427.09 | M85: =IF(TabProd[[#This Row],[Amount Charged]]<>TabProd[[#This Row],[Value]],TabProd[[#This Row],[Amount Charged]]-TabProd[[#This Row],[Value]],"") | N85: 5408 | O85: 46056 | P85: 1715 | Q85: 240167.28 | R85: 46066 | S85: =IF(R85="","",R85-J85) -> 13 | T85: 1055 | U85: 22259.81 | V85: 46066 | W85: =IF(V85="","",V85-J85) -> 13 | X85: =TabProd[[#This Row],[Value]]-TabProd[[#This Row],[InvoiceTotal Value]]-TabProd[[#This Row],[Rental Equipment Invoice Value]]+AR84 -> -3.2741809e-11 | Y85: 93 | AA85: =SUM(Y85:Z85) -> 93 | AB85: 193945.11 | AD85: 13222.17 | AG85: 22259.81 | AO85: 33000 | AP85: =SUM(AB85:AO85) -> 262427.09 | AQ85: =IF(TabProd[[#This Row],[Total Daily]]=0,"",TabProd[[#This Row],[Total]]/TabProd[[#This Row],[Total Daily]]) -> 2821.7967
A86: 46023 | B86: F | D86: 3812 | E86: Inspection Contract - Fixed Team | F86: Foresea | G86: Norbe 9 | H86: 2016 | I86: 46023 | J86: 46053 | K86: 173780.72 | L86: =SUM(TabProd[[#This Row],[Personal]:[Engineering]]) -> 173780.72 | M86: =IF(TabProd[[#This Row],[Amount Charged]]<>TabProd[[#This Row],[Value]],TabProd[[#This Row],[Amount Charged]]-TabProd[[#This Row],[Value]],"") | N86: 5445 | O86: 46055 | P86: 1673 | Q86: 173780.72 | R86: 46057 | S86: =IF(R86="","",R86-J86) -> 4 | W86: =IF(V86="","",V86-J86) | X86: =TabProd[[#This Row],[Value]]-TabProd[[#This Row],[InvoiceTotal Value]]-TabProd[[#This Row],[Rental Equipment Invoice Value]]+AR84 -> 0 | Y86: 93 | AA86: =SUM(Y86:Z86) -> 93 | AB86: 173780.72 | AP86: =SUM(AB86:AO86) -> 173780.72 | AQ86: =IF(TabProd[[#This Row],[Total Daily]]=0,"",TabProd[[#This Row],[Total]]/TabProd[[#This Row],[Total Daily]]) -> 1868.6099
A87: 46023 | B87: F | D87: 3486 | E87: Inspection Contract - Variable | F87: Transocean | G87: Orion | H87: 4964 | I87: 46023 | J87: 46053 | K87: 259499.9 | L87: =SUM(TabProd[[#This Row],[Personal]:[Engineering]]) -> 259499.9 | M87: =IF(TabProd[[#This Row],[Amount Charged]]<>TabProd[[#This Row],[Value]],TabProd[[#This Row],[Amount Charged]]-TabProd[[#This Row],[Value]],"") | N87: 5404 | O87: 46055 | P87: 1701 | Q87: 237240.09 | R87: 46065 | S87: =IF(R87="","",R87-J87) -> 12 | T87: 1043 | U87: 22259.81 | V87: 46065 | W87: =IF(V87="","",V87-J87) -> 12 | X87: =TabProd[[#This Row],[Value]]-TabProd[[#This Row],[InvoiceTotal Value]]-TabProd[[#This Row],[Rental Equipment Invoice Value]]+AR86 -> -3.6379788e-12 | Y87: 93 | Z87: 1 | AA87: =SUM(Y87:Z87) -> 94 | AB87: 193945.11 | AC87: 1141.17 | AD87: 9153.81 | AG87: 22259.81 | AO87: 33000 | AP87: =SUM(AB87:AO87) -> 259499.9 | AQ87: =IF(TabProd[[#This Row],[Total Daily]]=0,"",TabProd[[#This Row],[Total]]/TabProd[[#This Row],[Total Daily]]) -> 2760.6372
A88: 46023 | B88: F | D88: 3564 | E88: Inspection Contract - Variable | F88: Constellation | G88: Amaralina Star | H88: 5126 | I88: 46023 | J88: 46074 | K88: 215577.9 | L88: =SUM(TabProd[[#This Row],[Personal]:[Engineering]]) -> 215577.9 | M88: =IF(TabProd[[#This Row],[Amount Charged]]<>TabProd[[#This Row],[Value]],TabProd[[#This Row],[Amount Charged]]-TabProd[[#This Row],[Value]],"") | N88: 5419-5609 | O88: 46097 | P88: 1800-1801 | Q88: 215577.9 | R88: 46098 | S88: =IF(R88="","",R88-J88) -> 24 | W88: =IF(V88="","",V88-J88) | X88: =TabProd[[#This Row],[Value]]-TabProd[[#This Row],[InvoiceTotal Value]]-TabProd[[#This Row],[Rental Equipment Invoice Value]]+AR86 -> 0 | Y88: 92 | AA88: =SUM(Y88:Z88) -> 92 | AB88: 164098.42 | AD88: 2485.8 | AE88: 48993.68 | AP88: =SUM(AB88:AO88) -> 215577.9 | AQ88: =IF(TabProd[[#This Row],[Total Daily]]=0,"",TabProd[[#This Row],[Total]]/TabProd[[#This Row],[Total Daily]]) -> 2343.238
A89: 46054 | B89: F | D89: 3564 | E89: Inspection Contract - Variable | F89: Constellation | G89: Amaralina Star | H89: 5126 | I89: 46023 | J89: 46074 | K89: 143390.36 | L89: =SUM(TabProd[[#This Row],[Personal]:[Engineering]]) -> 143390.36 | M89: =IF(TabProd[[#This Row],[Amount Charged]]<>TabProd[[#This Row],[Value]],TabProd[[#This Row],[Amount Charged]]-TabProd[[#This Row],[Value]],"") | N89: 5419-5609 | O89: 46097 | P89: 1800-1801 | Q89: 143390.36 | R89: 46098 | S89: =IF(R89="","",R89-J89) -> 24 | W89: =IF(V89="","",V89-J89) | X89: =TabProd[[#This Row],[Value]]-TabProd[[#This Row],[InvoiceTotal Value]]-TabProd[[#This Row],[Rental Equipment Invoice Value]]+AR88 -> 0 | Y89: 57 | AA89: =SUM(Y89:Z89) -> 57 | AB89: 109306.88 | AD89: 3728.7 | AE89: 30354.78 | AP89: =SUM(AB89:AO89) -> 143390.36 | AQ89: =IF(TabProd[[#This Row],[Total Daily]]=0,"",TabProd[[#This Row],[Total]]/TabProd[[#This Row],[Total Daily]]) -> 2515.6204
A90: 46082 | B90: F | D90: 3564 | E90: Inspection Contract - Variable | F90: Constellation | G90: Amaralina Star | H90: 5126 | I90: 46023 | J90: 46074 | K90: -13680.1 | L90: =SUM(TabProd[[#This Row],[Personal]:[Engineering]]) -> -13680.1 | M90: =IF(TabProd[[#This Row],[Amount Charged]]<>TabProd[[#This Row],[Value]],TabProd[[#This Row],[Amount Charged]]-TabProd[[#This Row],[Value]],"") | N90: 5419-5609 | O90: 46097 | P90: 1800-1801 | Q90: -13680.1 | R90: 46098 | S90: =IF(R90="","",R90-J90) -> 24 | W90: =IF(V90="","",V90-J90) | X90: =TabProd[[#This Row],[Value]]-TabProd[[#This Row],[InvoiceTotal Value]]-TabProd[[#This Row],[Rental Equipment Invoice Value]]+AR90 -> 0 | AA90: =SUM(Y90:Z90) -> 0 | AM90: -13680.1 | AP90: =SUM(AB90:AO90) -> -13680.1 | AQ90: =IF(TabProd[[#This Row],[Total Daily]]=0,"",TabProd[[#This Row],[Total]]/TabProd[[#This Row],[Total Daily]])
A91: 46023 | B91: F | D91: 3811 | E91: Inspection Contract - Fixed Team | F91: Foresea | G91: Norbe 6 | H91: 2016 | I91: 46023 | J91: 46053 | K91: 175228.89 | L91: =SUM(TabProd[[#This Row],[Personal]:[Engineering]]) -> 175228.89 | M91: =IF(TabProd[[#This Row],[Amount Charged]]<>TabProd[[#This Row],[Value]],TabProd[[#This Row],[Amount Charged]]-TabProd[[#This Row],[Value]],"") | N91: 5443-5444 | O91: 46055 | P91: 1670-1671 | Q91: 175228.89 | R91: 46056 | S91: =IF(R91="","",R91-J91) -> 3 | W91: =IF(V91="","",V91-J91) | X91: =TabProd[[#This Row],[Value]]-TabProd[[#This Row],[InvoiceTotal Value]]-TabProd[[#This Row],[Rental Equipment Invoice Value]]+AR90 -> 0 | Y91: 94 | AA91: =SUM(Y91:Z91) -> 94 | AB91: 173780.72 | AL91: 1448.17 | AP91: =SUM(AB91:AO91) -> 175228.89 | AQ91: =IF(TabProd[[#This Row],[Total Daily]]=0,"",TabProd[[#This Row],[Total]]/TabProd[[#This Row],[Total Daily]]) -> 1864.1371
A92: 46023 | B92: F | D92: 3490 | E92: Inspection Contract - Variable | F92: Transocean | G92: PBS | H92: 4964 | I92: 46023 | J92: 46053 | K92: 255182.96 | L92: =SUM(TabProd[[#This Row],[Personal]:[Engineering]]) -> 255182.96 | M92: =IF(TabProd[[#This Row],[Amount Charged]]<>TabProd[[#This Row],[Value]],TabProd[[#This Row],[Amount Charged]]-TabProd[[#This Row],[Value]],"") | N92: 5407 | O92: 46055 | P92: 1714 | Q92: 232923.15 | R92: 46066 | S92: =IF(R92="","",R92-J92) -> 13 | T92: 1053 | U92: 22259.81 | V92: 46066 | W92: =IF(V92="","",V92-J92) -> 13 | X92: =TabProd[[#This Row],[Value]]-TabProd[[#This Row],[InvoiceTotal Value]]-TabProd[[#This Row],[Rental Equipment Invoice Value]]+AR91 -> -3.6379788e-12 | Y92: 93 | AA92: =SUM(Y92:Z92) -> 93 | AB92: 193945.11 | AD92: 5978.04 | AG92: 22259.81 | AO92: 33000 | AP92: =SUM(AB92:AO92) -> 255182.96 | AQ92: =IF(TabProd[[#This Row],[Total Daily]]=0,"",TabProd[[#This Row],[Total]]/TabProd[[#This Row],[Total Daily]]) -> 2743.9028
A93: 46023 | B93: F | D93: 3415 | E93: Inspection Contract - Variable | F93: Modec | G93: FPSO Bacalhau | H93: 4874 | I93: 46024 | J93: 46037 | K93: 59281.48 | L93: =SUM(TabProd[[#This Row],[Personal]:[Engineering]]) -> 59281.48 | M93: =IF(TabProd[[#This Row],[Amount Charged]]<>TabProd[[#This Row],[Value]],TabProd[[#This Row],[Amount Charged]]-TabProd[[#This Row],[Value]],"") | N93: 5366 | O93: 46049 | P93: 1729 | Q93: 59281.48 | R93: 46072 | S93: =IF(R93="","",R93-J93) -> 35 | W93: =IF(V93="","",V93-J93) | X93: =TabProd[[#This Row],[Value]]-TabProd[[#This Row],[InvoiceTotal Value]]-TabProd[[#This Row],[Rental Equipment Invoice Value]]+AR93 -> 0 | Y93: 41 | AA93: =SUM(Y93:Z93) -> 41 | AB93: 59281.48 | AP93: =SUM(AB93:AO93) -> 59281.48 | AQ93: =IF(TabProd[[#This Row],[Total Daily]]=0,"",TabProd[[#This Row],[Total]]/TabProd[[#This Row],[Total Daily]]) -> 1445.8898
A94: 46023 | B94: F | D94: 3457 | E94: Inspection Contract - Variable | F94: Foresea | G94: Norbe 6 | H94: 4940 | I94: 46025 | J94: 46067 | K94: 71143.04 | L94: =SUM(TabProd[[#This Row],[Personal]:[Engineering]]) -> 71143.04 | M94: =IF(TabProd[[#This Row],[Amount Charged]]<>TabProd[[#This Row],[Value]],TabProd[[#This Row],[Amount Charged]]-TabProd[[#This Row],[Value]],"") | N94: 5396 | O94: 46072 | P94: 1762 | Q94: 71143.04 | R94: 46087 | S94: =IF(R94="","",R94-J94) -> 20 | W94: =IF(V94="","",V94-J94) | X94: =TabProd[[#This Row],[Value]]-TabProd[[#This Row],[InvoiceTotal Value]]-TabProd[[#This Row],[Rental Equipment Invoice Value]]+AR94 -> 0 | Y94: 40 | AA94: =SUM(Y94:Z94) -> 40 | AB94: 71143.04 | AP94: =SUM(AB94:AO94) -> 71143.04 | AQ94: =IF(TabProd[[#This Row],[Total Daily]]=0,"",TabProd[[#This Row],[Total]]/TabProd[[#This Row],[Total Daily]]) -> 1778.576
A95: 46143 | B95: F | D95: 3457 | E95: Inspection Contract - Variable | F95: Foresea | G95: Norbe 6 | H95: 4940 | I95: 46025 | J95: 46067 | K95: 153080.54 | L95: =SUM(TabProd[[#This Row],[Personal]:[Engineering]]) -> 153080.54 | M95: =IF(TabProd[[#This Row],[Amount Charged]]<>TabProd[[#This Row],[Value]],TabProd[[#This Row],[Amount Charged]]-TabProd[[#This Row],[Value]],"") | N95: 5396 | O95: 46072 | P95: 1762 | Q95: 153080.54 | R95: 46087 | S95: =IF(R95="","",R95-J95) -> 20 | W95: =IF(V95="","",V95-J95) | X95: =TabProd[[#This Row],[Value]]-TabProd[[#This Row],[InvoiceTotal Value]]-TabProd[[#This Row],[Rental Equipment Invoice Value]]+AR95 -> -2.910383e-11 | Y95: 45 | AA95: =SUM(Y95:Z95) -> 45 | AB95: 153080.54 | AP95: =SUM(AB95:AO95) -> 153080.54 | AQ95: =IF(TabProd[[#This Row],[Total Daily]]=0,"",TabProd[[#This Row],[Total]]/TabProd[[#This Row],[Total Daily]]) -> 3401.7898
A96: 46023 | B96: F | D96: 3566 | E96: Inspection Contract - Variable | F96: Constellation | G96: Admarine | H96: 5116 | I96: 46025 | J96: 46039 | K96: 161719.87 | L96: =SUM(TabProd[[#This Row],[Personal]:[Engineering]]) -> 161719.87 | M96: =IF(TabProd[[#This Row],[Amount Charged]]<>TabProd[[#This Row],[Value]],TabProd[[#This Row],[Amount Charged]]-TabProd[[#This Row],[Value]],"") | N96: 5435 | O96: 46049 | P96: 1684 | Q96: 108369.26 | R96: 46059 | S96: =IF(R96="","",R96-J96) -> 20 | T96: 1036 | U96: 53350.61 | V96: 46059 | W96: =IF(V96="","",V96-J96) -> 20 | X96: =TabProd[[#This Row],[Value]]-TabProd[[#This Row],[InvoiceTotal Value]]-TabProd[[#This Row],[Rental Equipment Invoice Value]]+AR93 -> 2.910383e-11 | Y96: 42 | AA96: =SUM(Y96:Z96) -> 42 | AB96: 81934.16 | AD96: 25641.6 | AE96: 793.5 | AG96: 74503.2 | AM96: -21152.59 | AP96: =SUM(AB96:AO96) -> 161719.87 | AQ96: =IF(TabProd[[#This Row],[Total Daily]]=0,"",TabProd[[#This Row],[Total]]/TabProd[[#This Row],[Total Daily]]) -> 3850.4731
A97: 46023 | B97: F | D97: 3642 | E97: Inspection Spot | F97: Wilson Sons | G97: MV-18 | H97: 5283 | I97: 46027 | J97: 46031 | K97: 468261.24 | L97: =SUM(TabProd[[#This Row],[Personal]:[Engineering]]) -> 468261.24 | M97: =IF(TabProd[[#This Row],[Amount Charged]]<>TabProd[[#This Row],[Value]],TabProd[[#This Row],[Amount Charged]]-TabProd[[#This Row],[Value]],"") | N97: 5385 | O97: 46035 | P97: 1636-1638 | Q97: 468261.24 | R97: 46043 | S97: =IF(R97="","",R97-J97) -> 12 | W97: =IF(V97="","",V97-J97) | X97: =TabProd[[#This Row],[Value]]-TabProd[[#This Row],[InvoiceTotal Value]]-TabProd[[#This Row],[Rental Equipment Invoice Value]]+AR92 -> 0 | Y97: 60 | AA97: =SUM(Y97:Z97) -> 60 | AB97: 468261.24 | AP97: =SUM(AB97:AO97) -> 468261.24 | AQ97: =IF(TabProd[[#This Row],[Total Daily]]=0,"",TabProd[[#This Row],[Total]]/TabProd[[#This Row],[Total Daily]]) -> 7804.354
A98: 46023 | B98: F | D98: 3488 | E98: Inspection Contract - Variable | F98: Transocean | G98: Mykonos | H98: 4964 | I98: 46027 | J98: 46048 | K98: 188085.16 | L98: =SUM(TabProd[[#This Row],[Personal]:[Engineering]]) -> 188085.16 | M98: =IF(TabProd[[#This Row],[Amount Charged]]<>TabProd[[#This Row],[Value]],TabProd[[#This Row],[Amount Charged]]-TabProd[[#This Row],[Value]],"") | N98: 5406 | O98: 46049 | P98: 1703 | Q98: 171999.16 | R98: 46065 | S98: =IF(R98="","",R98-J98) -> 17 | T98: 1045 | U98: 16086 | V98: 46065 | W98: =IF(V98="","",V98-J98) -> 17 | X98: =TabProd[[#This Row],[Value]]-TabProd[[#This Row],[InvoiceTotal Value]]-TabProd[[#This Row],[Rental Equipment Invoice Value]]+AR97 -> 0 | Y98: 63 | AA98: =SUM(Y98:Z98) -> 63 | AB98: 169119.16 | AD98: 2880 | AG98: 16086 | AP98: =SUM(AB98:AO98) -> 188085.16 | AQ98: =IF(TabProd[[#This Row],[Total Daily]]=0,"",TabProd[[#This Row],[Total]]/TabProd[[#This Row],[Total Daily]]) -> 2985.4787
A99: 46023 | B99: F | D99: 3637 | E99: Inspection Spot | F99: Etesco | G99: Arabia | H99: 5226-5260 | I99: 46028 | J99: 46044 | K99: 175982.12 | L99: =SUM(TabProd[[#This Row],[Personal]:[Engineering]]) -> 175982.12 | M99: =IF(TabProd[[#This Row],[Amount Charged]]<>TabProd[[#This Row],[Value]],TabProd[[#This Row],[Amount Charged]]-TabProd[[#This Row],[Value]],"") | N99: 5418 | O99: 46050 | P99: 1682 | Q99: 136422.12 | R99: 46059 | S99: =IF(R99="","",R99-J99) -> 15 | T99: 1034 | U99: 39560 | V99: 46059 | W99: =IF(V99="","",V99-J99) -> 15 | X99: =TabProd[[#This Row],[Value]]-TabProd[[#This Row],[InvoiceTotal Value]]-TabProd[[#This Row],[Rental Equipment Invoice Value]]+AR98 -> 0 | Y99: 43 | Z99: 1 | AA99: =SUM(Y99:Z99) -> 44 | AB99: 104932 | AC99: 1174 | AD99: 24433.08 | AE99: 532.54 | AG99: 39560 | AL99: 5350.5 | AP99: =SUM(AB99:AO99) -> 175982.12 | AQ99: =IF(TabProd[[#This Row],[Total Daily]]=0,"",TabProd[[#This Row],[Total]]/TabProd[[#This Row],[Total Daily]]) -> 3999.5936
A100: 46023 | B100: F | D100: 3648 | E100: Inspection Spot | F100: Trident | G100: Base Qualitech | H100: 5317 | I100: 46029 | J100: 46029 | K100: 5768.31 | L100: =SUM(TabProd[[#This Row],[Personal]:[Engineering]]) -> 5768.31 | M100: =IF(TabProd[[#This Row],[Amount Charged]]<>TabProd[[#This Row],[Value]],TabProd[[#This Row],[Amount Charged]]-TabProd[[#This Row],[Value]],"") | N100: 5440 | O100: 46048 | P100: 1661 | Q100: 5051.29 | R100: 46055 | S100: =IF(R100="","",R100-J100) -> 26 | T100: 1021 | U100: 717.02 | V100: 46055 | W100: =IF(V100="","",V100-J100) -> 26 | X100: =TabProd[[#This Row],[Value]]-TabProd[[#This Row],[InvoiceTotal Value]]-TabProd[[#This Row],[Rental Equipment Invoice Value]]+AR99 -> 4.5474735e-13 | Y100: 2 | AA100: =SUM(Y100:Z100) -> 2 | AB100: 4560 | AG100: 717.02 | AN100: 491.29 | AP100: =SUM(AB100:AO100) -> 5768.31 | AQ100: =IF(TabProd[[#This Row],[Total Daily]]=0,"",TabProd[[#This Row],[Total]]/TabProd[[#This Row],[Total Daily]]) -> 2884.155
...

Sheet Planilha1
B1: Total Daily | C1: (Tudo)
C3: Rótulos de Coluna
C4: 45658 | D4: 45689 | E4: 45717 | F4: 45748 | G4: 45778 | H4: 45809 | I4: 45839 | J4: 45870 | K4: 45901 | L4: 45931 | M4: Total Geral
B5: Soma de Total | C5: 8162857.9 | D5: 11040023 | E5: 9503777 | F5: 7670252.1 | G5: 8360840.6 | H5: 8007506.7 | I5: 10241280 | J5: 12355008 | K5: 10410789 | L5: 13249252 | M5: 99001587
B7: Total Daily | C7: (Tudo)
B9: Soma de Total | C9: Rótulos de Coluna
B10: Rótulos de Linha | C10: 45658 | D10: 45689 | E10: 45717 | F10: 45748 | G10: 45778 | H10: 45809 | I10: 45839 | J10: 45870 | K10: 45901 | L10: 45931 | M10: Total Geral
B11: Engineering | G11: 99071 | H11: 218005 | I11: 311616 | J11: 376866 | K11: 203550 | L11: 409240 | M11: 1618348
B12: Equipment Rental | C12: 122519.06 | D12: 135038.28 | E12: 177870.84 | F12: 139228.43 | G12: 150764.34 | H12: 153932.9 | I12: 201974.08 | J12: 110764.1 | K12: 319698.7 | L12: -3632.72 | M12: 1508158
B13: Inspection Contract - Fixed Team | C13: 2527553.8 | D13: 2567526.7 | E13: 2552345.8 | F13: 2697320.1 | G13: 2634521.7 | H13: 2782488.6 | I13: 2892340.2 | J13: 2697071.4 | K13: 2352708.2 | L13: 2671161 | M13: 26375037
B14: Inspection Contract - Variable | C14: 1334866.5 | D14: 2677055.4 | E14: 2151275.9 | F14: 1509970.1 | G14: 1423202.2 | H14: 1211994.1 | I14: 2040312.8 | J14: 3786060.2 | K14: 3665965.3 | L14: 5588411.2 | M14: 25389114
B15: Inspection Spot | C15: 448449.54 | D15: 669372.35 | E15: 1503300.3 | F15: 1471788.9 | G15: 1778504.7 | H15: 1893352 | I15: 1706242.1 | J15: 2291293.9 | K15: 1597185.1 | L15: 1779596.5 | M15: 15139085
B16: Maintenance Contract - Variable | C16: 1419140.7 | D16: 3502008.9 | E16: 1969628.1 | F16: 1074008.6 | G16: 904611.12 | H16: 869121.47 | I16: 1791653.9 | J16: 2118005.3 | K16: 1764911.9 | L16: 1560597.5 | M16: 16973687
B17: Maintenance Spot | C17: 2310328.4 | D17: 1489021.7 | E17: 1149356.1 | F17: 777935.93 | G17: 1370165.7 | H17: 878612.64 | I17: 1297140.8 | J17: 974947.05 | K17: 506769.78 | L17: 1243878.8 | M17: 11998157
B18: Total Geral | C18: 8162857.9 | D18: 11040023 | E18: 9503777 | F18: 7670252.1 | G18: 8360840.6 | H18: 8007506.7 | I18: 10241280 | J18: 12355008 | K18: 10410789 | L18: 13249252 | M18: 99001587
B20: Inspeção | C20: =SUM(C13:C15) -> 4310869.8 | D20: =SUM(D13:D15) -> 5913954.4 | E20: =SUM(E13:E15) -> 6206922 | F20: =SUM(F13:F15) -> 5679079.1 | G20: =SUM(G13:G15) -> 5836228.5 | H20: =SUM(H13:H15) -> 5887834.7 | I20: =SUM(I13:I15) -> 6638895.1 | J20: =SUM(J13:J15) -> 8774425.5 | ... L20: =SUM(L13:L15) -> 10039169 | M20: =SUM(C20:L20) -> 66903236
B21: Manutenção | C21: =SUM(C16:C17) -> 3729469.1 | D21: =SUM(D16:D17) -> 4991030.5 | E21: =SUM(E16:E17) -> 3118984.1 | F21: =SUM(F16:F17) -> 1851944.5 | G21: =SUM(G16:G17) -> 2274776.8 | H21: =SUM(H16:H17) -> 1747734.1 | I21: =SUM(I16:I17) -> 3088794.7 | J21: =SUM(J16:J17) -> 3092952.4 | ... L21: =SUM(L16:L17) -> 2804476.3 | M21: =SUM(C21:L21) -> 28971844
B22: Engenharia | C22: =C11 -> 0 | D22: =D11 -> 0 | E22: =E11 -> 0 | F22: =F11 -> 0 | G22: =G11 -> 99071 | H22: =H11 -> 218005 | I22: =I11 -> 311616 | J22: =J11 -> 376866 | ... L22: =L11 -> 409240 | M22: =SUM(C22:L22) -> 1618348
B23: Outros | C23: =C18-C22-C21-C20 -> 122519.06 | D23: =D18-D22-D21-D20 -> 135038.28 | E23: =E18-E22-E21-E20 -> 177870.84 | F23: =F18-F22-F21-F20 -> 139228.43 | G23: =G18-G22-G21-G20 -> 150764.34 | H23: =H18-H22-H21-H20 -> 153932.9 | I23: =I18-I22-I21-I20 -> 201974.08 | J23: =J18-J22-J21-J20 -> 110764.1 | ... L23: =L18-L22-L21-L20 -> -3632.72 | M23: =SUM(C23:L23) -> 1508158
C28: Rótulos de Coluna
C29: 45658 | D29: 45689 | E29: 45717 | F29: 45748 | G29: 45778 | H29: 45809 | I29: 45839 | J29: 45870 | K29: 45901 | L29: 45931 | M29: Total Geral
B30: Soma de Daily | C30: 2989 | D30: 3586 | E30: 2975 | F30: 2889 | G30: 2991 | H30: 2836 | I30: 3475 | J30: 4264 | K30: 3703 | L30: 4249 | M30: 33957
B32: Total Daily | C32: (Tudo)
B34: Soma de Total | C34: Rótulos de Coluna
B35: Rótulos de Linha | C35: 45658 | D35: 45689 | E35: 45717 | F35: 45748 | G35: 45778 | H35: 45809 | I35: 45839 | J35: 45870 | K35: 45901 | L35: 45931 | M35: Total Geral
B36: Engineering | G36: 99071 | H36: 218005 | I36: 311616 | J36: 376866 | K36: 203550 | L36: 409240 | M36: 1618348
B37: Equipment Rental | C37: 122519.06 | D37: 135038.28 | E37: 177870.84 | F37: 139228.43 | G37: 150764.34 | H37: 153932.9 | I37: 201974.08 | J37: 110764.1 | K37: 319698.7 | L37: -3632.72 | M37: 1508158
B38: Inspection Contract - Fixed Team | C38: 2527553.8 | D38: 2567526.7 | E38: 2552345.8 | F38: 2697320.1 | G38: 2634521.7 | H38: 2782488.6 | I38: 2892340.2 | J38: 2697071.4 | K38: 2352708.2 | L38: 2671161 | M38: 26375037
B39: Inspection Contract - Variable | C39: 1334866.5 | D39: 2677055.4 | E39: 2151275.9 | F39: 1509970.1 | G39: 1423202.2 | H39: 1211994.1 | I39: 2040312.8 | J39: 3786060.2 | K39: 3665965.3 | L39: 5588411.2 | M39: 25389114
B40: Inspection Spot | C40: 448449.54 | D40: 669372.35 | E40: 1503300.3 | F40: 1471788.9 | G40: 1778504.7 | H40: 1893352 | I40: 1706242.1 | J40: 2291293.9 | K40: 1597185.1 | L40: 1779596.5 | M40: 15139085
B41: Maintenance Contract - Variable | C41: 1419140.7 | D41: 3502008.9 | E41: 1969628.1 | F41: 1074008.6 | G41: 904611.12 | H41: 869121.47 | I41: 1791653.9 | J41: 2118005.3 | K41: 1764911.9 | L41: 1560597.5 | M41: 16973687
B42: Maintenance Spot | C42: 2310328.4 | D42: 1489021.7 | E42: 1149356.1 | F42: 777935.93 | G42: 1370165.7 | H42: 878612.64 | I42: 1297140.8 | J42: 974947.05 | K42: 506769.78 | L42: 1243878.8 | M42: 11998157
B43: Total Geral | C43: 8162857.9 | D43: 11040023 | E43: 9503777 | F43: 7670252.1 | G43: 8360840.6 | H43: 8007506.7 | I43: 10241280 | J43: 12355008 | K43: 10410789 | L43: 13249252 | M43: 99001587
N44: Nov | O44: Dez
B45: Inspeção | C45: =SUM(C38:C40) -> 4310869.8 | D45: =SUM(D38:D40) -> 5913954.4 | E45: =SUM(E38:E40) -> 6206922 | F45: =SUM(F38:F40) -> 5679079.1 | G45: =SUM(G38:G40) -> 5836228.5 | H45: =SUM(H38:H40) -> 5887834.7 | I45: =SUM(I38:I40) -> 6638895.1 | J45: =SUM(J38:J40) -> 8774425.5 | ... L45: =SUM(L38:L40) -> 10039169 | N45: 9949954.5 | O45: 8989950 | P45: =SUM(C45:O45) -> 85843141
B46: Manutenção | C46: =SUM(C41:C42) -> 3729469.1 | D46: =SUM(D41:D42) -> 4991030.5 | E46: =SUM(E41:E42) -> 3118984.1 | F46: =SUM(F41:F42) -> 1851944.5 | G46: =SUM(G41:G42) -> 2274776.8 | H46: =SUM(H41:H42) -> 1747734.1 | I46: =SUM(I41:I42) -> 3088794.7 | J46: =SUM(J41:J42) -> 3092952.4 | ... L46: =SUM(L41:L42) -> 2804476.3 | N46: 987819 | O46: 1640483 | P46: =SUM(C46:O46) -> 31600146
B47: Engenharia | C47: =C36 -> 0 | D47: =D36 -> 0 | E47: =E36 -> 0 | F47: =F36 -> 0 | G47: =G36 -> 99071 | H47: =H36 -> 218005 | I47: =I36 -> 311616 | J47: =J36 -> 376866 | ... L47: =L36 -> 409240 | N47: 488345.72 | O47: 605301.44 | P47: =SUM(C47:O47) -> 2711995.2
B48: Outros | C48: =C43-C47-C46-C45 -> 122519.06 | D48: =D43-D47-D46-D45 -> 135038.28 | E48: =E43-E47-E46-E45 -> 177870.84 | F48: =F43-F47-F46-F45 -> 139228.43 | G48: =G43-G47-G46-G45 -> 150764.34 | H48: =H43-H47-H46-H45 -> 153932.9 | I48: =I43-I47-I46-I45 -> 201974.08 | J48: =J43-J47-J46-J45 -> 110764.1 | ... L48: =L43-L47-L46-L45 -> -3632.72 | N48: 0 | O48: 0 | P48: =SUM(C48:O48) -> 1508158
C49: =SUM(C45:C48) -> 8162857.9 | D49: =SUM(D45:D48) -> 11040023 | E49: =SUM(E45:E48) -> 9503777 | F49: =SUM(F45:F48) -> 7670252.1 | G49: =SUM(G45:G48) -> 8360840.6 | H49: =SUM(H45:H48) -> 8007506.7 | I49: =SUM(I45:I48) -> 10241280 | J49: =SUM(J45:J48) -> 12355008 | ... L49: =SUM(L45:L48) -> 13249252 | N49: =SUM(N45:N48) -> 11426119 | O49: =SUM(O45:O48) -> 11235734
B52: Total Daily | C52: (Tudo)
B54: Soma de Total Daily | C54: Rótulos de Coluna
B55: Rótulos de Linha | C55: 45658 | D55: 45689 | E55: 45717 | F55: 45748 | G55: 45778 | H55: 45809 | I55: 45839 | J55: 45870 | K55: 45901 | L55: 45931 | M55: Total Geral
B56: Engineering | G56: 0 | H56: 0 | I56: 0 | J56: 0 | K56: 0 | L56: 45 | M56: 45
B57: Equipment Rental | C57: 0 | D57: 0 | E57: 0 | F57: 0 | G57: 0 | H57: 0 | I57: 0 | J57: 0 | K57: 0 | L57: 0 | M57: 0
B58: Inspection Contract - Fixed Team | C58: 1321 | D58: 1210 | E58: 1315 | F58: 1343 | G58: 1353 | H58: 1360 | I58: 1400 | J58: 1394 | K58: 1168 | L58: 1352 | M58: 13216
B59: Inspection Contract - Variable | C59: 487 | D59: 756 | E59: 590 | F59: 606 | G59: 573 | H59: 534 | I59: 882 | J59: 1339 | K59: 1520 | L59: 1759 | M59: 9046
B60: Inspection Spot | C60: 97 | D60: 235 | E60: 472 | F60: 481 | G60: 583 | H60: 629 | I60: 560 | J60: 747 | K60: 446 | L60: 526 | M60: 4776
B61: Maintenance Contract - Variable | C61: 487 | D61: 1008 | E61: 334 | F61: 318 | G61: 196 | H61: 213 | I61: 388 | J61: 627 | K61: 476 | L61: 383 | M61: 4430
B62: Maintenance Spot | C62: 681 | D62: 396 | E62: 311 | F62: 217 | G62: 325 | H62: 184 | I62: 290 | J62: 253 | K62: 92 | L62: 303 | M62: 3052
B63: Total Geral | C63: 3073 | D63: 3605 | E63: 3022 | F63: 2965 | G63: 3030 | H63: 2920 | I63: 3520 | J63: 4360 | K63: 3702 | L63: 4368 | M63: 34565
N64: Nov | O64: Dez
B65: Inspeção | C65: =SUM(C58:C60) -> 1905 | D65: =SUM(D58:D60) -> 2201 | E65: =SUM(E58:E60) -> 2377 | F65: =SUM(F58:F60) -> 2430 | G65: =SUM(G58:G60) -> 2509 | H65: =SUM(H58:H60) -> 2523 | I65: =SUM(I58:I60) -> 2842 | J65: =SUM(J58:J60) -> 3480 | ... L65: =SUM(L58:L60) -> 3637 | N65: 3910 | O65: 3502 | P65: =SUM(C65:O65) -> 34450
B66: Manutenção | C66: =SUM(C61:C62) -> 1168 | D66: =SUM(D61:D62) -> 1404 | E66: =SUM(E61:E62) -> 645 | F66: =SUM(F61:F62) -> 535 | G66: =SUM(G61:G62) -> 521 | H66: =SUM(H61:H62) -> 397 | I66: =SUM(I61:I62) -> 678 | J66: =SUM(J61:J62) -> 880 | ... L66: =SUM(L61:L62) -> 686 | N66: 322 | O66: 571 | P66: =SUM(C66:O66) -> 8375
B67: Engenharia | C67: =C56 -> 0 | D67: =D56 -> 0 | E67: =E56 -> 0 | F67: =F56 -> 0 | G67: =G56 -> 0 | H67: =H56 -> 0 | I67: =I56 -> 0 | J67: =J56 -> 0 | ... L67: =L56 -> 45 | N67: 42 | O67: 84 | P67: =SUM(C67:O67) -> 171
B68: Outros | C68: =C63-C67-C66-C65 -> 0 | D68: =D63-D67-D66-D65 -> 0 | E68: =E63-E67-E66-E65 -> 0 | F68: =F63-F67-F66-F65 -> 0 | G68: =G63-G67-G66-G65 -> 0 | H68: =H63-H67-H66-H65 -> 0 | I68: =I63-I67-I66-I65 -> 0 | J68: =J63-J67-J66-J65 -> 0 | ... L68: =L63-L67-L66-L65 -> 0 | N68: 0 | O68: 0 | P68: =SUM(C68:O68) -> 0
C69: =SUM(C65:C68) -> 3073 | D69: =SUM(D65:D68) -> 3605 | E69: =SUM(E65:E68) -> 3022 | F69: =SUM(F65:F68) -> 2965 | G69: =SUM(G65:G68) -> 3030 | H69: =SUM(H65:H68) -> 2920 | I69: =SUM(I65:I68) -> 3520 | J69: =SUM(J65:J68) -> 4360 | ... L69: =SUM(L65:L68) -> 4368 | N69: =SUM(N65:N68) -> 4274 | O69: =SUM(O65:O68) -> 4157
B71: Total Daily | C71: (Tudo)
B72: Contract Category | C72: (Tudo)
B74: Soma de Total Daily | C74: Rótulos de Coluna
B75: Rótulos de Linha | C75: 45658 | D75: 45689 | E75: 45717 | F75: 45748 | G75: 45778 | H75: 45809 | I75: 45839 | J75: 45870 | K75: 45901 | L75: 45931 | M75: Total Geral
B76: Akofs Offshore | F76: 3 | G76: 151 | I76: 30 | J76: 15 | K76: 70 | L76: 6 | M76: 275
B77: Ambipar | I77: 7 | J77: 0 | M77: 7
B78: Archer | C78: 91 | D78: 121 | E78: 310 | F78: 55 | G78: 270 | H78: 166 | I78: 158 | J78: 127 | K78: 5 | L78: 96 | M78: 1399
B79: Constellation | C79: 352 | D79: 232 | E79: 276 | F79: 271 | G79: 315 | H79: 304 | I79: 472 | J79: 1159 | K79: 760 | L79: 453 | M79: 4594
B80: Equinor | C80: 0 | M80: 0
B81: Etesco | C81: 262 | D81: 702 | E81: 343 | F81: 316 | G81: 171 | H81: 171 | I81: 214 | J81: 215 | K81: 155 | L81: 109 | M81: 2658
B82: Foresea | C82: 574 | D82: 332 | E82: 430 | F82: 394 | G82: 439 | H82: 301 | I82: 423 | J82: 390 | K82: 363 | L82: 365 | M82: 4011
B83: Fugro | D83: 9 | M83: 9
B84: GranServices | E84: 0 | M84: 0
B85: Haleon | C85: 4 | F85: 4 | G85: -1 | M85: 7
B86: Halliburton | C86: 3 | D86: 3 | J86: 3 | M86: 9
B87: Helix | C87: 222 | D87: 749 | E87: 159 | F87: 91 | G87: 109 | H87: 93 | I87: 114 | J87: 151 | K87: 258 | L87: 892 | M87: 2838
B88: Modec | C88: 30 | D88: 126 | E88: 98 | F88: 212 | G88: 181 | H88: 246 | I88: 317 | J88: 173 | K88: 202 | L88: 165 | M88: 1750
B89: Oceaneering | C89: 1 | D89: 17 | E89: 4 | F89: 4 | G89: 2 | H89: 4 | I89: 10 | J89: 1 | K89: 10 | L89: 3 | M89: 56
B90: Petrobrás | K90: 27 | L90: 60 | M90: 87
B91: PRIO | E91: 4 | F91: 11 | H91: 0 | L91: 159 | M91: 174
B92: Prosafe | J92: 39 | K92: 45 | L92: 0 | M92: 84
B93: Qualitech Por | H93: 2 | I93: 46 | K93: 0 | M93: 48
B94: Qualitech USA | C94: 30 | D94: 91 | E94: 56 | F94: 0 | M94: 177
B95: SBM | C95: 29 | D95: 26 | E95: 86 | F95: -2 | G95: 0 | M95: 139
B96: SEA1 | C96: 80 | D96: 0 | E96: 24 | F96: 37 | G96: 88 | H96: 36 | I96: 72 | J96: 98 | K96: 18 | L96: 150 | M96: 603
B97: Seadrill | C97: 364 | D97: 343 | E97: 262 | F97: 295 | G97: 463 | H97: 625 | I97: 522 | J97: 516 | K97: 363 | L97: 321 | M97: 4074
B98: Seagems | G98: 0 | M98: 0
B99: SLB | C99: 244 | D99: 13 | E99: 10 | F99: 16 | G99: 0 | H99: 12 | I99: 4 | J99: 287 | K99: 1 | M99: 587
B100: Solstad | J100: 9 | K100: 0 | M100: 9
B101: Subsea 7 | D101: 6 | E101: 3 | K101: 6 | L101: 12 | M101: 27
B102: Technip | C102: 12 | D102: 2 | E102: 18 | F102: 210 | G102: 38 | H102: 4 | I102: 12 | K102: 8 | L102: 172 | M102: 476
B103: Transocean | C103: 626 | D103: 671 | E103: 724 | F103: 849 | G103: 654 | H103: 739 | I103: 745 | J103: 740 | K103: 1103 | L103: 1014 | M103: 7865
B104: Trident | G104: 13 | I104: 61 | M104: 74
B105: Valaris | E105: 2 | F105: 84 | G105: -28 | M105: 58
B106: Ventura | C106: 149 | D106: 162 | E106: 213 | F106: 115 | G106: 165 | H106: 217 | I106: 313 | J106: 434 | K106: 308 | L106: 391 | M106: 2467
B107: Weatherford | J107: 3 | K107: 0 | M107: 3
B108: Total Geral | C108: 3073 | D108: 3605 | E108: 3022 | F108: 2965 | G108: 3030 | H108: 2920 | I108: 3520 | J108: 4360 | K108: 3702 | L108: 4368 | M108: 34565
B110: Total Daily | C110: (Tudo)
B111: Contract Category | C111: (Tudo)
B113: Soma de Total | C113: Rótulos de Coluna
B114: Rótulos de Linha | C114: 45658 | D114: 45689 | E114: 45717 | F114: 45748 | G114: 45778 | H114: 45809 | I114: 45839 | J114: 45870 | K114: 45901 | L114: 45931 | M114: Total Geral | N114: 1Q | O114: 2Q | P114: 3Q
A115: Others | B115: Akofs Offshore | F115: 12544.9 | G115: 637580.39 | I115: 102121.39 | J115: 67030.9 | K115: 288264.52 | L115: 32903.18 | M115: 1140445.3 | N115: =SUM(C115:E115) -> 0 | O115: =SUM(F115:H115) -> 650125.29 | P115: =SUM(I115:K115) -> 457416.81
A116: Others | B116: Ambipar | I116: 17118.54 | J116: 8389.9 | M116: 25508.44 | N116: =SUM(C116:E116) -> 0 | O116: =SUM(F116:H116) -> 0 | P116: =SUM(I116:K116) -> 25508.44
A117: Equinor | B117: Archer | C117: 363485.9 | D117: 467390.71 | E117: 1023387.3 | F117: 379535.43 | G117: 984814.04 | H117: 786092.73 | I117: 760854.52 | J117: 412753.3 | K117: 97503.5 | L117: 391872.41 | M117: 5667689.8 | N117: =SUM(C117:E117) -> 1854263.9 | O117: =SUM(F117:H117) -> 2150442.2 | P117: =SUM(I117:K117) -> 1271111.3
...

Sheet Comparação
B1: 46023 | C1: Daily | D1: R$ | E1: TM | F1: 46054 | G1: Daily | H1: R$ | I1: TM | J1: 46082 | K1: Daily | L1: R$ | M1: TM | N1: 46113 | O1: Daily | P1: R$ | Q1: TM | R1: 46143 | S1: Daily | T1: R$ | U1: TM | V1: 46174 | W1: Daily | X1: R$ | Y1: TM | Z1: 46204 | AA1: Daily | AB1: R$ | AC1: TM | AD1: 46235 | AE1: Daily | AF1: R$ | AG1: TM | AH1: 46266 | AI1: Daily | AJ1: R$ | AK1: TM | AL1: 46296 | AM1: Daily | AN1: R$ | AO1: TM | AP1: 46327 | AQ1: Daily | AR1: R$ | AS1: TM | AT1: 46357 | AU1: Daily | AV1: R$ | AW1: TM | AZ1: Q1.2026 | BA1: Q2.2026 | BB1: 45839 | BC1: %
B2: Inspection Contract - Fixed Team | C2: =SUMIFS(Input!$AA:$AA,Input!$A:$A,Comparação!B1,Input!$E:$E,Comparação!B2) -> 1448 | D2: =SUMIFS(Input!$K:$K,Input!$A:$A,Comparação!B1,Input!$E:$E,Comparação!B2) -> 2999216.4 | E2: =D2/C2 -> 2071.282 | F2: Inspection Contract - Fixed Team | G2: =SUMIFS(Input!$AA:$AA,Input!$A:$A,Comparação!F1,Input!$E:$E,Comparação!F2) -> 1301 | H2: =SUMIFS(Input!$K:$K,Input!$A:$A,Comparação!F1,Input!$E:$E,Comparação!F2) -> 2869507.2 | I2: =H2/G2 -> 2205.6166 | J2: Inspection Contract - Fixed Team | K2: =SUMIFS(Input!$AA:$AA,Input!$A:$A,Comparação!J1,Input!$E:$E,Comparação!J2) -> 1470 | L2: =SUMIFS(Input!$K:$K,Input!$A:$A,Comparação!J1,Input!$E:$E,Comparação!J2) -> 3000090.2 | M2: =L2/K2 -> 2040.8777 | N2: Inspection Contract - Fixed Team | O2: =SUMIFS(Input!$AA:$AA,Input!$A:$A,Comparação!N1,Input!$E:$E,Comparação!N2) -> 1427 | P2: =SUMIFS(Input!$K:$K,Input!$A:$A,Comparação!N1,Input!$E:$E,Comparação!N2) -> 2998666.3 | Q2: =P2/O2 -> 2101.378 | R2: Inspection Contract - Fixed Team | S2: =SUMIFS(Input!$AA:$AA,Input!$A:$A,Comparação!R1,Input!$E:$E,Comparação!R2) -> 1328 | T2: =SUMIFS(Input!$K:$K,Input!$A:$A,Comparação!R1,Input!$E:$E,Comparação!R2) -> 2751373.6 | U2: =T2/S2 -> 2071.8175 | V2: Inspection Contract - Fixed Team | W2: =SUMIFS(Input!$AA:$AA,Input!$A:$A,Comparação!V1,Input!$E:$E,Comparação!V2) -> 117 | X2: =SUMIFS(Input!$K:$K,Input!$A:$A,Comparação!V1,Input!$E:$E,Comparação!V2) -> 146563.82 | Y2: =X2/W2 -> 1252.6822 | Z2: Inspection Contract - Fixed Team | AA2: =SUMIFS(Input!$AA:$AA,Input!$A:$A,Comparação!Z1,Input!$E:$E,Comparação!Z2) -> 0 | AB2: =SUMIFS(Input!$K:$K,Input!$A:$A,Comparação!Z1,Input!$E:$E,Comparação!Z2) -> 0 | AC2: =AB2/AA2 -> #DIV/0! | AD2: Inspection Contract - Fixed Team | AE2: =SUMIFS(Input!$AA:$AA,Input!$A:$A,Comparação!AD1,Input!$E:$E,Comparação!AD2) -> 0 | AF2: =SUMIFS(Input!$K:$K,Input!$A:$A,Comparação!AD1,Input!$E:$E,Comparação!AD2) -> 0 | AG2: =AF2/AE2 -> #DIV/0! | AH2: Inspection Contract - Fixed Team | AI2: =SUMIFS(Input!$AA:$AA,Input!$A:$A,Comparação!AH1,Input!$E:$E,Comparação!AH2) -> 0 | AJ2: =SUMIFS(Input!$K:$K,Input!$A:$A,Comparação!AH1,Input!$E:$E,Comparação!AH2) -> 0 | AK2: =AJ2/AI2 -> #DIV/0! | AL2: Inspection Contract - Fixed Team | AM2: =SUMIFS(Input!$AA:$AA,Input!$A:$A,Comparação!AL1,Input!$E:$E,Comparação!AL2) -> 0 | AN2: =SUMIFS(Input!$K:$K,Input!$A:$A,Comparação!AL1,Input!$E:$E,Comparação!AL2) -> 0 | AO2: =AN2/AM2 -> #DIV/0! | AP2: Inspection Contract - Fixed Team | AQ2: =SUMIFS(Input!$AA:$AA,Input!$A:$A,Comparação!AP1,Input!$E:$E,Comparação!AP2) -> 0 | AR2: =SUMIFS(Input!$K:$K,Input!$A:$A,Comparação!AP1,Input!$E:$E,Comparação!AP2) -> 0 | AS2: =AR2/AQ2 -> #DIV/0! | AT2: Inspection Contract - Fixed Team | AU2: =SUMIFS(Input!$AA:$AA,Input!$A:$A,Comparação!AT1,Input!$E:$E,Comparação!AT2) -> 0 | AV2: =SUMIFS(Input!$K:$K,Input!$A:$A,Comparação!AT1,Input!$E:$E,Comparação!AT2) -> 0 | AW2: =AV2/AU2 -> #DIV/0! | AY2: Inspection Contract - Fixed Team | AZ2: =AVERAGE(E2,I2,M2) -> 2105.9254 | BA2: =AVERAGE(Q2,U2,Y2) -> 1808.6259 | BB2: =AC2 -> #DIV/0! | BC2: =BB2/AVERAGE(AZ2:BA2) -> #DIV/0!
B3: GranServices | C3: =SUMIFS(Input!$AA:$AA,Input!$A:$A,Comparação!$B$1,Input!$E:$E,Comparação!B2,Input!$F:$F,Comparação!B3) -> 0 | D3: =SUMIFS(Input!$K:$K,Input!$A:$A,Comparação!$B$1,Input!$E:$E,Comparação!$B$2,Input!$F:$F,Comparação!B3) -> 0 | F3: GranServices | G3: =SUMIFS(Input!$AA:$AA,Input!$A:$A,F1,Input!$E:$E,Comparação!F2,Input!$F:$F,Comparação!F3) -> 0 | H3: =SUMIFS(Input!$K:$K,Input!$A:$A,F1,Input!$E:$E,F2,Input!$F:$F,Comparação!F3) -> 0 | J3: GranServices | K3: =SUMIFS(Input!$AA:$AA,Input!$A:$A,$J$1,Input!$E:$E,Comparação!$J$2,Input!$F:$F,Comparação!J3) -> 0 | L3: =SUMIFS(Input!$K:$K,Input!$A:$A,$J$1,Input!$E:$E,$J$2,Input!$F:$F,Comparação!J3) -> 0 | M3: =IF(L3=0,"",L3/K3) | N3: GranServices | O3: =SUMIFS(Input!$AA:$AA,Input!$A:$A,$N$1,Input!$E:$E,Comparação!$N$2,Input!$F:$F,Comparação!N3) -> 0 | P3: =SUMIFS(Input!$K:$K,Input!$A:$A,$N$1,Input!$E:$E,$N$2,Input!$F:$F,Comparação!N3) -> 0 | Q3: =IF(P3=0,"",P3/O3) | R3: GranServices | S3: =SUMIFS(Input!$AA:$AA,Input!$A:$A,$R$1,Input!$E:$E,Comparação!$R$2,Input!$F:$F,Comparação!R3) -> 0 | T3: =SUMIFS(Input!$K:$K,Input!$A:$A,$R$1,Input!$E:$E,$R$2,Input!$F:$F,Comparação!R3) -> 0 | U3: =IF(T3=0,"",T3/S3) | V3: GranServices | W3: =SUMIFS(Input!$AA:$AA,Input!$A:$A,V1,Input!$E:$E,Comparação!V2,Input!$F:$F,Comparação!V3) -> 0 | X3: =SUMIFS(Input!$K:$K,Input!$A:$A,V1,Input!$E:$E,V2,Input!$F:$F,Comparação!V3) -> 0 | Y3: =IF(X3=0,"",X3/W3) | Z3: GranServices | AA3: =SUMIFS(Input!$AA:$AA,Input!$A:$A,Z1,Input!$E:$E,Comparação!Z2,Input!$F:$F,Comparação!Z3) -> 0 | AB3: =SUMIFS(Input!$K:$K,Input!$A:$A,Z1,Input!$E:$E,Z2,Input!$F:$F,Comparação!Z3) -> 0 | AC3: =IF(AB3=0,"",AB3/AA3) | AD3: GranServices | AE3: =SUMIFS(Input!$AA:$AA,Input!$A:$A,AD1,Input!$E:$E,Comparação!AD2,Input!$F:$F,Comparação!AD3) -> 0 | AF3: =SUMIFS(Input!$K:$K,Input!$A:$A,AD1,Input!$E:$E,AD2,Input!$F:$F,Comparação!AD3) -> 0 | AG3: =IF(AF3=0,"",AF3/AE3) | AH3: GranServices | AI3: =SUMIFS(Input!$AA:$AA,Input!$A:$A,AH1,Input!$E:$E,Comparação!AH2,Input!$F:$F,Comparação!AH3) -> 0 | AJ3: =SUMIFS(Input!$K:$K,Input!$A:$A,AH1,Input!$E:$E,AH2,Input!$F:$F,Comparação!AH3) -> 0 | AK3: =IF(AJ3=0,"",AJ3/AI3) | AL3: GranServices | AM3: =SUMIFS(Input!$AA:$AA,Input!$A:$A,AL1,Input!$E:$E,Comparação!AL2,Input!$F:$F,Comparação!AL3) -> 0 | AN3: =SUMIFS(Input!$K:$K,Input!$A:$A,AL1,Input!$E:$E,AL2,Input!$F:$F,Comparação!AL3) -> 0 | AO3: =IF(AN3=0,"",AN3/AM3) | AP3: GranServices | AQ3: =SUMIFS(Input!$AA:$AA,Input!$A:$A,AP1,Input!$E:$E,Comparação!AP2,Input!$F:$F,Comparação!AP3) -> 0 | AR3: =SUMIFS(Input!$K:$K,Input!$A:$A,AP1,Input!$E:$E,AP2,Input!$F:$F,Comparação!AP3) -> 0 | AS3: =IF(AR3=0,"",AR3/AQ3) | AT3: GranServices | AU3: =SUMIFS(Input!$AA:$AA,Input!$A:$A,AT1,Input!$E:$E,Comparação!AT2,Input!$F:$F,Comparação!AT3) -> 0 | AV3: =SUMIFS(Input!$K:$K,Input!$A:$A,AT1,Input!$E:$E,AT2,Input!$F:$F,Comparação!AT3) -> 0 | AW3: =IF(AV3=0,"",AV3/AU3) | AY3: GranServices
B4: Modec | C4: =SUMIFS(Input!$AA:$AA,Input!$A:$A,Comparação!$B$1,Input!$E:$E,Comparação!$B$2,Input!$F:$F,Comparação!B4) -> 0 | D4: =SUMIFS(Input!$K:$K,Input!$A:$A,Comparação!$B$1,Input!$E:$E,Comparação!$B$2,Input!$F:$F,Comparação!B4) -> 0 | F4: Modec | G4: =SUMIFS(Input!$AA:$AA,Input!$A:$A,$F$1,Input!$E:$E,Comparação!$F$2,Input!$F:$F,Comparação!F4) -> 0 | H4: =SUMIFS(Input!$K:$K,Input!$A:$A,$F$1,Input!$E:$E,$F$2,Input!$F:$F,Comparação!F4) -> 0 | J4: Modec | K4: =SUMIFS(Input!$AA:$AA,Input!$A:$A,$J$1,Input!$E:$E,Comparação!$J$2,Input!$F:$F,Comparação!J4) -> 0 | L4: =SUMIFS(Input!$K:$K,Input!$A:$A,$J$1,Input!$E:$E,$J$2,Input!$F:$F,Comparação!J4) -> 0 | M4: =IF(L4=0,"",L4/K4) | N4: Modec | O4: =SUMIFS(Input!$AA:$AA,Input!$A:$A,$N$1,Input!$E:$E,Comparação!$N$2,Input!$F:$F,Comparação!N4) -> 0 | P4: =SUMIFS(Input!$K:$K,Input!$A:$A,$N$1,Input!$E:$E,$N$2,Input!$F:$F,Comparação!N4) -> 0 | Q4: =IF(P4=0,"",P4/O4) | R4: Modec | S4: =SUMIFS(Input!$AA:$AA,Input!$A:$A,$R$1,Input!$E:$E,Comparação!$R$2,Input!$F:$F,Comparação!R4) -> 0 | T4: =SUMIFS(Input!$K:$K,Input!$A:$A,$R$1,Input!$E:$E,$R$2,Input!$F:$F,Comparação!R4) -> 0 | U4: =IF(T4=0,"",T4/S4) | V4: Modec | W4: =SUMIFS([1]Input!$AC:$AC,[1]Input!$A:$A,[1]Comparação!$V$1,[1]Input!$E:$E,[1]Comparação!$V$2,[1]Input!$F:$F,[1]Comparação!V4) -> #VALUE! | X4: =SUMIFS([1]Input!$M:$M,[1]Input!$A:$A,[1]Comparação!$V$1,[1]Input!$E:$E,[1]Comparação!$V$2,[1]Input!$F:$F,[1]Comparação!V4) -> #VALUE! | Y4: =IF(X4=0,"",X4/W4) -> #VALUE! | Z4: Modec | AA4: =SUMIFS([1]Input!$AC:$AC,[1]Input!$A:$A,[1]Comparação!$Z$1,[1]Input!$E:$E,[1]Comparação!$Z$2,[1]Input!$F:$F,[1]Comparação!Z4) -> #VALUE! | AB4: =SUMIFS([1]Input!$M:$M,[1]Input!$A:$A,[1]Comparação!$Z$1,[1]Input!$E:$E,[1]Comparação!$Z$2,[1]Input!$F:$F,[1]Comparação!Z4) -> #VALUE! | AC4: =IF(AB4=0,"",AB4/AA4) -> #VALUE! | AD4: Modec | AE4: =SUMIFS([1]Input!$AC:$AC,[1]Input!$A:$A,[1]Comparação!$AD$1,[1]Input!$E:$E,[1]Comparação!$AD$2,[1]Input!$F:$F,[1]Comparação!AD4) -> #VALUE! | AF4: =SUMIFS([1]Input!$M:$M,[1]Input!$A:$A,[1]Comparação!$AD$1,[1]Input!$E:$E,[1]Comparação!$AD$2,[1]Input!$F:$F,[1]Comparação!AD4) -> #VALUE! | AG4: =IF(AF4=0,"",AF4/AE4) -> #VALUE! | AH4: Modec | AI4: =SUMIFS([1]Input!$AC:$AC,[1]Input!$A:$A,[1]Comparação!$AH$1,[1]Input!$E:$E,[1]Comparação!$AH$2,[1]Input!$F:$F,[1]Comparação!AH4) -> #VALUE! | AJ4: =SUMIFS([1]Input!$M:$M,[1]Input!$A:$A,[1]Comparação!$AH$1,[1]Input!$E:$E,[1]Comparação!$AH$2,[1]Input!$F:$F,[1]Comparação!AH4) -> #VALUE! | AK4: =IF(AJ4=0,"",AJ4/AI4) -> #VALUE! | AL4: Modec | AM4: =SUMIFS([1]Input!$AC:$AC,[1]Input!$A:$A,[1]Comparação!$AL$1,[1]Input!$E:$E,[1]Comparação!$AL$2,[1]Input!$F:$F,[1]Comparação!AL4) -> #VALUE! | AN4: =SUMIFS([1]Input!$M:$M,[1]Input!$A:$A,[1]Comparação!$AL$1,[1]Input!$E:$E,[1]Comparação!$AL$2,[1]Input!$F:$F,[1]Comparação!AL4) -> #VALUE! | AO4: =IF(AN4=0,"",AN4/AM4) -> #VALUE! | AP4: Modec | AQ4: =SUMIFS([1]Input!$AC:$AC,[1]Input!$A:$A,[1]Comparação!$AP$1,[1]Input!$E:$E,[1]Comparação!$AP$2,[1]Input!$F:$F,[1]Comparação!AP4) -> #VALUE! | AR4: =SUMIFS([1]Input!$M:$M,[1]Input!$A:$A,[1]Comparação!$AP$1,[1]Input!$E:$E,[1]Comparação!$AP$2,[1]Input!$F:$F,[1]Comparação!AP4) -> #VALUE! | AS4: =IF(AR4=0,"",AR4/AQ4) -> #VALUE! | AT4: Modec | AU4: =SUMIFS([1]Input!$AC:$AC,[1]Input!$A:$A,[1]Comparação!$AT$1,[1]Input!$E:$E,[1]Comparação!$AT$2,[1]Input!$F:$F,[1]Comparação!AT4) -> #VALUE! | AV4: =SUMIFS([1]Input!$M:$M,[1]Input!$A:$A,[1]Comparação!$AT$1,[1]Input!$E:$E,[1]Comparação!$AT$2,[1]Input!$F:$F,[1]Comparação!AT4) -> #VALUE! | AW4: =IF(AV4=0,"",AV4/AU4) -> #VALUE! | AY4: Modec
B5: Transocean | C5: =SUMIFS(Input!$AA:$AA,Input!$A:$A,Comparação!$B$1,Input!$E:$E,Comparação!$B$2,Input!$F:$F,Comparação!B5) -> 533 | D5: =SUMIFS(Input!$K:$K,Input!$A:$A,Comparação!$B$1,Input!$E:$E,Comparação!$B$2,Input!$F:$F,Comparação!B5) -> 1187596.7 | E5: =D5/C5 -> 2228.1363 | F5: Transocean | G5: =SUMIFS(Input!$AA:$AA,Input!$A:$A,$F$1,Input!$E:$E,Comparação!$F$2,Input!$F:$F,Comparação!F5) -> 507 | H5: =SUMIFS(Input!$K:$K,Input!$A:$A,$F$1,Input!$E:$E,$F$2,Input!$F:$F,Comparação!F5) -> 1184635.2 | I5: =H5/G5 -> 2336.5586 | J5: Transocean | K5: =SUMIFS(Input!$AA:$AA,Input!$A:$A,$J$1,Input!$E:$E,Comparação!$J$2,Input!$F:$F,Comparação!J5) -> 557 | L5: =SUMIFS(Input!$K:$K,Input!$A:$A,$J$1,Input!$E:$E,$J$2,Input!$F:$F,Comparação!J5) -> 1178042.8 | M5: =IF(L5=0,"",L5/K5) -> 2114.9781 | N5: Transocean | O5: =SUMIFS(Input!$AA:$AA,Input!$A:$A,$N$1,Input!$E:$E,Comparação!$N$2,Input!$F:$F,Comparação!N5) -> 547 | P5: =SUMIFS(Input!$K:$K,Input!$A:$A,$N$1,Input!$E:$E,$N$2,Input!$F:$F,Comparação!N5) -> 1196923.8 | Q5: =IF(P5=0,"",P5/O5) -> 2188.1606 | R5: Transocean | S5: =SUMIFS(Input!$AA:$AA,Input!$A:$A,$R$1,Input!$E:$E,Comparação!$R$2,Input!$F:$F,Comparação!R5) -> 486 | T5: =SUMIFS(Input!$K:$K,Input!$A:$A,$R$1,Input!$E:$E,$R$2,Input!$F:$F,Comparação!R5) -> 1061018.8 | U5: =IF(T5=0,"",T5/S5) -> 2183.1663 | V5: Transocean | W5: =SUMIFS([1]Input!$AC:$AC,[1]Input!$A:$A,[1]Comparação!$V$1,[1]Input!$E:$E,[1]Comparação!$V$2,[1]Input!$F:$F,[1]Comparação!V5) -> #VALUE! | X5: =SUMIFS([1]Input!$M:$M,[1]Input!$A:$A,[1]Comparação!$V$1,[1]Input!$E:$E,[1]Comparação!$V$2,[1]Input!$F:$F,[1]Comparação!V5) -> #VALUE! | Y5: =IF(X5=0,"",X5/W5) -> #VALUE! | Z5: Transocean | AA5: =SUMIFS([1]Input!$AC:$AC,[1]Input!$A:$A,[1]Comparação!$Z$1,[1]Input!$E:$E,[1]Comparação!$Z$2,[1]Input!$F:$F,[1]Comparação!Z5) -> #VALUE! | AB5: =SUMIFS([1]Input!$M:$M,[1]Input!$A:$A,[1]Comparação!$Z$1,[1]Input!$E:$E,[1]Comparação!$Z$2,[1]Input!$F:$F,[1]Comparação!Z5) -> #VALUE! | AC5: =IF(AB5=0,"",AB5/AA5) -> #VALUE! | AD5: Transocean | AE5: =SUMIFS([1]Input!$AC:$AC,[1]Input!$A:$A,[1]Comparação!$AD$1,[1]Input!$E:$E,[1]Comparação!$AD$2,[1]Input!$F:$F,[1]Comparação!AD5) -> #VALUE! | AF5: =SUMIFS([1]Input!$M:$M,[1]Input!$A:$A,[1]Comparação!$AD$1,[1]Input!$E:$E,[1]Comparação!$AD$2,[1]Input!$F:$F,[1]Comparação!AD5) -> #VALUE! | AG5: =IF(AF5=0,"",AF5/AE5) -> #VALUE! | AH5: Transocean | AI5: =SUMIFS([1]Input!$AC:$AC,[1]Input!$A:$A,[1]Comparação!$AH$1,[1]Input!$E:$E,[1]Comparação!$AH$2,[1]Input!$F:$F,[1]Comparação!AH5) -> #VALUE! | AJ5: =SUMIFS([1]Input!$M:$M,[1]Input!$A:$A,[1]Comparação!$AH$1,[1]Input!$E:$E,[1]Comparação!$AH$2,[1]Input!$F:$F,[1]Comparação!AH5) -> #VALUE! | AK5: =IF(AJ5=0,"",AJ5/AI5) -> #VALUE! | AL5: Transocean | AM5: =SUMIFS([1]Input!$AC:$AC,[1]Input!$A:$A,[1]Comparação!$AL$1,[1]Input!$E:$E,[1]Comparação!$AL$2,[1]Input!$F:$F,[1]Comparação!AL5) -> #VALUE! | AN5: =SUMIFS([1]Input!$M:$M,[1]Input!$A:$A,[1]Comparação!$AL$1,[1]Input!$E:$E,[1]Comparação!$AL$2,[1]Input!$F:$F,[1]Comparação!AL5) -> #VALUE! | AO5: =IF(AN5=0,"",AN5/AM5) -> #VALUE! | AP5: Transocean | AQ5: =SUMIFS([1]Input!$AC:$AC,[1]Input!$A:$A,[1]Comparação!$AP$1,[1]Input!$E:$E,[1]Comparação!$AP$2,[1]Input!$F:$F,[1]Comparação!AP5) -> #VALUE! | AR5: =SUMIFS([1]Input!$M:$M,[1]Input!$A:$A,[1]Comparação!$AP$1,[1]Input!$E:$E,[1]Comparação!$AP$2,[1]Input!$F:$F,[1]Comparação!AP5) -> #VALUE! | AS5: =IF(AR5=0,"",AR5/AQ5) -> #VALUE! | AT5: Transocean | AU5: =SUMIFS([1]Input!$AC:$AC,[1]Input!$A:$A,[1]Comparação!$AT$1,[1]Input!$E:$E,[1]Comparação!$AT$2,[1]Input!$F:$F,[1]Comparação!AT5) -> #VALUE! | AV5: =SUMIFS([1]Input!$M:$M,[1]Input!$A:$A,[1]Comparação!$AT$1,[1]Input!$E:$E,[1]Comparação!$AT$2,[1]Input!$F:$F,[1]Comparação!AT5) -> #VALUE! | AW5: =IF(AV5=0,"",AV5/AU5) -> #VALUE! | AY5: Transocean
B6: SBM | C6: =SUMIFS(Input!$AA:$AA,Input!$A:$A,Comparação!$B$1,Input!$E:$E,Comparação!$B$2,Input!$F:$F,Comparação!B6) -> 0 | D6: =SUMIFS(Input!$K:$K,Input!$A:$A,Comparação!$B$1,Input!$E:$E,Comparação!$B$2,Input!$F:$F,Comparação!B6) -> 0 | F6: SBM | G6: =SUMIFS(Input!$AA:$AA,Input!$A:$A,$F$1,Input!$E:$E,Comparação!$F$2,Input!$F:$F,Comparação!F6) -> 0 | H6: =SUMIFS(Input!$K:$K,Input!$A:$A,$F$1,Input!$E:$E,$F$2,Input!$F:$F,Comparação!F6) -> 0 | J6: SBM | K6: =SUMIFS(Input!$AA:$AA,Input!$A:$A,$J$1,Input!$E:$E,Comparação!$J$2,Input!$F:$F,Comparação!J6) -> 0 | L6: =SUMIFS(Input!$K:$K,Input!$A:$A,$J$1,Input!$E:$E,$J$2,Input!$F:$F,Comparação!J6) -> 0 | M6: =IF(L6=0,"",L6/K6) | N6: SBM | O6: =SUMIFS(Input!$AA:$AA,Input!$A:$A,$N$1,Input!$E:$E,Comparação!$N$2,Input!$F:$F,Comparação!N6) -> 0 | P6: =SUMIFS(Input!$K:$K,Input!$A:$A,$N$1,Input!$E:$E,$N$2,Input!$F:$F,Comparação!N6) -> 0 | Q6: =IF(P6=0,"",P6/O6) | R6: SBM | S6: =SUMIFS(Input!$AA:$AA,Input!$A:$A,$R$1,Input!$E:$E,Comparação!$R$2,Input!$F:$F,Comparação!R6) -> 0 | T6: =SUMIFS(Input!$K:$K,Input!$A:$A,$R$1,Input!$E:$E,$R$2,Input!$F:$F,Comparação!R6) -> 0 | U6: =IF(T6=0,"",T6/S6) | V6: SBM | W6: =SUMIFS([1]Input!$AC:$AC,[1]Input!$A:$A,[1]Comparação!$V$1,[1]Input!$E:$E,[1]Comparação!$V$2,[1]Input!$F:$F,[1]Comparação!V6) -> #VALUE! | X6: =SUMIFS([1]Input!$M:$M,[1]Input!$A:$A,[1]Comparação!$V$1,[1]Input!$E:$E,[1]Comparação!$V$2,[1]Input!$F:$F,[1]Comparação!V6) -> #VALUE! | Y6: =IF(X6=0,"",X6/W6) -> #VALUE! | Z6: SBM | AA6: =SUMIFS([1]Input!$AC:$AC,[1]Input!$A:$A,[1]Comparação!$Z$1,[1]Input!$E:$E,[1]Comparação!$Z$2,[1]Input!$F:$F,[1]Comparação!Z6) -> #VALUE! | AB6: =SUMIFS([1]Input!$M:$M,[1]Input!$A:$A,[1]Comparação!$Z$1,[1]Input!$E:$E,[1]Comparação!$Z$2,[1]Input!$F:$F,[1]Comparação!Z6) -> #VALUE! | AC6: =IF(AB6=0,"",AB6/AA6) -> #VALUE! | AD6: SBM | AE6: =SUMIFS([1]Input!$AC:$AC,[1]Input!$A:$A,[1]Comparação!$AD$1,[1]Input!$E:$E,[1]Comparação!$AD$2,[1]Input!$F:$F,[1]Comparação!AD6) -> #VALUE! | AF6: =SUMIFS([1]Input!$M:$M,[1]Input!$A:$A,[1]Comparação!$AD$1,[1]Input!$E:$E,[1]Comparação!$AD$2,[1]Input!$F:$F,[1]Comparação!AD6) -> #VALUE! | AG6: =IF(AF6=0,"",AF6/AE6) -> #VALUE! | AH6: SBM | AI6: =SUMIFS([1]Input!$AC:$AC,[1]Input!$A:$A,[1]Comparação!$AH$1,[1]Input!$E:$E,[1]Comparação!$AH$2,[1]Input!$F:$F,[1]Comparação!AH6) -> #VALUE! | AJ6: =SUMIFS([1]Input!$M:$M,[1]Input!$A:$A,[1]Comparação!$AH$1,[1]Input!$E:$E,[1]Comparação!$AH$2,[1]Input!$F:$F,[1]Comparação!AH6) -> #VALUE! | AK6: =IF(AJ6=0,"",AJ6/AI6) -> #VALUE! | AL6: SBM | AM6: =SUMIFS([1]Input!$AC:$AC,[1]Input!$A:$A,[1]Comparação!$AL$1,[1]Input!$E:$E,[1]Comparação!$AL$2,[1]Input!$F:$F,[1]Comparação!AL6) -> #VALUE! | AN6: =SUMIFS([1]Input!$M:$M,[1]Input!$A:$A,[1]Comparação!$AL$1,[1]Input!$E:$E,[1]Comparação!$AL$2,[1]Input!$F:$F,[1]Comparação!AL6) -> #VALUE! | AO6: =IF(AN6=0,"",AN6/AM6) -> #VALUE! | AP6: SBM | AQ6: =SUMIFS([1]Input!$AC:$AC,[1]Input!$A:$A,[1]Comparação!$AP$1,[1]Input!$E:$E,[1]Comparação!$AP$2,[1]Input!$F:$F,[1]Comparação!AP6) -> #VALUE! | AR6: =SUMIFS([1]Input!$M:$M,[1]Input!$A:$A,[1]Comparação!$AP$1,[1]Input!$E:$E,[1]Comparação!$AP$2,[1]Input!$F:$F,[1]Comparação!AP6) -> #VALUE! | AS6: =IF(AR6=0,"",AR6/AQ6) -> #VALUE! | AT6: SBM | AU6: =SUMIFS([1]Input!$AC:$AC,[1]Input!$A:$A,[1]Comparação!$AT$1,[1]Input!$E:$E,[1]Comparação!$AT$2,[1]Input!$F:$F,[1]Comparação!AT6) -> #VALUE! | AV6: =SUMIFS([1]Input!$M:$M,[1]Input!$A:$A,[1]Comparação!$AT$1,[1]Input!$E:$E,[1]Comparação!$AT$2,[1]Input!$F:$F,[1]Comparação!AT6) -> #VALUE! | AW6: =IF(AV6=0,"",AV6/AU6) -> #VALUE! | AY6: SBM
B7: Technip | C7: =SUMIFS(Input!$AA:$AA,Input!$A:$A,Comparação!$B$1,Input!$E:$E,Comparação!$B$2,Input!$F:$F,Comparação!B7) -> 0 | D7: =SUMIFS(Input!$K:$K,Input!$A:$A,Comparação!$B$1,Input!$E:$E,Comparação!$B$2,Input!$F:$F,Comparação!B7) -> 0 | F7: Technip | G7: =SUMIFS(Input!$AA:$AA,Input!$A:$A,$F$1,Input!$E:$E,Comparação!$F$2,Input!$F:$F,Comparação!F7) -> 0 | H7: =SUMIFS(Input!$K:$K,Input!$A:$A,$F$1,Input!$E:$E,$F$2,Input!$F:$F,Comparação!F7) -> 0 | J7: Technip | K7: =SUMIFS(Input!$AA:$AA,Input!$A:$A,$J$1,Input!$E:$E,Comparação!$J$2,Input!$F:$F,Comparação!J7) -> 0 | L7: =SUMIFS(Input!$K:$K,Input!$A:$A,$J$1,Input!$E:$E,$J$2,Input!$F:$F,Comparação!J7) -> 0 | M7: =IF(L7=0,"",L7/K7) | N7: Technip | O7: =SUMIFS(Input!$AA:$AA,Input!$A:$A,$N$1,Input!$E:$E,Comparação!$N$2,Input!$F:$F,Comparação!N7) -> 0 | P7: =SUMIFS(Input!$K:$K,Input!$A:$A,$N$1,Input!$E:$E,$N$2,Input!$F:$F,Comparação!N7) -> 0 | Q7: =IF(P7=0,"",P7/O7) | R7: Technip | S7: =SUMIFS(Input!$AA:$AA,Input!$A:$A,$R$1,Input!$E:$E,Comparação!$R$2,Input!$F:$F,Comparação!R7) -> 0 | T7: =SUMIFS(Input!$K:$K,Input!$A:$A,$R$1,Input!$E:$E,$R$2,Input!$F:$F,Comparação!R7) -> 0 | U7: =IF(T7=0,"",T7/S7) | V7: Technip | W7: =SUMIFS([1]Input!$AC:$AC,[1]Input!$A:$A,[1]Comparação!$V$1,[1]Input!$E:$E,[1]Comparação!$V$2,[1]Input!$F:$F,[1]Comparação!V7) -> #VALUE! | X7: =SUMIFS([1]Input!$M:$M,[1]Input!$A:$A,[1]Comparação!$V$1,[1]Input!$E:$E,[1]Comparação!$V$2,[1]Input!$F:$F,[1]Comparação!V7) -> #VALUE! | Y7: =IF(X7=0,"",X7/W7) -> #VALUE! | Z7: Technip | AA7: =SUMIFS([1]Input!$AC:$AC,[1]Input!$A:$A,[1]Comparação!$Z$1,[1]Input!$E:$E,[1]Comparação!$Z$2,[1]Input!$F:$F,[1]Comparação!Z7) -> #VALUE! | AB7: =SUMIFS([1]Input!$M:$M,[1]Input!$A:$A,[1]Comparação!$Z$1,[1]Input!$E:$E,[1]Comparação!$Z$2,[1]Input!$F:$F,[1]Comparação!Z7) -> #VALUE! | AC7: =IF(AB7=0,"",AB7/AA7) -> #VALUE! | AD7: Technip | AE7: =SUMIFS([1]Input!$AC:$AC,[1]Input!$A:$A,[1]Comparação!$AD$1,[1]Input!$E:$E,[1]Comparação!$AD$2,[1]Input!$F:$F,[1]Comparação!AD7) -> #VALUE! | AF7: =SUMIFS([1]Input!$M:$M,[1]Input!$A:$A,[1]Comparação!$AD$1,[1]Input!$E:$E,[1]Comparação!$AD$2,[1]Input!$F:$F,[1]Comparação!AD7) -> #VALUE! | AG7: =IF(AF7=0,"",AF7/AE7) -> #VALUE! | AH7: Technip | AI7: =SUMIFS([1]Input!$AC:$AC,[1]Input!$A:$A,[1]Comparação!$AH$1,[1]Input!$E:$E,[1]Comparação!$AH$2,[1]Input!$F:$F,[1]Comparação!AH7) -> #VALUE! | AJ7: =SUMIFS([1]Input!$M:$M,[1]Input!$A:$A,[1]Comparação!$AH$1,[1]Input!$E:$E,[1]Comparação!$AH$2,[1]Input!$F:$F,[1]Comparação!AH7) -> #VALUE! | AK7: =IF(AJ7=0,"",AJ7/AI7) -> #VALUE! | AL7: Technip | AM7: =SUMIFS([1]Input!$AC:$AC,[1]Input!$A:$A,[1]Comparação!$AL$1,[1]Input!$E:$E,[1]Comparação!$AL$2,[1]Input!$F:$F,[1]Comparação!AL7) -> #VALUE! | AN7: =SUMIFS([1]Input!$M:$M,[1]Input!$A:$A,[1]Comparação!$AL$1,[1]Input!$E:$E,[1]Comparação!$AL$2,[1]Input!$F:$F,[1]Comparação!AL7) -> #VALUE! | AO7: =IF(AN7=0,"",AN7/AM7) -> #VALUE! | AP7: Technip | AQ7: =SUMIFS([1]Input!$AC:$AC,[1]Input!$A:$A,[1]Comparação!$AP$1,[1]Input!$E:$E,[1]Comparação!$AP$2,[1]Input!$F:$F,[1]Comparação!AP7) -> #VALUE! | AR7: =SUMIFS([1]Input!$M:$M,[1]Input!$A:$A,[1]Comparação!$AP$1,[1]Input!$E:$E,[1]Comparação!$AP$2,[1]Input!$F:$F,[1]Comparação!AP7) -> #VALUE! | AS7: =IF(AR7=0,"",AR7/AQ7) -> #VALUE! | AT7: Technip | AU7: =SUMIFS([1]Input!$AC:$AC,[1]Input!$A:$A,[1]Comparação!$AT$1,[1]Input!$E:$E,[1]Comparação!$AT$2,[1]Input!$F:$F,[1]Comparação!AT7) -> #VALUE! | AV7: =SUMIFS([1]Input!$M:$M,[1]Input!$A:$A,[1]Comparação!$AT$1,[1]Input!$E:$E,[1]Comparação!$AT$2,[1]Input!$F:$F,[1]Comparação!AT7) -> #VALUE! | AW7: =IF(AV7=0,"",AV7/AU7) -> #VALUE! | AY7: Technip
B8: Ventura | C8: =SUMIFS(Input!$AA:$AA,Input!$A:$A,Comparação!$B$1,Input!$E:$E,Comparação!$B$2,Input!$F:$F,Comparação!B8) -> 186 | D8: =SUMIFS(Input!$K:$K,Input!$A:$A,Comparação!$B$1,Input!$E:$E,Comparação!$B$2,Input!$F:$F,Comparação!B8) -> 324840 | E8: =D8/C8 -> 1746.4516 | F8: Ventura | G8: =SUMIFS(Input!$AA:$AA,Input!$A:$A,$F$1,Input!$E:$E,Comparação!$F$2,Input!$F:$F,Comparação!F8) -> 120 | H8: =SUMIFS(Input!$K:$K,Input!$A:$A,$F$1,Input!$E:$E,$F$2,Input!$F:$F,Comparação!F8) -> 231520.69 | I8: =H8/G8 -> 1929.3391 | J8: Ventura | K8: =SUMIFS(Input!$AA:$AA,Input!$A:$A,$J$1,Input!$E:$E,Comparação!$J$2,Input!$F:$F,Comparação!J8) -> 140 | L8: =SUMIFS(Input!$K:$K,Input!$A:$A,$J$1,Input!$E:$E,$J$2,Input!$F:$F,Comparação!J8) -> 249763 | M8: =IF(L8=0,"",L8/K8) -> 1784.0214 | N8: Ventura | O8: =SUMIFS(Input!$AA:$AA,Input!$A:$A,$N$1,Input!$E:$E,Comparação!$N$2,Input!$F:$F,Comparação!N8) -> 142 | P8: =SUMIFS(Input!$K:$K,Input!$A:$A,$N$1,Input!$E:$E,$N$2,Input!$F:$F,Comparação!N8) -> 273295 | Q8: =IF(P8=0,"",P8/O8) -> 1924.6127 | R8: Ventura | S8: =SUMIFS(Input!$AA:$AA,Input!$A:$A,$R$1,Input!$E:$E,Comparação!$R$2,Input!$F:$F,Comparação!R8) -> 119 | T8: =SUMIFS(Input!$K:$K,Input!$A:$A,$R$1,Input!$E:$E,$R$2,Input!$F:$F,Comparação!R8) -> 233358 | U8: =IF(T8=0,"",T8/S8) -> 1960.9916 | V8: Ventura | W8: =SUMIFS([1]Input!$AC:$AC,[1]Input!$A:$A,[1]Comparação!$V$1,[1]Input!$E:$E,[1]Comparação!$V$2,[1]Input!$F:$F,[1]Comparação!V8) -> #VALUE! | X8: =SUMIFS([1]Input!$M:$M,[1]Input!$A:$A,[1]Comparação!$V$1,[1]Input!$E:$E,[1]Comparação!$V$2,[1]Input!$F:$F,[1]Comparação!V8) -> #VALUE! | Y8: =IF(X8=0,"",X8/W8) -> #VALUE! | Z8: Ventura | AA8: =SUMIFS([1]Input!$AC:$AC,[1]Input!$A:$A,[1]Comparação!$Z$1,[1]Input!$E:$E,[1]Comparação!$Z$2,[1]Input!$F:$F,[1]Comparação!Z8) -> #VALUE! | AB8: =SUMIFS([1]Input!$M:$M,[1]Input!$A:$A,[1]Comparação!$Z$1,[1]Input!$E:$E,[1]Comparação!$Z$2,[1]Input!$F:$F,[1]Comparação!Z8) -> #VALUE! | AC8: =IF(AB8=0,"",AB8/AA8) -> #VALUE! | AD8: Ventura | AE8: =SUMIFS([1]Input!$AC:$AC,[1]Input!$A:$A,[1]Comparação!$AD$1,[1]Input!$E:$E,[1]Comparação!$AD$2,[1]Input!$F:$F,[1]Comparação!AD8) -> #VALUE! | AF8: =SUMIFS([1]Input!$M:$M,[1]Input!$A:$A,[1]Comparação!$AD$1,[1]Input!$E:$E,[1]Comparação!$AD$2,[1]Input!$F:$F,[1]Comparação!AD8) -> #VALUE! | AG8: =IF(AF8=0,"",AF8/AE8) -> #VALUE! | AH8: Ventura | AI8: =SUMIFS([1]Input!$AC:$AC,[1]Input!$A:$A,[1]Comparação!$AH$1,[1]Input!$E:$E,[1]Comparação!$AH$2,[1]Input!$F:$F,[1]Comparação!AH8) -> #VALUE! | AJ8: =SUMIFS([1]Input!$M:$M,[1]Input!$A:$A,[1]Comparação!$AH$1,[1]Input!$E:$E,[1]Comparação!$AH$2,[1]Input!$F:$F,[1]Comparação!AH8) -> #VALUE! | AK8: =IF(AJ8=0,"",AJ8/AI8) -> #VALUE! | AL8: Ventura | AM8: =SUMIFS([1]Input!$AC:$AC,[1]Input!$A:$A,[1]Comparação!$AL$1,[1]Input!$E:$E,[1]Comparação!$AL$2,[1]Input!$F:$F,[1]Comparação!AL8) -> #VALUE! | AN8: =SUMIFS([1]Input!$M:$M,[1]Input!$A:$A,[1]Comparação!$AL$1,[1]Input!$E:$E,[1]Comparação!$AL$2,[1]Input!$F:$F,[1]Comparação!AL8) -> #VALUE! | AO8: =IF(AN8=0,"",AN8/AM8) -> #VALUE! | AP8: Ventura | AQ8: =SUMIFS([1]Input!$AC:$AC,[1]Input!$A:$A,[1]Comparação!$AP$1,[1]Input!$E:$E,[1]Comparação!$AP$2,[1]Input!$F:$F,[1]Comparação!AP8) -> #VALUE! | AR8: =SUMIFS([1]Input!$M:$M,[1]Input!$A:$A,[1]Comparação!$AP$1,[1]Input!$E:$E,[1]Comparação!$AP$2,[1]Input!$F:$F,[1]Comparação!AP8) -> #VALUE! | AS8: =IF(AR8=0,"",AR8/AQ8) -> #VALUE! | AT8: Ventura | AU8: =SUMIFS([1]Input!$AC:$AC,[1]Input!$A:$A,[1]Comparação!$AT$1,[1]Input!$E:$E,[1]Comparação!$AT$2,[1]Input!$F:$F,[1]Comparação!AT8) -> #VALUE! | AV8: =SUMIFS([1]Input!$M:$M,[1]Input!$A:$A,[1]Comparação!$AT$1,[1]Input!$E:$E,[1]Comparação!$AT$2,[1]Input!$F:$F,[1]Comparação!AT8) -> #VALUE! | AW8: =IF(AV8=0,"",AV8/AU8) -> #VALUE! | AY8: Ventura
B9: Equinor | C9: =SUMIFS(Input!$AA:$AA,Input!$A:$A,Comparação!$B$1,Input!$E:$E,Comparação!$B$2,Input!$F:$F,Comparação!B9) -> 0 | D9: =SUMIFS(Input!$K:$K,Input!$A:$A,Comparação!$B$1,Input!$E:$E,Comparação!$B$2,Input!$F:$F,Comparação!B9) -> 0 | F9: Equinor | G9: =SUMIFS(Input!$AA:$AA,Input!$A:$A,$F$1,Input!$E:$E,Comparação!$F$2,Input!$F:$F,Comparação!F9) -> 0 | H9: =SUMIFS(Input!$K:$K,Input!$A:$A,$F$1,Input!$E:$E,$F$2,Input!$F:$F,Comparação!F9) -> 0 | J9: Equinor | K9: =SUMIFS(Input!$AA:$AA,Input!$A:$A,$J$1,Input!$E:$E,Comparação!$J$2,Input!$F:$F,Comparação!J9) -> 0 | L9: =SUMIFS(Input!$K:$K,Input!$A:$A,$J$1,Input!$E:$E,$J$2,Input!$F:$F,Comparação!J9) -> 0 | M9: =IF(L9=0,"",L9/K9) | N9: Equinor | O9: =SUMIFS(Input!$AA:$AA,Input!$A:$A,$N$1,Input!$E:$E,Comparação!$N$2,Input!$F:$F,Comparação!N9) -> 0 | P9: =SUMIFS(Input!$K:$K,Input!$A:$A,$N$1,Input!$E:$E,$N$2,Input!$F:$F,Comparação!N9) -> 0 | Q9: =IF(P9=0,"",P9/O9) | R9: Equinor | S9: =SUMIFS(Input!$AA:$AA,Input!$A:$A,$R$1,Input!$E:$E,Comparação!$R$2,Input!$F:$F,Comparação!R9) -> 0 | T9: =SUMIFS(Input!$K:$K,Input!$A:$A,$R$1,Input!$E:$E,$R$2,Input!$F:$F,Comparação!R9) -> 0 | U9: =IF(T9=0,"",T9/S9) | V9: Equinor | W9: =SUMIFS([1]Input!$AC:$AC,[1]Input!$A:$A,[1]Comparação!$V$1,[1]Input!$E:$E,[1]Comparação!$V$2,[1]Input!$F:$F,[1]Comparação!V9) -> #VALUE! | X9: =SUMIFS([1]Input!$M:$M,[1]Input!$A:$A,[1]Comparação!$V$1,[1]Input!$E:$E,[1]Comparação!$V$2,[1]Input!$F:$F,[1]Comparação!V9) -> #VALUE! | Y9: =IF(X9=0,"",X9/W9) -> #VALUE! | Z9: Equinor | AA9: =SUMIFS([1]Input!$AC:$AC,[1]Input!$A:$A,[1]Comparação!$Z$1,[1]Input!$E:$E,[1]Comparação!$Z$2,[1]Input!$F:$F,[1]Comparação!Z9) -> #VALUE! | AB9: =SUMIFS([1]Input!$M:$M,[1]Input!$A:$A,[1]Comparação!$Z$1,[1]Input!$E:$E,[1]Comparação!$Z$2,[1]Input!$F:$F,[1]Comparação!Z9) -> #VALUE! | AC9: =IF(AB9=0,"",AB9/AA9) -> #VALUE! | AD9: Equinor | AE9: =SUMIFS([1]Input!$AC:$AC,[1]Input!$A:$A,[1]Comparação!$AD$1,[1]Input!$E:$E,[1]Comparação!$AD$2,[1]Input!$F:$F,[1]Comparação!AD9) -> #VALUE! | AF9: =SUMIFS([1]Input!$M:$M,[1]Input!$A:$A,[1]Comparação!$AD$1,[1]Input!$E:$E,[1]Comparação!$AD$2,[1]Input!$F:$F,[1]Comparação!AD9) -> #VALUE! | AG9: =IF(AF9=0,"",AF9/AE9) -> #VALUE! | AH9: Equinor | AI9: =SUMIFS([1]Input!$AC:$AC,[1]Input!$A:$A,[1]Comparação!$AH$1,[1]Input!$E:$E,[1]Comparação!$AH$2,[1]Input!$F:$F,[1]Comparação!AH9) -> #VALUE! | AJ9: =SUMIFS([1]Input!$M:$M,[1]Input!$A:$A,[1]Comparação!$AH$1,[1]Input!$E:$E,[1]Comparação!$AH$2,[1]Input!$F:$F,[1]Comparação!AH9) -> #VALUE! | AK9: =IF(AJ9=0,"",AJ9/AI9) -> #VALUE! | AL9: Equinor | AM9: =SUMIFS([1]Input!$AC:$AC,[1]Input!$A:$A,[1]Comparação!$AL$1,[1]Input!$E:$E,[1]Comparação!$AL$2,[1]Input!$F:$F,[1]Comparação!AL9) -> #VALUE! | AN9: =SUMIFS([1]Input!$M:$M,[1]Input!$A:$A,[1]Comparação!$AL$1,[1]Input!$E:$E,[1]Comparação!$AL$2,[1]Input!$F:$F,[1]Comparação!AL9) -> #VALUE! | AO9: =IF(AN9=0,"",AN9/AM9) -> #VALUE! | AP9: Equinor | AQ9: =SUMIFS([1]Input!$AC:$AC,[1]Input!$A:$A,[1]Comparação!$AP$1,[1]Input!$E:$E,[1]Comparação!$AP$2,[1]Input!$F:$F,[1]Comparação!AP9) -> #VALUE! | AR9: =SUMIFS([1]Input!$M:$M,[1]Input!$A:$A,[1]Comparação!$AP$1,[1]Input!$E:$E,[1]Comparação!$AP$2,[1]Input!$F:$F,[1]Comparação!AP9) -> #VALUE! | AS9: =IF(AR9=0,"",AR9/AQ9) -> #VALUE! | AT9: Equinor | AU9: =SUMIFS([1]Input!$AC:$AC,[1]Input!$A:$A,[1]Comparação!$AT$1,[1]Input!$E:$E,[1]Comparação!$AT$2,[1]Input!$F:$F,[1]Comparação!AT9) -> #VALUE! | AV9: =SUMIFS([1]Input!$M:$M,[1]Input!$A:$A,[1]Comparação!$AT$1,[1]Input!$E:$E,[1]Comparação!$AT$2,[1]Input!$F:$F,[1]Comparação!AT9) -> #VALUE! | AW9: =IF(AV9=0,"",AV9/AU9) -> #VALUE! | AY9: Equinor
B10: Helix | C10: =SUMIFS(Input!$AA:$AA,Input!$A:$A,Comparação!$B$1,Input!$E:$E,Comparação!$B$2,Input!$F:$F,Comparação!B10) -> 89 | D10: =SUMIFS(Input!$K:$K,Input!$A:$A,Comparação!$B$1,Input!$E:$E,Comparação!$B$2,Input!$F:$F,Comparação!B10) -> 198472.77 | E10: =D10/C10 -> 2230.0311 | F10: Helix | G10: =SUMIFS(Input!$AA:$AA,Input!$A:$A,$F$1,Input!$E:$E,Comparação!$F$2,Input!$F:$F,Comparação!F10) -> 86 | H10: =SUMIFS(Input!$K:$K,Input!$A:$A,$F$1,Input!$E:$E,$F$2,Input!$F:$F,Comparação!F10) -> 189159.77 | I10: =H10/G10 -> 2199.5322 | J10: Helix | K10: =SUMIFS(Input!$AA:$AA,Input!$A:$A,$J$1,Input!$E:$E,Comparação!$J$2,Input!$F:$F,Comparação!J10) -> 102 | L10: =SUMIFS(Input!$K:$K,Input!$A:$A,$J$1,Input!$E:$E,$J$2,Input!$F:$F,Comparação!J10) -> 226458.84 | M10: =IF(L10=0,"",L10/K10) -> 2220.1847 | N10: Helix | O10: =SUMIFS(Input!$AA:$AA,Input!$A:$A,$N$1,Input!$E:$E,Comparação!$N$2,Input!$F:$F,Comparação!N10) -> 101 | P10: =SUMIFS(Input!$K:$K,Input!$A:$A,$N$1,Input!$E:$E,$N$2,Input!$F:$F,Comparação!N10) -> 229702.12 | Q10: =IF(P10=0,"",P10/O10) -> 2274.2784 | R10: Helix | S10: =SUMIFS(Input!$AA:$AA,Input!$A:$A,$R$1,Input!$E:$E,Comparação!$R$2,Input!$F:$F,Comparação!R10) -> 96 | T10: =SUMIFS(Input!$K:$K,Input!$A:$A,$R$1,Input!$E:$E,$R$2,Input!$F:$F,Comparação!R10) -> 229113.92 | U10: =IF(T10=0,"",T10/S10) -> 2386.6033 | V10: Helix | W10: =SUMIFS([1]Input!$AC:$AC,[1]Input!$A:$A,[1]Comparação!$V$1,[1]Input!$E:$E,[1]Comparação!$V$2,[1]Input!$F:$F,[1]Comparação!V10) -> #VALUE! | X10: =SUMIFS([1]Input!$M:$M,[1]Input!$A:$A,[1]Comparação!$V$1,[1]Input!$E:$E,[1]Comparação!$V$2,[1]Input!$F:$F,[1]Comparação!V10) -> #VALUE! | Y10: =IF(X10=0,"",X10/W10) -> #VALUE! | Z10: Helix | AA10: =SUMIFS([1]Input!$AC:$AC,[1]Input!$A:$A,[1]Comparação!$Z$1,[1]Input!$E:$E,[1]Comparação!$Z$2,[1]Input!$F:$F,[1]Comparação!Z10) -> #VALUE! | AB10: =SUMIFS([1]Input!$M:$M,[1]Input!$A:$A,[1]Comparação!$Z$1,[1]Input!$E:$E,[1]Comparação!$Z$2,[1]Input!$F:$F,[1]Comparação!Z10) -> #VALUE! | AC10: =IF(AB10=0,"",AB10/AA10) -> #VALUE! | AD10: Helix | AE10: =SUMIFS([1]Input!$AC:$AC,[1]Input!$A:$A,[1]Comparação!$AD$1,[1]Input!$E:$E,[1]Comparação!$AD$2,[1]Input!$F:$F,[1]Comparação!AD10) -> #VALUE! | AF10: =SUMIFS([1]Input!$M:$M,[1]Input!$A:$A,[1]Comparação!$AD$1,[1]Input!$E:$E,[1]Comparação!$AD$2,[1]Input!$F:$F,[1]Comparação!AD10) -> #VALUE! | AG10: =IF(AF10=0,"",AF10/AE10) -> #VALUE! | AH10: Helix | AI10: =SUMIFS([1]Input!$AC:$AC,[1]Input!$A:$A,[1]Comparação!$AH$1,[1]Input!$E:$E,[1]Comparação!$AH$2,[1]Input!$F:$F,[1]Comparação!AH10) -> #VALUE! | AJ10: =SUMIFS([1]Input!$M:$M,[1]Input!$A:$A,[1]Comparação!$AH$1,[1]Input!$E:$E,[1]Comparação!$AH$2,[1]Input!$F:$F,[1]Comparação!AH10) -> #VALUE! | AK10: =IF(AJ10=0,"",AJ10/AI10) -> #VALUE! | AL10: Helix | AM10: =SUMIFS([1]Input!$AC:$AC,[1]Input!$A:$A,[1]Comparação!$AL$1,[1]Input!$E:$E,[1]Comparação!$AL$2,[1]Input!$F:$F,[1]Comparação!AL10) -> #VALUE! | AN10: =SUMIFS([1]Input!$M:$M,[1]Input!$A:$A,[1]Comparação!$AL$1,[1]Input!$E:$E,[1]Comparação!$AL$2,[1]Input!$F:$F,[1]Comparação!AL10) -> #VALUE! | AO10: =IF(AN10=0,"",AN10/AM10) -> #VALUE! | AP10: Helix | AQ10: =SUMIFS([1]Input!$AC:$AC,[1]Input!$A:$A,[1]Comparação!$AP$1,[1]Input!$E:$E,[1]Comparação!$AP$2,[1]Input!$F:$F,[1]Comparação!AP10) -> #VALUE! | AR10: =SUMIFS([1]Input!$M:$M,[1]Input!$A:$A,[1]Comparação!$AP$1,[1]Input!$E:$E,[1]Comparação!$AP$2,[1]Input!$F:$F,[1]Comparação!AP10) -> #VALUE! | AS10: =IF(AR10=0,"",AR10/AQ10) -> #VALUE! | AT10: Helix | AU10: =SUMIFS([1]Input!$AC:$AC,[1]Input!$A:$A,[1]Comparação!$AT$1,[1]Input!$E:$E,[1]Comparação!$AT$2,[1]Input!$F:$F,[1]Comparação!AT10) -> #VALUE! | AV10: =SUMIFS([1]Input!$M:$M,[1]Input!$A:$A,[1]Comparação!$AT$1,[1]Input!$E:$E,[1]Comparação!$AT$2,[1]Input!$F:$F,[1]Comparação!AT10) -> #VALUE! | AW10: =IF(AV10=0,"",AV10/AU10) -> #VALUE! | AY10: Helix
B11: Foresea | C11: =SUMIFS(Input!$AA:$AA,Input!$A:$A,Comparação!$B$1,Input!$E:$E,Comparação!$B$2,Input!$F:$F,Comparação!B11) -> 279 | D11: =SUMIFS(Input!$K:$K,Input!$A:$A,Comparação!$B$1,Input!$E:$E,Comparação!$B$2,Input!$F:$F,Comparação!B11) -> 522790.33 | E11: =D11/C11 -> 1873.8005 | F11: Foresea | G11: =SUMIFS(Input!$AA:$AA,Input!$A:$A,$F$1,Input!$E:$E,Comparação!$F$2,Input!$F:$F,Comparação!F11) -> 254 | H11: =SUMIFS(Input!$K:$K,Input!$A:$A,$F$1,Input!$E:$E,$F$2,Input!$F:$F,Comparação!F11) -> 521342.16 | I11: =H11/G11 -> 2052.5282 | J11: Foresea | K11: =SUMIFS(Input!$AA:$AA,Input!$A:$A,$J$1,Input!$E:$E,Comparação!$J$2,Input!$F:$F,Comparação!J11) -> 281 | L11: =SUMIFS(Input!$K:$K,Input!$A:$A,$J$1,Input!$E:$E,$J$2,Input!$F:$F,Comparação!J11) -> 530031.16 | M11: =IF(L11=0,"",L11/K11) -> 1886.2319 | N11: Foresea | O11: =SUMIFS(Input!$AA:$AA,Input!$A:$A,$N$1,Input!$E:$E,Comparação!$N$2,Input!$F:$F,Comparação!N11) -> 270 | P11: =SUMIFS(Input!$K:$K,Input!$A:$A,$N$1,Input!$E:$E,$N$2,Input!$F:$F,Comparação!N11) -> 521342.12 | Q11: =IF(P11=0,"",P11/O11) -> 1930.8967 | R11: Foresea | S11: =SUMIFS(Input!$AA:$AA,Input!$A:$A,$R$1,Input!$E:$E,Comparação!$R$2,Input!$F:$F,Comparação!R11) -> 279 | T11: =SUMIFS(Input!$K:$K,Input!$A:$A,$R$1,Input!$E:$E,$R$2,Input!$F:$F,Comparação!R11) -> 521342.16 | U11: =IF(T11=0,"",T11/S11) -> 1868.6099 | V11: Foresea | W11: =SUMIFS([1]Input!$AC:$AC,[1]Input!$A:$A,[1]Comparação!$V$1,[1]Input!$E:$E,[1]Comparação!$V$2,[1]Input!$F:$F,[1]Comparação!V11) -> #VALUE! | X11: =SUMIFS([1]Input!$M:$M,[1]Input!$A:$A,[1]Comparação!$V$1,[1]Input!$E:$E,[1]Comparação!$V$2,[1]Input!$F:$F,[1]Comparação!V11) -> #VALUE! | Y11: =IF(X11=0,"",X11/W11) -> #VALUE! | Z11: Foresea | AA11: =SUMIFS([1]Input!$AC:$AC,[1]Input!$A:$A,[1]Comparação!$Z$1,[1]Input!$E:$E,[1]Comparação!$Z$2,[1]Input!$F:$F,[1]Comparação!Z11) -> #VALUE! | AB11: =SUMIFS([1]Input!$M:$M,[1]Input!$A:$A,[1]Comparação!$Z$1,[1]Input!$E:$E,[1]Comparação!$Z$2,[1]Input!$F:$F,[1]Comparação!Z11) -> #VALUE! | AC11: =IF(AB11=0,"",AB11/AA11) -> #VALUE! | AD11: Foresea | AE11: =SUMIFS([1]Input!$AC:$AC,[1]Input!$A:$A,[1]Comparação!$AD$1,[1]Input!$E:$E,[1]Comparação!$AD$2,[1]Input!$F:$F,[1]Comparação!AD11) -> #VALUE! | AF11: =SUMIFS([1]Input!$M:$M,[1]Input!$A:$A,[1]Comparação!$AD$1,[1]Input!$E:$E,[1]Comparação!$AD$2,[1]Input!$F:$F,[1]Comparação!AD11) -> #VALUE! | AG11: =IF(AF11=0,"",AF11/AE11) -> #VALUE! | AH11: Foresea | AI11: =SUMIFS([1]Input!$AC:$AC,[1]Input!$A:$A,[1]Comparação!$AH$1,[1]Input!$E:$E,[1]Comparação!$AH$2,[1]Input!$F:$F,[1]Comparação!AH11) -> #VALUE! | AJ11: =SUMIFS([1]Input!$M:$M,[1]Input!$A:$A,[1]Comparação!$AH$1,[1]Input!$E:$E,[1]Comparação!$AH$2,[1]Input!$F:$F,[1]Comparação!AH11) -> #VALUE! | AK11: =IF(AJ11=0,"",AJ11/AI11) -> #VALUE! | AL11: Foresea | AM11: =SUMIFS([1]Input!$AC:$AC,[1]Input!$A:$A,[1]Comparação!$AL$1,[1]Input!$E:$E,[1]Comparação!$AL$2,[1]Input!$F:$F,[1]Comparação!AL11) -> #VALUE! | AN11: =SUMIFS([1]Input!$M:$M,[1]Input!$A:$A,[1]Comparação!$AL$1,[1]Input!$E:$E,[1]Comparação!$AL$2,[1]Input!$F:$F,[1]Comparação!AL11) -> #VALUE! | AO11: =IF(AN11=0,"",AN11/AM11) -> #VALUE! | AP11: Foresea | AQ11: =SUMIFS([1]Input!$AC:$AC,[1]Input!$A:$A,[1]Comparação!$AP$1,[1]Input!$E:$E,[1]Comparação!$AP$2,[1]Input!$F:$F,[1]Comparação!AP11) -> #VALUE! | AR11: =SUMIFS([1]Input!$M:$M,[1]Input!$A:$A,[1]Comparação!$AP$1,[1]Input!$E:$E,[1]Comparação!$AP$2,[1]Input!$F:$F,[1]Comparação!AP11) -> #VALUE! | AS11: =IF(AR11=0,"",AR11/AQ11) -> #VALUE! | AT11: Foresea | AU11: =SUMIFS([1]Input!$AC:$AC,[1]Input!$A:$A,[1]Comparação!$AT$1,[1]Input!$E:$E,[1]Comparação!$AT$2,[1]Input!$F:$F,[1]Comparação!AT11) -> #VALUE! | AV11: =SUMIFS([1]Input!$M:$M,[1]Input!$A:$A,[1]Comparação!$AT$1,[1]Input!$E:$E,[1]Comparação!$AT$2,[1]Input!$F:$F,[1]Comparação!AT11) -> #VALUE! | AW11: =IF(AV11=0,"",AV11/AU11) -> #VALUE! | AY11: Foresea
B12: Archer | C12: =SUMIFS(Input!$AA:$AA,Input!$A:$A,Comparação!$B$1,Input!$E:$E,Comparação!$B$2,Input!$F:$F,Comparação!B12) -> 0 | D12: =SUMIFS(Input!$K:$K,Input!$A:$A,Comparação!$B$1,Input!$E:$E,Comparação!$B$2,Input!$F:$F,Comparação!B12) -> 0 | F12: Archer | G12: =SUMIFS(Input!$AA:$AA,Input!$A:$A,$F$1,Input!$E:$E,Comparação!$F$2,Input!$F:$F,Comparação!F12) -> 0 | H12: =SUMIFS(Input!$K:$K,Input!$A:$A,$F$1,Input!$E:$E,$F$2,Input!$F:$F,Comparação!F12) -> 0 | J12: Archer | K12: =SUMIFS(Input!$AA:$AA,Input!$A:$A,$J$1,Input!$E:$E,Comparação!$J$2,Input!$F:$F,Comparação!J12) -> 0 | L12: =SUMIFS(Input!$K:$K,Input!$A:$A,$J$1,Input!$E:$E,$J$2,Input!$F:$F,Comparação!J12) -> 0 | M12: =IF(L12=0,"",L12/K12) | N12: Archer | O12: =SUMIFS(Input!$AA:$AA,Input!$A:$A,$N$1,Input!$E:$E,Comparação!$N$2,Input!$F:$F,Comparação!N12) -> 0 | P12: =SUMIFS(Input!$K:$K,Input!$A:$A,$N$1,Input!$E:$E,$N$2,Input!$F:$F,Comparação!N12) -> 0 | Q12: =IF(P12=0,"",P12/O12) | R12: Archer | S12: =SUMIFS(Input!$AA:$AA,Input!$A:$A,$R$1,Input!$E:$E,Comparação!$R$2,Input!$F:$F,Comparação!R12) -> 0 | T12: =SUMIFS(Input!$K:$K,Input!$A:$A,$R$1,Input!$E:$E,$R$2,Input!$F:$F,Comparação!R12) -> 0 | U12: =IF(T12=0,"",T12/S12) | V12: Archer | W12: =SUMIFS([1]Input!$AC:$AC,[1]Input!$A:$A,[1]Comparação!$V$1,[1]Input!$E:$E,[1]Comparação!$V$2,[1]Input!$F:$F,[1]Comparação!V12) -> #VALUE! | X12: =SUMIFS([1]Input!$M:$M,[1]Input!$A:$A,[1]Comparação!$V$1,[1]Input!$E:$E,[1]Comparação!$V$2,[1]Input!$F:$F,[1]Comparação!V12) -> #VALUE! | Y12: =IF(X12=0,"",X12/W12) -> #VALUE! | Z12: Archer | AA12: =SUMIFS([1]Input!$AC:$AC,[1]Input!$A:$A,[1]Comparação!$Z$1,[1]Input!$E:$E,[1]Comparação!$Z$2,[1]Input!$F:$F,[1]Comparação!Z12) -> #VALUE! | AB12: =SUMIFS([1]Input!$M:$M,[1]Input!$A:$A,[1]Comparação!$Z$1,[1]Input!$E:$E,[1]Comparação!$Z$2,[1]Input!$F:$F,[1]Comparação!Z12) -> #VALUE! | AC12: =IF(AB12=0,"",AB12/AA12) -> #VALUE! | AD12: Archer | AE12: =SUMIFS([1]Input!$AC:$AC,[1]Input!$A:$A,[1]Comparação!$AD$1,[1]Input!$E:$E,[1]Comparação!$AD$2,[1]Input!$F:$F,[1]Comparação!AD12) -> #VALUE! | AF12: =SUMIFS([1]Input!$M:$M,[1]Input!$A:$A,[1]Comparação!$AD$1,[1]Input!$E:$E,[1]Comparação!$AD$2,[1]Input!$F:$F,[1]Comparação!AD12) -> #VALUE! | AG12: =IF(AF12=0,"",AF12/AE12) -> #VALUE! | AH12: Archer | AI12: =SUMIFS([1]Input!$AC:$AC,[1]Input!$A:$A,[1]Comparação!$AH$1,[1]Input!$E:$E,[1]Comparação!$AH$2,[1]Input!$F:$F,[1]Comparação!AH12) -> #VALUE! | AJ12: =SUMIFS([1]Input!$M:$M,[1]Input!$A:$A,[1]Comparação!$AH$1,[1]Input!$E:$E,[1]Comparação!$AH$2,[1]Input!$F:$F,[1]Comparação!AH12) -> #VALUE! | AK12: =IF(AJ12=0,"",AJ12/AI12) -> #VALUE! | AL12: Archer | AM12: =SUMIFS([1]Input!$AC:$AC,[1]Input!$A:$A,[1]Comparação!$AL$1,[1]Input!$E:$E,[1]Comparação!$AL$2,[1]Input!$F:$F,[1]Comparação!AL12) -> #VALUE! | AN12: =SUMIFS([1]Input!$M:$M,[1]Input!$A:$A,[1]Comparação!$AL$1,[1]Input!$E:$E,[1]Comparação!$AL$2,[1]Input!$F:$F,[1]Comparação!AL12) -> #VALUE! | AO12: =IF(AN12=0,"",AN12/AM12) -> #VALUE! | AP12: Archer | AQ12: =SUMIFS([1]Input!$AC:$AC,[1]Input!$A:$A,[1]Comparação!$AP$1,[1]Input!$E:$E,[1]Comparação!$AP$2,[1]Input!$F:$F,[1]Comparação!AP12) -> #VALUE! | AR12: =SUMIFS([1]Input!$M:$M,[1]Input!$A:$A,[1]Comparação!$AP$1,[1]Input!$E:$E,[1]Comparação!$AP$2,[1]Input!$F:$F,[1]Comparação!AP12) -> #VALUE! | AS12: =IF(AR12=0,"",AR12/AQ12) -> #VALUE! | AT12: Archer | AU12: =SUMIFS([1]Input!$AC:$AC,[1]Input!$A:$A,[1]Comparação!$AT$1,[1]Input!$E:$E,[1]Comparação!$AT$2,[1]Input!$F:$F,[1]Comparação!AT12) -> #VALUE! | AV12: =SUMIFS([1]Input!$M:$M,[1]Input!$A:$A,[1]Comparação!$AT$1,[1]Input!$E:$E,[1]Comparação!$AT$2,[1]Input!$F:$F,[1]Comparação!AT12) -> #VALUE! | AW12: =IF(AV12=0,"",AV12/AU12) -> #VALUE! | AY12: Archer
B13: Etesco | C13: =SUMIFS(Input!$AA:$AA,Input!$A:$A,Comparação!$B$1,Input!$E:$E,Comparação!$B$2,Input!$F:$F,Comparação!B13) -> 99 | D13: =SUMIFS(Input!$K:$K,Input!$A:$A,Comparação!$B$1,Input!$E:$E,Comparação!$B$2,Input!$F:$F,Comparação!B13) -> 206746.15 | E13: =D13/C13 -> 2088.3449 | F13: Etesco | G13: =SUMIFS(Input!$AA:$AA,Input!$A:$A,$F$1,Input!$E:$E,Comparação!$F$2,Input!$F:$F,Comparação!F13) -> 82 | H13: =SUMIFS(Input!$K:$K,Input!$A:$A,$F$1,Input!$E:$E,$F$2,Input!$F:$F,Comparação!F13) -> 193810.31 | I13: =H13/G13 -> 2363.5404 | J13: Etesco | K13: =SUMIFS(Input!$AA:$AA,Input!$A:$A,$J$1,Input!$E:$E,Comparação!$J$2,Input!$F:$F,Comparação!J13) -> 99 | L13: =SUMIFS(Input!$K:$K,Input!$A:$A,$J$1,Input!$E:$E,$J$2,Input!$F:$F,Comparação!J13) -> 218152.1 | M13: =IF(L13=0,"",L13/K13) -> 2203.5566 | N13: Etesco | O13: =SUMIFS(Input!$AA:$AA,Input!$A:$A,$N$1,Input!$E:$E,Comparação!$N$2,Input!$F:$F,Comparação!N13) -> 87 | P13: =SUMIFS(Input!$K:$K,Input!$A:$A,$N$1,Input!$E:$E,$N$2,Input!$F:$F,Comparação!N13) -> 188964.6 | Q13: =IF(P13=0,"",P13/O13) -> 2172.0069 | R13: Etesco | S13: =SUMIFS(Input!$AA:$AA,Input!$A:$A,$R$1,Input!$E:$E,Comparação!$R$2,Input!$F:$F,Comparação!R13) -> 96 | T13: =SUMIFS(Input!$K:$K,Input!$A:$A,$R$1,Input!$E:$E,$R$2,Input!$F:$F,Comparação!R13) -> 206998.02 | U13: =IF(T13=0,"",T13/S13) -> 2156.2294 | V13: Etesco | W13: =SUMIFS([1]Input!$AC:$AC,[1]Input!$A:$A,[1]Comparação!$V$1,[1]Input!$E:$E,[1]Comparação!$V$2,[1]Input!$F:$F,[1]Comparação!V13) -> #VALUE! | X13: =SUMIFS([1]Input!$M:$M,[1]Input!$A:$A,[1]Comparação!$V$1,[1]Input!$E:$E,[1]Comparação!$V$2,[1]Input!$F:$F,[1]Comparação!V13) -> #VALUE! | Y13: =IF(X13=0,"",X13/W13) -> #VALUE! | Z13: Etesco | AA13: =SUMIFS([1]Input!$AC:$AC,[1]Input!$A:$A,[1]Comparação!$Z$1,[1]Input!$E:$E,[1]Comparação!$Z$2,[1]Input!$F:$F,[1]Comparação!Z13) -> #VALUE! | AB13: =SUMIFS([1]Input!$M:$M,[1]Input!$A:$A,[1]Comparação!$Z$1,[1]Input!$E:$E,[1]Comparação!$Z$2,[1]Input!$F:$F,[1]Comparação!Z13) -> #VALUE! | AC13: =IF(AB13=0,"",AB13/AA13) -> #VALUE! | AD13: Etesco | AE13: =SUMIFS([1]Input!$AC:$AC,[1]Input!$A:$A,[1]Comparação!$AD$1,[1]Input!$E:$E,[1]Comparação!$AD$2,[1]Input!$F:$F,[1]Comparação!AD13) -> #VALUE! | AF13: =SUMIFS([1]Input!$M:$M,[1]Input!$A:$A,[1]Comparação!$AD$1,[1]Input!$E:$E,[1]Comparação!$AD$2,[1]Input!$F:$F,[1]Comparação!AD13) -> #VALUE! | AG13: =IF(AF13=0,"",AF13/AE13) -> #VALUE! | AH13: Etesco | AI13: =SUMIFS([1]Input!$AC:$AC,[1]Input!$A:$A,[1]Comparação!$AH$1,[1]Input!$E:$E,[1]Comparação!$AH$2,[1]Input!$F:$F,[1]Comparação!AH13) -> #VALUE! | AJ13: =SUMIFS([1]Input!$M:$M,[1]Input!$A:$A,[1]Comparação!$AH$1,[1]Input!$E:$E,[1]Comparação!$AH$2,[1]Input!$F:$F,[1]Comparação!AH13) -> #VALUE! | AK13: =IF(AJ13=0,"",AJ13/AI13) -> #VALUE! | AL13: Etesco | AM13: =SUMIFS([1]Input!$AC:$AC,[1]Input!$A:$A,[1]Comparação!$AL$1,[1]Input!$E:$E,[1]Comparação!$AL$2,[1]Input!$F:$F,[1]Comparação!AL13) -> #VALUE! | AN13: =SUMIFS([1]Input!$M:$M,[1]Input!$A:$A,[1]Comparação!$AL$1,[1]Input!$E:$E,[1]Comparação!$AL$2,[1]Input!$F:$F,[1]Comparação!AL13) -> #VALUE! | AO13: =IF(AN13=0,"",AN13/AM13) -> #VALUE! | AP13: Etesco | AQ13: =SUMIFS([1]Input!$AC:$AC,[1]Input!$A:$A,[1]Comparação!$AP$1,[1]Input!$E:$E,[1]Comparação!$AP$2,[1]Input!$F:$F,[1]Comparação!AP13) -> #VALUE! | AR13: =SUMIFS([1]Input!$M:$M,[1]Input!$A:$A,[1]Comparação!$AP$1,[1]Input!$E:$E,[1]Comparação!$AP$2,[1]Input!$F:$F,[1]Comparação!AP13) -> #VALUE! | AS13: =IF(AR13=0,"",AR13/AQ13) -> #VALUE! | AT13: Etesco | AU13: =SUMIFS([1]Input!$AC:$AC,[1]Input!$A:$A,[1]Comparação!$AT$1,[1]Input!$E:$E,[1]Comparação!$AT$2,[1]Input!$F:$F,[1]Comparação!AT13) -> #VALUE! | AV13: =SUMIFS([1]Input!$M:$M,[1]Input!$A:$A,[1]Comparação!$AT$1,[1]Input!$E:$E,[1]Comparação!$AT$2,[1]Input!$F:$F,[1]Comparação!AT13) -> #VALUE! | AW13: =IF(AV13=0,"",AV13/AU13) -> #VALUE! | AY13: Etesco
B14: Constellation | C14: =SUMIFS(Input!$AA:$AA,Input!$A:$A,Comparação!$B$1,Input!$E:$E,Comparação!$B$2,Input!$F:$F,Comparação!B14) -> 262 | D14: =SUMIFS(Input!$K:$K,Input!$A:$A,Comparação!$B$1,Input!$E:$E,Comparação!$B$2,Input!$F:$F,Comparação!B14) -> 558770.45 | E14: =D14/C14 -> 2132.7116 | F14: Constellation | G14: =SUMIFS(Input!$AA:$AA,Input!$A:$A,$F$1,Input!$E:$E,Comparação!$F$2,Input!$F:$F,Comparação!F14) -> 252 | H14: =SUMIFS(Input!$K:$K,Input!$A:$A,$F$1,Input!$E:$E,$F$2,Input!$F:$F,Comparação!F14) -> 549039.09 | I14: =H14/G14 -> 2178.7265 | J14: Constellation | K14: =SUMIFS(Input!$AA:$AA,Input!$A:$A,$J$1,Input!$E:$E,Comparação!$J$2,Input!$F:$F,Comparação!J14) -> 291 | L14: =SUMIFS(Input!$K:$K,Input!$A:$A,$J$1,Input!$E:$E,$J$2,Input!$F:$F,Comparação!J14) -> 597642.27 | M14: =IF(L14=0,"",L14/K14) -> 2053.7535 | N14: Constellation | O14: =SUMIFS(Input!$AA:$AA,Input!$A:$A,$N$1,Input!$E:$E,Comparação!$N$2,Input!$F:$F,Comparação!N14) -> 280 | P14: =SUMIFS(Input!$K:$K,Input!$A:$A,$N$1,Input!$E:$E,$N$2,Input!$F:$F,Comparação!N14) -> 588438.67 | Q14: =IF(P14=0,"",P14/O14) -> 2101.5667 | R14: Constellation | S14: =SUMIFS(Input!$AA:$AA,Input!$A:$A,$R$1,Input!$E:$E,Comparação!$R$2,Input!$F:$F,Comparação!R14) -> 252 | T14: =SUMIFS(Input!$K:$K,Input!$A:$A,$R$1,Input!$E:$E,$R$2,Input!$F:$F,Comparação!R14) -> 499542.66 | U14: =IF(T14=0,"",T14/S14) -> 1982.3121 | V14: Constellation | W14: =SUMIFS([1]Input!$AC:$AC,[1]Input!$A:$A,[1]Comparação!$V$1,[1]Input!$E:$E,[1]Comparação!$V$2,[1]Input!$F:$F,[1]Comparação!V14) -> #VALUE! | X14: =SUMIFS([1]Input!$M:$M,[1]Input!$A:$A,[1]Comparação!$V$1,[1]Input!$E:$E,[1]Comparação!$V$2,[1]Input!$F:$F,[1]Comparação!V14) -> #VALUE! | Y14: =IF(X14=0,"",X14/W14) -> #VALUE! | Z14: Constellation | AA14: =SUMIFS([1]Input!$AC:$AC,[1]Input!$A:$A,[1]Comparação!$Z$1,[1]Input!$E:$E,[1]Comparação!$Z$2,[1]Input!$F:$F,[1]Comparação!Z14) -> #VALUE! | AB14: =SUMIFS([1]Input!$M:$M,[1]Input!$A:$A,[1]Comparação!$Z$1,[1]Input!$E:$E,[1]Comparação!$Z$2,[1]Input!$F:$F,[1]Comparação!Z14) -> #VALUE! | AC14: =IF(AB14=0,"",AB14/AA14) -> #VALUE! | AD14: Constellation | AE14: =SUMIFS([1]Input!$AC:$AC,[1]Input!$A:$A,[1]Comparação!$AD$1,[1]Input!$E:$E,[1]Comparação!$AD$2,[1]Input!$F:$F,[1]Comparação!AD14) -> #VALUE! | AF14: =SUMIFS([1]Input!$M:$M,[1]Input!$A:$A,[1]Comparação!$AD$1,[1]Input!$E:$E,[1]Comparação!$AD$2,[1]Input!$F:$F,[1]Comparação!AD14) -> #VALUE! | AG14: =IF(AF14=0,"",AF14/AE14) -> #VALUE! | AH14: Constellation | AI14: =SUMIFS([1]Input!$AC:$AC,[1]Input!$A:$A,[1]Comparação!$AH$1,[1]Input!$E:$E,[1]Comparação!$AH$2,[1]Input!$F:$F,[1]Comparação!AH14) -> #VALUE! | AJ14: =SUMIFS([1]Input!$M:$M,[1]Input!$A:$A,[1]Comparação!$AH$1,[1]Input!$E:$E,[1]Comparação!$AH$2,[1]Input!$F:$F,[1]Comparação!AH14) -> #VALUE! | AK14: =IF(AJ14=0,"",AJ14/AI14) -> #VALUE! | AL14: Constellation | AM14: =SUMIFS([1]Input!$AC:$AC,[1]Input!$A:$A,[1]Comparação!$AL$1,[1]Input!$E:$E,[1]Comparação!$AL$2,[1]Input!$F:$F,[1]Comparação!AL14) -> #VALUE! | AN14: =SUMIFS([1]Input!$M:$M,[1]Input!$A:$A,[1]Comparação!$AL$1,[1]Input!$E:$E,[1]Comparação!$AL$2,[1]Input!$F:$F,[1]Comparação!AL14) -> #VALUE! | AO14: =IF(AN14=0,"",AN14/AM14) -> #VALUE! | AP14: Constellation | AQ14: =SUMIFS([1]Input!$AC:$AC,[1]Input!$A:$A,[1]Comparação!$AP$1,[1]Input!$E:$E,[1]Comparação!$AP$2,[1]Input!$F:$F,[1]Comparação!AP14) -> #VALUE! | AR14: =SUMIFS([1]Input!$M:$M,[1]Input!$A:$A,[1]Comparação!$AP$1,[1]Input!$E:$E,[1]Comparação!$AP$2,[1]Input!$F:$F,[1]Comparação!AP14) -> #VALUE! | AS14: =IF(AR14=0,"",AR14/AQ14) -> #VALUE! | AT14: Constellation | AU14: =SUMIFS([1]Input!$AC:$AC,[1]Input!$A:$A,[1]Comparação!$AT$1,[1]Input!$E:$E,[1]Comparação!$AT$2,[1]Input!$F:$F,[1]Comparação!AT14) -> #VALUE! | AV14: =SUMIFS([1]Input!$M:$M,[1]Input!$A:$A,[1]Comparação!$AT$1,[1]Input!$E:$E,[1]Comparação!$AT$2,[1]Input!$F:$F,[1]Comparação!AT14) -> #VALUE! | AW14: =IF(AV14=0,"",AV14/AU14) -> #VALUE! | AY14: Constellation
B15: Halliburton | C15: =SUMIFS(Input!$AA:$AA,Input!$A:$A,Comparação!$B$1,Input!$E:$E,Comparação!$B$2,Input!$F:$F,Comparação!B15) -> 0 | D15: =SUMIFS(Input!$K:$K,Input!$A:$A,Comparação!$B$1,Input!$E:$E,Comparação!$B$2,Input!$F:$F,Comparação!B15) -> 0 | F15: Halliburton | G15: =SUMIFS(Input!$AA:$AA,Input!$A:$A,$F$1,Input!$E:$E,Comparação!$F$2,Input!$F:$F,Comparação!F15) -> 0 | H15: =SUMIFS(Input!$K:$K,Input!$A:$A,$F$1,Input!$E:$E,$F$2,Input!$F:$F,Comparação!F15) -> 0 | J15: Halliburton | K15: =SUMIFS(Input!$AA:$AA,Input!$A:$A,$J$1,Input!$E:$E,Comparação!$J$2,Input!$F:$F,Comparação!J15) -> 0 | L15: =SUMIFS(Input!$K:$K,Input!$A:$A,$J$1,Input!$E:$E,$J$2,Input!$F:$F,Comparação!J15) -> 0 | M15: =IF(L15=0,"",L15/K15) | N15: Halliburton | O15: =SUMIFS(Input!$AA:$AA,Input!$A:$A,$N$1,Input!$E:$E,Comparação!$N$2,Input!$F:$F,Comparação!N15) -> 0 | P15: =SUMIFS(Input!$K:$K,Input!$A:$A,$N$1,Input!$E:$E,$N$2,Input!$F:$F,Comparação!N15) -> 0 | Q15: =IF(P15=0,"",P15/O15) | R15: Halliburton | S15: =SUMIFS(Input!$AA:$AA,Input!$A:$A,$R$1,Input!$E:$E,Comparação!$R$2,Input!$F:$F,Comparação!R15) -> 0 | T15: =SUMIFS(Input!$K:$K,Input!$A:$A,$R$1,Input!$E:$E,$R$2,Input!$F:$F,Comparação!R15) -> 0 | U15: =IF(T15=0,"",T15/S15) | V15: Halliburton | W15: =SUMIFS([1]Input!$AC:$AC,[1]Input!$A:$A,[1]Comparação!$V$1,[1]Input!$E:$E,[1]Comparação!$V$2,[1]Input!$F:$F,[1]Comparação!V15) -> #VALUE! | X15: =SUMIFS([1]Input!$M:$M,[1]Input!$A:$A,[1]Comparação!$V$1,[1]Input!$E:$E,[1]Comparação!$V$2,[1]Input!$F:$F,[1]Comparação!V15) -> #VALUE! | Y15: =IF(X15=0,"",X15/W15) -> #VALUE! | Z15: Halliburton | AA15: =SUMIFS([1]Input!$AC:$AC,[1]Input!$A:$A,[1]Comparação!$Z$1,[1]Input!$E:$E,[1]Comparação!$Z$2,[1]Input!$F:$F,[1]Comparação!Z15) -> #VALUE! | AB15: =SUMIFS([1]Input!$M:$M,[1]Input!$A:$A,[1]Comparação!$Z$1,[1]Input!$E:$E,[1]Comparação!$Z$2,[1]Input!$F:$F,[1]Comparação!Z15) -> #VALUE! | AC15: =IF(AB15=0,"",AB15/AA15) -> #VALUE! | AD15: Halliburton | AE15: =SUMIFS([1]Input!$AC:$AC,[1]Input!$A:$A,[1]Comparação!$AD$1,[1]Input!$E:$E,[1]Comparação!$AD$2,[1]Input!$F:$F,[1]Comparação!AD15) -> #VALUE! | AF15: =SUMIFS([1]Input!$M:$M,[1]Input!$A:$A,[1]Comparação!$AD$1,[1]Input!$E:$E,[1]Comparação!$AD$2,[1]Input!$F:$F,[1]Comparação!AD15) -> #VALUE! | AG15: =IF(AF15=0,"",AF15/AE15) -> #VALUE! | AH15: Halliburton | AI15: =SUMIFS([1]Input!$AC:$AC,[1]Input!$A:$A,[1]Comparação!$AH$1,[1]Input!$E:$E,[1]Comparação!$AH$2,[1]Input!$F:$F,[1]Comparação!AH15) -> #VALUE! | AJ15: =SUMIFS([1]Input!$M:$M,[1]Input!$A:$A,[1]Comparação!$AH$1,[1]Input!$E:$E,[1]Comparação!$AH$2,[1]Input!$F:$F,[1]Comparação!AH15) -> #VALUE! | AK15: =IF(AJ15=0,"",AJ15/AI15) -> #VALUE! | AL15: Halliburton | AM15: =SUMIFS([1]Input!$AC:$AC,[1]Input!$A:$A,[1]Comparação!$AL$1,[1]Input!$E:$E,[1]Comparação!$AL$2,[1]Input!$F:$F,[1]Comparação!AL15) -> #VALUE! | AN15: =SUMIFS([1]Input!$M:$M,[1]Input!$A:$A,[1]Comparação!$AL$1,[1]Input!$E:$E,[1]Comparação!$AL$2,[1]Input!$F:$F,[1]Comparação!AL15) -> #VALUE! | AO15: =IF(AN15=0,"",AN15/AM15) -> #VALUE! | AP15: Halliburton | AQ15: =SUMIFS([1]Input!$AC:$AC,[1]Input!$A:$A,[1]Comparação!$AP$1,[1]Input!$E:$E,[1]Comparação!$AP$2,[1]Input!$F:$F,[1]Comparação!AP15) -> #VALUE! | AR15: =SUMIFS([1]Input!$M:$M,[1]Input!$A:$A,[1]Comparação!$AP$1,[1]Input!$E:$E,[1]Comparação!$AP$2,[1]Input!$F:$F,[1]Comparação!AP15) -> #VALUE! | AS15: =IF(AR15=0,"",AR15/AQ15) -> #VALUE! | AT15: Halliburton | AU15: =SUMIFS([1]Input!$AC:$AC,[1]Input!$A:$A,[1]Comparação!$AT$1,[1]Input!$E:$E,[1]Comparação!$AT$2,[1]Input!$F:$F,[1]Comparação!AT15) -> #VALUE! | AV15: =SUMIFS([1]Input!$M:$M,[1]Input!$A:$A,[1]Comparação!$AT$1,[1]Input!$E:$E,[1]Comparação!$AT$2,[1]Input!$F:$F,[1]Comparação!AT15) -> #VALUE! | AW15: =IF(AV15=0,"",AV15/AU15) -> #VALUE! | AY15: Halliburton
B16: Siem | C16: =SUMIFS(Input!$AA:$AA,Input!$A:$A,Comparação!$B$1,Input!$E:$E,Comparação!$B$2,Input!$F:$F,Comparação!B16) -> 0 | D16: =SUMIFS(Input!$K:$K,Input!$A:$A,Comparação!$B$1,Input!$E:$E,Comparação!$B$2,Input!$F:$F,Comparação!B16) -> 0 | F16: Siem | G16: =SUMIFS(Input!$AA:$AA,Input!$A:$A,$F$1,Input!$E:$E,Comparação!$F$2,Input!$F:$F,Comparação!F16) -> 0 | H16: =SUMIFS(Input!$K:$K,Input!$A:$A,$F$1,Input!$E:$E,$F$2,Input!$F:$F,Comparação!F16) -> 0 | J16: Siem | K16: =SUMIFS(Input!$AA:$AA,Input!$A:$A,$J$1,Input!$E:$E,Comparação!$J$2,Input!$F:$F,Comparação!J16) -> 0 | L16: =SUMIFS(Input!$K:$K,Input!$A:$A,$J$1,Input!$E:$E,$J$2,Input!$F:$F,Comparação!J16) -> 0 | M16: =IF(L16=0,"",L16/K16) | N16: Siem | O16: =SUMIFS(Input!$AA:$AA,Input!$A:$A,$N$1,Input!$E:$E,Comparação!$N$2,Input!$F:$F,Comparação!N16) -> 0 | P16: =SUMIFS(Input!$K:$K,Input!$A:$A,$N$1,Input!$E:$E,$N$2,Input!$F:$F,Comparação!N16) -> 0 | Q16: =IF(P16=0,"",P16/O16) | R16: Siem | S16: =SUMIFS(Input!$AA:$AA,Input!$A:$A,$R$1,Input!$E:$E,Comparação!$R$2,Input!$F:$F,Comparação!R16) -> 0 | T16: =SUMIFS(Input!$K:$K,Input!$A:$A,$R$1,Input!$E:$E,$R$2,Input!$F:$F,Comparação!R16) -> 0 | U16: =IF(T16=0,"",T16/S16) | V16: Siem | W16: =SUMIFS([1]Input!$AC:$AC,[1]Input!$A:$A,[1]Comparação!$V$1,[1]Input!$E:$E,[1]Comparação!$V$2,[1]Input!$F:$F,[1]Comparação!V16) -> #VALUE! | X16: =SUMIFS([1]Input!$M:$M,[1]Input!$A:$A,[1]Comparação!$V$1,[1]Input!$E:$E,[1]Comparação!$V$2,[1]Input!$F:$F,[1]Comparação!V16) -> #VALUE! | Y16: =IF(X16=0,"",X16/W16) -> #VALUE! | Z16: Siem | AA16: =SUMIFS([1]Input!$AC:$AC,[1]Input!$A:$A,[1]Comparação!$Z$1,[1]Input!$E:$E,[1]Comparação!$Z$2,[1]Input!$F:$F,[1]Comparação!Z16) -> #VALUE! | AB16: =SUMIFS([1]Input!$M:$M,[1]Input!$A:$A,[1]Comparação!$Z$1,[1]Input!$E:$E,[1]Comparação!$Z$2,[1]Input!$F:$F,[1]Comparação!Z16) -> #VALUE! | AC16: =IF(AB16=0,"",AB16/AA16) -> #VALUE! | AD16: Siem | AE16: =SUMIFS([1]Input!$AC:$AC,[1]Input!$A:$A,[1]Comparação!$AD$1,[1]Input!$E:$E,[1]Comparação!$AD$2,[1]Input!$F:$F,[1]Comparação!AD16) -> #VALUE! | AF16: =SUMIFS([1]Input!$M:$M,[1]Input!$A:$A,[1]Comparação!$AD$1,[1]Input!$E:$E,[1]Comparação!$AD$2,[1]Input!$F:$F,[1]Comparação!AD16) -> #VALUE! | AG16: =IF(AF16=0,"",AF16/AE16) -> #VALUE! | AH16: Siem | AI16: =SUMIFS([1]Input!$AC:$AC,[1]Input!$A:$A,[1]Comparação!$AH$1,[1]Input!$E:$E,[1]Comparação!$AH$2,[1]Input!$F:$F,[1]Comparação!AH16) -> #VALUE! | AJ16: =SUMIFS([1]Input!$M:$M,[1]Input!$A:$A,[1]Comparação!$AH$1,[1]Input!$E:$E,[1]Comparação!$AH$2,[1]Input!$F:$F,[1]Comparação!AH16) -> #VALUE! | AK16: =IF(AJ16=0,"",AJ16/AI16) -> #VALUE! | AL16: Siem | AM16: =SUMIFS([1]Input!$AC:$AC,[1]Input!$A:$A,[1]Comparação!$AL$1,[1]Input!$E:$E,[1]Comparação!$AL$2,[1]Input!$F:$F,[1]Comparação!AL16) -> #VALUE! | AN16: =SUMIFS([1]Input!$M:$M,[1]Input!$A:$A,[1]Comparação!$AL$1,[1]Input!$E:$E,[1]Comparação!$AL$2,[1]Input!$F:$F,[1]Comparação!AL16) -> #VALUE! | AO16: =IF(AN16=0,"",AN16/AM16) -> #VALUE! | AP16: Siem | AQ16: =SUMIFS([1]Input!$AC:$AC,[1]Input!$A:$A,[1]Comparação!$AP$1,[1]Input!$E:$E,[1]Comparação!$AP$2,[1]Input!$F:$F,[1]Comparação!AP16) -> #VALUE! | AR16: =SUMIFS([1]Input!$M:$M,[1]Input!$A:$A,[1]Comparação!$AP$1,[1]Input!$E:$E,[1]Comparação!$AP$2,[1]Input!$F:$F,[1]Comparação!AP16) -> #VALUE! | AS16: =IF(AR16=0,"",AR16/AQ16) -> #VALUE! | AT16: Siem | AU16: =SUMIFS([1]Input!$AC:$AC,[1]Input!$A:$A,[1]Comparação!$AT$1,[1]Input!$E:$E,[1]Comparação!$AT$2,[1]Input!$F:$F,[1]Comparação!AT16) -> #VALUE! | AV16: =SUMIFS([1]Input!$M:$M,[1]Input!$A:$A,[1]Comparação!$AT$1,[1]Input!$E:$E,[1]Comparação!$AT$2,[1]Input!$F:$F,[1]Comparação!AT16) -> #VALUE! | AW16: =IF(AV16=0,"",AV16/AU16) -> #VALUE! | AY16: Siem
B17: SLB | C17: =SUMIFS(Input!$AA:$AA,Input!$A:$A,Comparação!$B$1,Input!$E:$E,Comparação!$B$2,Input!$F:$F,Comparação!B17) -> 0 | D17: =SUMIFS(Input!$K:$K,Input!$A:$A,Comparação!$B$1,Input!$E:$E,Comparação!$B$2,Input!$F:$F,Comparação!B17) -> 0 | F17: SLB | G17: =SUMIFS(Input!$AA:$AA,Input!$A:$A,$F$1,Input!$E:$E,Comparação!$F$2,Input!$F:$F,Comparação!F17) -> 0 | H17: =SUMIFS(Input!$K:$K,Input!$A:$A,$F$1,Input!$E:$E,$F$2,Input!$F:$F,Comparação!F17) -> 0 | J17: SLB | K17: =SUMIFS(Input!$AA:$AA,Input!$A:$A,$J$1,Input!$E:$E,Comparação!$J$2,Input!$F:$F,Comparação!J17) -> 0 | L17: =SUMIFS(Input!$K:$K,Input!$A:$A,$J$1,Input!$E:$E,$J$2,Input!$F:$F,Comparação!J17) -> 0 | M17: =IF(L17=0,"",L17/K17) | N17: SLB | O17: =SUMIFS(Input!$AA:$AA,Input!$A:$A,$N$1,Input!$E:$E,Comparação!$N$2,Input!$F:$F,Comparação!N17) -> 0 | P17: =SUMIFS(Input!$K:$K,Input!$A:$A,$N$1,Input!$E:$E,$N$2,Input!$F:$F,Comparação!N17) -> 0 | Q17: =IF(P17=0,"",P17/O17) | R17: SLB | S17: =SUMIFS(Input!$AA:$AA,Input!$A:$A,$R$1,Input!$E:$E,Comparação!$R$2,Input!$F:$F,Comparação!R17) -> 0 | T17: =SUMIFS(Input!$K:$K,Input!$A:$A,$R$1,Input!$E:$E,$R$2,Input!$F:$F,Comparação!R17) -> 0 | U17: =IF(T17=0,"",T17/S17) | V17: SLB | W17: =SUMIFS([1]Input!$AC:$AC,[1]Input!$A:$A,[1]Comparação!$V$1,[1]Input!$E:$E,[1]Comparação!$V$2,[1]Input!$F:$F,[1]Comparação!V17) -> #VALUE! | X17: =SUMIFS([1]Input!$M:$M,[1]Input!$A:$A,[1]Comparação!$V$1,[1]Input!$E:$E,[1]Comparação!$V$2,[1]Input!$F:$F,[1]Comparação!V17) -> #VALUE! | Y17: =IF(X17=0,"",X17/W17) -> #VALUE! | Z17: SLB | AA17: =SUMIFS([1]Input!$AC:$AC,[1]Input!$A:$A,[1]Comparação!$Z$1,[1]Input!$E:$E,[1]Comparação!$Z$2,[1]Input!$F:$F,[1]Comparação!Z17) -> #VALUE! | AB17: =SUMIFS([1]Input!$M:$M,[1]Input!$A:$A,[1]Comparação!$Z$1,[1]Input!$E:$E,[1]Comparação!$Z$2,[1]Input!$F:$F,[1]Comparação!Z17) -> #VALUE! | AC17: =IF(AB17=0,"",AB17/AA17) -> #VALUE! | AD17: SLB | AE17: =SUMIFS([1]Input!$AC:$AC,[1]Input!$A:$A,[1]Comparação!$AD$1,[1]Input!$E:$E,[1]Comparação!$AD$2,[1]Input!$F:$F,[1]Comparação!AD17) -> #VALUE! | AF17: =SUMIFS([1]Input!$M:$M,[1]Input!$A:$A,[1]Comparação!$AD$1,[1]Input!$E:$E,[1]Comparação!$AD$2,[1]Input!$F:$F,[1]Comparação!AD17) -> #VALUE! | AG17: =IF(AF17=0,"",AF17/AE17) -> #VALUE! | AH17: SLB | AI17: =SUMIFS([1]Input!$AC:$AC,[1]Input!$A:$A,[1]Comparação!$AH$1,[1]Input!$E:$E,[1]Comparação!$AH$2,[1]Input!$F:$F,[1]Comparação!AH17) -> #VALUE! | AJ17: =SUMIFS([1]Input!$M:$M,[1]Input!$A:$A,[1]Comparação!$AH$1,[1]Input!$E:$E,[1]Comparação!$AH$2,[1]Input!$F:$F,[1]Comparação!AH17) -> #VALUE! | AK17: =IF(AJ17=0,"",AJ17/AI17) -> #VALUE! | AL17: SLB | AM17: =SUMIFS([1]Input!$AC:$AC,[1]Input!$A:$A,[1]Comparação!$AL$1,[1]Input!$E:$E,[1]Comparação!$AL$2,[1]Input!$F:$F,[1]Comparação!AL17) -> #VALUE! | AN17: =SUMIFS([1]Input!$M:$M,[1]Input!$A:$A,[1]Comparação!$AL$1,[1]Input!$E:$E,[1]Comparação!$AL$2,[1]Input!$F:$F,[1]Comparação!AL17) -> #VALUE! | AO17: =IF(AN17=0,"",AN17/AM17) -> #VALUE! | AP17: SLB | AQ17: =SUMIFS([1]Input!$AC:$AC,[1]Input!$A:$A,[1]Comparação!$AP$1,[1]Input!$E:$E,[1]Comparação!$AP$2,[1]Input!$F:$F,[1]Comparação!AP17) -> #VALUE! | AR17: =SUMIFS([1]Input!$M:$M,[1]Input!$A:$A,[1]Comparação!$AP$1,[1]Input!$E:$E,[1]Comparação!$AP$2,[1]Input!$F:$F,[1]Comparação!AP17) -> #VALUE! | AS17: =IF(AR17=0,"",AR17/AQ17) -> #VALUE! | AT17: SLB | AU17: =SUMIFS([1]Input!$AC:$AC,[1]Input!$A:$A,[1]Comparação!$AT$1,[1]Input!$E:$E,[1]Comparação!$AT$2,[1]Input!$F:$F,[1]Comparação!AT17) -> #VALUE! | AV17: =SUMIFS([1]Input!$M:$M,[1]Input!$A:$A,[1]Comparação!$AT$1,[1]Input!$E:$E,[1]Comparação!$AT$2,[1]Input!$F:$F,[1]Comparação!AT17) -> #VALUE! | AW17: =IF(AV17=0,"",AV17/AU17) -> #VALUE! | AY17: SLB
B18: Seadrill | C18: =SUMIFS(Input!$AA:$AA,Input!$A:$A,Comparação!$B$1,Input!$E:$E,Comparação!$B$2,Input!$F:$F,Comparação!B18) -> 0 | D18: =SUMIFS(Input!$K:$K,Input!$A:$A,Comparação!$B$1,Input!$E:$E,Comparação!$B$2,Input!$F:$F,Comparação!B18) -> 0 | F18: Seadrill | G18: =SUMIFS(Input!$AA:$AA,Input!$A:$A,$F$1,Input!$E:$E,Comparação!$F$2,Input!$F:$F,Comparação!F18) -> 0 | H18: =SUMIFS(Input!$K:$K,Input!$A:$A,$F$1,Input!$E:$E,$F$2,Input!$F:$F,Comparação!F18) -> 0 | J18: Seadrill | K18: =SUMIFS(Input!$AA:$AA,Input!$A:$A,$J$1,Input!$E:$E,Comparação!$J$2,Input!$F:$F,Comparação!J18) -> 0 | L18: =SUMIFS(Input!$K:$K,Input!$A:$A,$J$1,Input!$E:$E,$J$2,Input!$F:$F,Comparação!J18) -> 0 | M18: =IF(L18=0,"",L18/K18) | N18: Seadrill | O18: =SUMIFS(Input!$AA:$AA,Input!$A:$A,$N$1,Input!$E:$E,Comparação!$N$2,Input!$F:$F,Comparação!N18) -> 0 | P18: =SUMIFS(Input!$K:$K,Input!$A:$A,$N$1,Input!$E:$E,$N$2,Input!$F:$F,Comparação!N18) -> 0 | Q18: =IF(P18=0,"",P18/O18) | R18: Seadrill | S18: =SUMIFS(Input!$AA:$AA,Input!$A:$A,$R$1,Input!$E:$E,Comparação!$R$2,Input!$F:$F,Comparação!R18) -> 0 | T18: =SUMIFS(Input!$K:$K,Input!$A:$A,$R$1,Input!$E:$E,$R$2,Input!$F:$F,Comparação!R18) -> 0 | U18: =IF(T18=0,"",T18/S18) | V18: Seadrill | W18: =SUMIFS([1]Input!$AC:$AC,[1]Input!$A:$A,[1]Comparação!$V$1,[1]Input!$E:$E,[1]Comparação!$V$2,[1]Input!$F:$F,[1]Comparação!V18) -> #VALUE! | X18: =SUMIFS([1]Input!$M:$M,[1]Input!$A:$A,[1]Comparação!$V$1,[1]Input!$E:$E,[1]Comparação!$V$2,[1]Input!$F:$F,[1]Comparação!V18) -> #VALUE! | Y18: =IF(X18=0,"",X18/W18) -> #VALUE! | Z18: Seadrill | AA18: =SUMIFS([1]Input!$AC:$AC,[1]Input!$A:$A,[1]Comparação!$Z$1,[1]Input!$E:$E,[1]Comparação!$Z$2,[1]Input!$F:$F,[1]Comparação!Z18) -> #VALUE! | AB18: =SUMIFS([1]Input!$M:$M,[1]Input!$A:$A,[1]Comparação!$Z$1,[1]Input!$E:$E,[1]Comparação!$Z$2,[1]Input!$F:$F,[1]Comparação!Z18) -> #VALUE! | AC18: =IF(AB18=0,"",AB18/AA18) -> #VALUE! | AD18: Seadrill | AE18: =SUMIFS([1]Input!$AC:$AC,[1]Input!$A:$A,[1]Comparação!$AD$1,[1]Input!$E:$E,[1]Comparação!$AD$2,[1]Input!$F:$F,[1]Comparação!AD18) -> #VALUE! | AF18: =SUMIFS([1]Input!$M:$M,[1]Input!$A:$A,[1]Comparação!$AD$1,[1]Input!$E:$E,[1]Comparação!$AD$2,[1]Input!$F:$F,[1]Comparação!AD18) -> #VALUE! | AG18: =IF(AF18=0,"",AF18/AE18) -> #VALUE! | AH18: Seadrill | AI18: =SUMIFS([1]Input!$AC:$AC,[1]Input!$A:$A,[1]Comparação!$AH$1,[1]Input!$E:$E,[1]Comparação!$AH$2,[1]Input!$F:$F,[1]Comparação!AH18) -> #VALUE! | AJ18: =SUMIFS([1]Input!$M:$M,[1]Input!$A:$A,[1]Comparação!$AH$1,[1]Input!$E:$E,[1]Comparação!$AH$2,[1]Input!$F:$F,[1]Comparação!AH18) -> #VALUE! | AK18: =IF(AJ18=0,"",AJ18/AI18) -> #VALUE! | AL18: Seadrill | AM18: =SUMIFS([1]Input!$AC:$AC,[1]Input!$A:$A,[1]Comparação!$AL$1,[1]Input!$E:$E,[1]Comparação!$AL$2,[1]Input!$F:$F,[1]Comparação!AL18) -> #VALUE! | AN18: =SUMIFS([1]Input!$M:$M,[1]Input!$A:$A,[1]Comparação!$AL$1,[1]Input!$E:$E,[1]Comparação!$AL$2,[1]Input!$F:$F,[1]Comparação!AL18) -> #VALUE! | AO18: =IF(AN18=0,"",AN18/AM18) -> #VALUE! | AP18: Seadrill | AQ18: =SUMIFS([1]Input!$AC:$AC,[1]Input!$A:$A,[1]Comparação!$AP$1,[1]Input!$E:$E,[1]Comparação!$AP$2,[1]Input!$F:$F,[1]Comparação!AP18) -> #VALUE! | AR18: =SUMIFS([1]Input!$M:$M,[1]Input!$A:$A,[1]Comparação!$AP$1,[1]Input!$E:$E,[1]Comparação!$AP$2,[1]Input!$F:$F,[1]Comparação!AP18) -> #VALUE! | AS18: =IF(AR18=0,"",AR18/AQ18) -> #VALUE! | AT18: Seadrill | AU18: =SUMIFS([1]Input!$AC:$AC,[1]Input!$A:$A,[1]Comparação!$AT$1,[1]Input!$E:$E,[1]Comparação!$AT$2,[1]Input!$F:$F,[1]Comparação!AT18) -> #VALUE! | AV18: =SUMIFS([1]Input!$M:$M,[1]Input!$A:$A,[1]Comparação!$AT$1,[1]Input!$E:$E,[1]Comparação!$AT$2,[1]Input!$F:$F,[1]Comparação!AT18) -> #VALUE! | AW18: =IF(AV18=0,"",AV18/AU18) -> #VALUE! | AY18: Seadrill
B19: Haleon | C19: =SUMIFS(Input!$AA:$AA,Input!$A:$A,Comparação!$B$1,Input!$E:$E,Comparação!$B$2,Input!$F:$F,Comparação!B19) -> 0 | D19: =SUMIFS(Input!$K:$K,Input!$A:$A,Comparação!$B$1,Input!$E:$E,Comparação!$B$2,Input!$F:$F,Comparação!B19) -> 0 | F19: Haleon | G19: =SUMIFS(Input!$AA:$AA,Input!$A:$A,$F$1,Input!$E:$E,Comparação!$F$2,Input!$F:$F,Comparação!F19) -> 0 | H19: =SUMIFS(Input!$K:$K,Input!$A:$A,$F$1,Input!$E:$E,$F$2,Input!$F:$F,Comparação!F19) -> 0 | J19: Haleon | K19: =SUMIFS(Input!$AA:$AA,Input!$A:$A,$J$1,Input!$E:$E,Comparação!$J$2,Input!$F:$F,Comparação!J19) -> 0 | L19: =SUMIFS(Input!$K:$K,Input!$A:$A,$J$1,Input!$E:$E,$J$2,Input!$F:$F,Comparação!J19) -> 0 | M19: =IF(L19=0,"",L19/K19) | N19: Haleon | O19: =SUMIFS(Input!$AA:$AA,Input!$A:$A,$N$1,Input!$E:$E,Comparação!$N$2,Input!$F:$F,Comparação!N19) -> 0 | P19: =SUMIFS(Input!$K:$K,Input!$A:$A,$N$1,Input!$E:$E,$N$2,Input!$F:$F,Comparação!N19) -> 0 | Q19: =IF(P19=0,"",P19/O19) | R19: Haleon | S19: =SUMIFS(Input!$AA:$AA,Input!$A:$A,$R$1,Input!$E:$E,Comparação!$R$2,Input!$F:$F,Comparação!R19) -> 0 | T19: =SUMIFS(Input!$K:$K,Input!$A:$A,$R$1,Input!$E:$E,$R$2,Input!$F:$F,Comparação!R19) -> 0 | U19: =IF(T19=0,"",T19/S19) | V19: Haleon | W19: =SUMIFS([1]Input!$AC:$AC,[1]Input!$A:$A,[1]Comparação!$V$1,[1]Input!$E:$E,[1]Comparação!$V$2,[1]Input!$F:$F,[1]Comparação!V19) -> #VALUE! | X19: =SUMIFS([1]Input!$M:$M,[1]Input!$A:$A,[1]Comparação!$V$1,[1]Input!$E:$E,[1]Comparação!$V$2,[1]Input!$F:$F,[1]Comparação!V19) -> #VALUE! | Y19: =IF(X19=0,"",X19/W19) -> #VALUE! | Z19: Haleon | AA19: =SUMIFS([1]Input!$AC:$AC,[1]Input!$A:$A,[1]Comparação!$Z$1,[1]Input!$E:$E,[1]Comparação!$Z$2,[1]Input!$F:$F,[1]Comparação!Z19) -> #VALUE! | AB19: =SUMIFS([1]Input!$M:$M,[1]Input!$A:$A,[1]Comparação!$Z$1,[1]Input!$E:$E,[1]Comparação!$Z$2,[1]Input!$F:$F,[1]Comparação!Z19) -> #VALUE! | AC19: =IF(AB19=0,"",AB19/AA19) -> #VALUE! | AD19: Haleon | AE19: =SUMIFS([1]Input!$AC:$AC,[1]Input!$A:$A,[1]Comparação!$AD$1,[1]Input!$E:$E,[1]Comparação!$AD$2,[1]Input!$F:$F,[1]Comparação!AD19) -> #VALUE! | AF19: =SUMIFS([1]Input!$M:$M,[1]Input!$A:$A,[1]Comparação!$AD$1,[1]Input!$E:$E,[1]Comparação!$AD$2,[1]Input!$F:$F,[1]Comparação!AD19) -> #VALUE! | AG19: =IF(AF19=0,"",AF19/AE19) -> #VALUE! | AH19: Haleon | AI19: =SUMIFS([1]Input!$AC:$AC,[1]Input!$A:$A,[1]Comparação!$AH$1,[1]Input!$E:$E,[1]Comparação!$AH$2,[1]Input!$F:$F,[1]Comparação!AH19) -> #VALUE! | AJ19: =SUMIFS([1]Input!$M:$M,[1]Input!$A:$A,[1]Comparação!$AH$1,[1]Input!$E:$E,[1]Comparação!$AH$2,[1]Input!$F:$F,[1]Comparação!AH19) -> #VALUE! | AK19: =IF(AJ19=0,"",AJ19/AI19) -> #VALUE! | AL19: Haleon | AM19: =SUMIFS([1]Input!$AC:$AC,[1]Input!$A:$A,[1]Comparação!$AL$1,[1]Input!$E:$E,[1]Comparação!$AL$2,[1]Input!$F:$F,[1]Comparação!AL19) -> #VALUE! | AN19: =SUMIFS([1]Input!$M:$M,[1]Input!$A:$A,[1]Comparação!$AL$1,[1]Input!$E:$E,[1]Comparação!$AL$2,[1]Input!$F:$F,[1]Comparação!AL19) -> #VALUE! | AO19: =IF(AN19=0,"",AN19/AM19) -> #VALUE! | AP19: Haleon | AQ19: =SUMIFS([1]Input!$AC:$AC,[1]Input!$A:$A,[1]Comparação!$AP$1,[1]Input!$E:$E,[1]Comparação!$AP$2,[1]Input!$F:$F,[1]Comparação!AP19) -> #VALUE! | AR19: =SUMIFS([1]Input!$M:$M,[1]Input!$A:$A,[1]Comparação!$AP$1,[1]Input!$E:$E,[1]Comparação!$AP$2,[1]Input!$F:$F,[1]Comparação!AP19) -> #VALUE! | AS19: =IF(AR19=0,"",AR19/AQ19) -> #VALUE! | AT19: Haleon | AU19: =SUMIFS([1]Input!$AC:$AC,[1]Input!$A:$A,[1]Comparação!$AT$1,[1]Input!$E:$E,[1]Comparação!$AT$2,[1]Input!$F:$F,[1]Comparação!AT19) -> #VALUE! | AV19: =SUMIFS([1]Input!$M:$M,[1]Input!$A:$A,[1]Comparação!$AT$1,[1]Input!$E:$E,[1]Comparação!$AT$2,[1]Input!$F:$F,[1]Comparação!AT19) -> #VALUE! | AW19: =IF(AV19=0,"",AV19/AU19) -> #VALUE! | AY19: Haleon
B20: Trident | C20: =SUMIFS(Input!$AA:$AA,Input!$A:$A,Comparação!$B$1,Input!$E:$E,Comparação!$B$2,Input!$F:$F,Comparação!B20) -> 0 | D20: =SUMIFS(Input!$K:$K,Input!$A:$A,Comparação!$B$1,Input!$E:$E,Comparação!$B$2,Input!$F:$F,Comparação!B20) -> 0 | F20: Trident | G20: =SUMIFS(Input!$AA:$AA,Input!$A:$A,$F$1,Input!$E:$E,Comparação!$F$2,Input!$F:$F,Comparação!F20) -> 0 | H20: =SUMIFS(Input!$K:$K,Input!$A:$A,$F$1,Input!$E:$E,$F$2,Input!$F:$F,Comparação!F20) -> 0 | J20: Trident | K20: =SUMIFS(Input!$AA:$AA,Input!$A:$A,$J$1,Input!$E:$E,Comparação!$J$2,Input!$F:$F,Comparação!J20) -> 0 | L20: =SUMIFS(Input!$K:$K,Input!$A:$A,$J$1,Input!$E:$E,$J$2,Input!$F:$F,Comparação!J20) -> 0 | M20: =IF(L20=0,"",L20/K20) | N20: Trident | O20: =SUMIFS(Input!$AA:$AA,Input!$A:$A,$N$1,Input!$E:$E,Comparação!$N$2,Input!$F:$F,Comparação!N20) -> 0 | P20: =SUMIFS(Input!$K:$K,Input!$A:$A,$N$1,Input!$E:$E,$N$2,Input!$F:$F,Comparação!N20) -> 0 | Q20: =IF(P20=0,"",P20/O20) | R20: Trident | S20: =SUMIFS(Input!$AA:$AA,Input!$A:$A,$R$1,Input!$E:$E,Comparação!$R$2,Input!$F:$F,Comparação!R20) -> 0 | T20: =SUMIFS(Input!$K:$K,Input!$A:$A,$R$1,Input!$E:$E,$R$2,Input!$F:$F,Comparação!R20) -> 0 | U20: =IF(T20=0,"",T20/S20) | V20: Trident | W20: =SUMIFS([1]Input!$AC:$AC,[1]Input!$A:$A,[1]Comparação!$V$1,[1]Input!$E:$E,[1]Comparação!$V$2,[1]Input!$F:$F,[1]Comparação!V20) -> #VALUE! | X20: =SUMIFS([1]Input!$M:$M,[1]Input!$A:$A,[1]Comparação!$V$1,[1]Input!$E:$E,[1]Comparação!$V$2,[1]Input!$F:$F,[1]Comparação!V20) -> #VALUE! | Y20: =IF(X20=0,"",X20/W20) -> #VALUE! | Z20: Trident | AA20: =SUMIFS([1]Input!$AC:$AC,[1]Input!$A:$A,[1]Comparação!$Z$1,[1]Input!$E:$E,[1]Comparação!$Z$2,[1]Input!$F:$F,[1]Comparação!Z20) -> #VALUE! | AB20: =SUMIFS([1]Input!$M:$M,[1]Input!$A:$A,[1]Comparação!$Z$1,[1]Input!$E:$E,[1]Comparação!$Z$2,[1]Input!$F:$F,[1]Comparação!Z20) -> #VALUE! | AC20: =IF(AB20=0,"",AB20/AA20) -> #VALUE! | AD20: Trident | AE20: =SUMIFS([1]Input!$AC:$AC,[1]Input!$A:$A,[1]Comparação!$AD$1,[1]Input!$E:$E,[1]Comparação!$AD$2,[1]Input!$F:$F,[1]Comparação!AD20) -> #VALUE! | AF20: =SUMIFS([1]Input!$M:$M,[1]Input!$A:$A,[1]Comparação!$AD$1,[1]Input!$E:$E,[1]Comparação!$AD$2,[1]Input!$F:$F,[1]Comparação!AD20) -> #VALUE! | AG20: =IF(AF20=0,"",AF20/AE20) -> #VALUE! | AH20: Trident | AI20: =SUMIFS([1]Input!$AC:$AC,[1]Input!$A:$A,[1]Comparação!$AH$1,[1]Input!$E:$E,[1]Comparação!$AH$2,[1]Input!$F:$F,[1]Comparação!AH20) -> #VALUE! | AJ20: =SUMIFS([1]Input!$M:$M,[1]Input!$A:$A,[1]Comparação!$AH$1,[1]Input!$E:$E,[1]Comparação!$AH$2,[1]Input!$F:$F,[1]Comparação!AH20) -> #VALUE! | AK20: =IF(AJ20=0,"",AJ20/AI20) -> #VALUE! | AL20: Trident | AM20: =SUMIFS([1]Input!$AC:$AC,[1]Input!$A:$A,[1]Comparação!$AL$1,[1]Input!$E:$E,[1]Comparação!$AL$2,[1]Input!$F:$F,[1]Comparação!AL20) -> #VALUE! | AN20: =SUMIFS([1]Input!$M:$M,[1]Input!$A:$A,[1]Comparação!$AL$1,[1]Input!$E:$E,[1]Comparação!$AL$2,[1]Input!$F:$F,[1]Comparação!AL20) -> #VALUE! | AO20: =IF(AN20=0,"",AN20/AM20) -> #VALUE! | AP20: Trident | AQ20: =SUMIFS([1]Input!$AC:$AC,[1]Input!$A:$A,[1]Comparação!$AP$1,[1]Input!$E:$E,[1]Comparação!$AP$2,[1]Input!$F:$F,[1]Comparação!AP20) -> #VALUE! | AR20: =SUMIFS([1]Input!$M:$M,[1]Input!$A:$A,[1]Comparação!$AP$1,[1]Input!$E:$E,[1]Comparação!$AP$2,[1]Input!$F:$F,[1]Comparação!AP20) -> #VALUE! | AS20: =IF(AR20=0,"",AR20/AQ20) -> #VALUE! | AT20: Trident | AU20: =SUMIFS([1]Input!$AC:$AC,[1]Input!$A:$A,[1]Comparação!$AT$1,[1]Input!$E:$E,[1]Comparação!$AT$2,[1]Input!$F:$F,[1]Comparação!AT20) -> #VALUE! | AV20: =SUMIFS([1]Input!$M:$M,[1]Input!$A:$A,[1]Comparação!$AT$1,[1]Input!$E:$E,[1]Comparação!$AT$2,[1]Input!$F:$F,[1]Comparação!AT20) -> #VALUE! | AW20: =IF(AV20=0,"",AV20/AU20) -> #VALUE! | AY20: Trident
B21: Oceaneering | C21: =SUMIFS(Input!$AA:$AA,Input!$A:$A,Comparação!$B$1,Input!$E:$E,Comparação!$B$2,Input!$F:$F,Comparação!B21) -> 0 | D21: =SUMIFS(Input!$K:$K,Input!$A:$A,Comparação!$B$1,Input!$E:$E,Comparação!$B$2,Input!$F:$F,Comparação!B21) -> 0 | F21: Oceaneering | G21: =SUMIFS(Input!$AA:$AA,Input!$A:$A,$F$1,Input!$E:$E,Comparação!$F$2,Input!$F:$F,Comparação!F21) -> 0 | H21: =SUMIFS(Input!$K:$K,Input!$A:$A,$F$1,Input!$E:$E,$F$2,Input!$F:$F,Comparação!F21) -> 0 | J21: Oceaneering | K21: =SUMIFS(Input!$AA:$AA,Input!$A:$A,$J$1,Input!$E:$E,Comparação!$J$2,Input!$F:$F,Comparação!J21) -> 0 | L21: =SUMIFS(Input!$K:$K,Input!$A:$A,$J$1,Input!$E:$E,$J$2,Input!$F:$F,Comparação!J21) -> 0 | M21: =IF(L21=0,"",L21/K21) | N21: Oceaneering | O21: =SUMIFS(Input!$AA:$AA,Input!$A:$A,$N$1,Input!$E:$E,Comparação!$N$2,Input!$F:$F,Comparação!N21) -> 0 | P21: =SUMIFS(Input!$K:$K,Input!$A:$A,$N$1,Input!$E:$E,$N$2,Input!$F:$F,Comparação!N21) -> 0 | Q21: =IF(P21=0,"",P21/O21) | R21: Oceaneering | S21: =SUMIFS(Input!$AA:$AA,Input!$A:$A,$R$1,Input!$E:$E,Comparação!$R$2,Input!$F:$F,Comparação!R21) -> 0 | T21: =SUMIFS(Input!$K:$K,Input!$A:$A,$R$1,Input!$E:$E,$R$2,Input!$F:$F,Comparação!R21) -> 0 | U21: =IF(T21=0,"",T21/S21) | V21: Oceaneering | W21: =SUMIFS([1]Input!$AC:$AC,[1]Input!$A:$A,[1]Comparação!$V$1,[1]Input!$E:$E,[1]Comparação!$V$2,[1]Input!$F:$F,[1]Comparação!V21) -> #VALUE! | X21: =SUMIFS([1]Input!$M:$M,[1]Input!$A:$A,[1]Comparação!$V$1,[1]Input!$E:$E,[1]Comparação!$V$2,[1]Input!$F:$F,[1]Comparação!V21) -> #VALUE! | Y21: =IF(X21=0,"",X21/W21) -> #VALUE! | Z21: Oceaneering | AA21: =SUMIFS([1]Input!$AC:$AC,[1]Input!$A:$A,[1]Comparação!$Z$1,[1]Input!$E:$E,[1]Comparação!$Z$2,[1]Input!$F:$F,[1]Comparação!Z21) -> #VALUE! | AB21: =SUMIFS([1]Input!$M:$M,[1]Input!$A:$A,[1]Comparação!$Z$1,[1]Input!$E:$E,[1]Comparação!$Z$2,[1]Input!$F:$F,[1]Comparação!Z21) -> #VALUE! | AC21: =IF(AB21=0,"",AB21/AA21) -> #VALUE! | AD21: Oceaneering | AE21: =SUMIFS([1]Input!$AC:$AC,[1]Input!$A:$A,[1]Comparação!$AD$1,[1]Input!$E:$E,[1]Comparação!$AD$2,[1]Input!$F:$F,[1]Comparação!AD21) -> #VALUE! | AF21: =SUMIFS([1]Input!$M:$M,[1]Input!$A:$A,[1]Comparação!$AD$1,[1]Input!$E:$E,[1]Comparação!$AD$2,[1]Input!$F:$F,[1]Comparação!AD21) -> #VALUE! | AG21: =IF(AF21=0,"",AF21/AE21) -> #VALUE! | AH21: Oceaneering | AI21: =SUMIFS([1]Input!$AC:$AC,[1]Input!$A:$A,[1]Comparação!$AH$1,[1]Input!$E:$E,[1]Comparação!$AH$2,[1]Input!$F:$F,[1]Comparação!AH21) -> #VALUE! | AJ21: =SUMIFS([1]Input!$M:$M,[1]Input!$A:$A,[1]Comparação!$AH$1,[1]Input!$E:$E,[1]Comparação!$AH$2,[1]Input!$F:$F,[1]Comparação!AH21) -> #VALUE! | AK21: =IF(AJ21=0,"",AJ21/AI21) -> #VALUE! | AL21: Oceaneering | AM21: =SUMIFS([1]Input!$AC:$AC,[1]Input!$A:$A,[1]Comparação!$AL$1,[1]Input!$E:$E,[1]Comparação!$AL$2,[1]Input!$F:$F,[1]Comparação!AL21) -> #VALUE! | AN21: =SUMIFS([1]Input!$M:$M,[1]Input!$A:$A,[1]Comparação!$AL$1,[1]Input!$E:$E,[1]Comparação!$AL$2,[1]Input!$F:$F,[1]Comparação!AL21) -> #VALUE! | AO21: =IF(AN21=0,"",AN21/AM21) -> #VALUE! | AP21: Oceaneering | AQ21: =SUMIFS([1]Input!$AC:$AC,[1]Input!$A:$A,[1]Comparação!$AP$1,[1]Input!$E:$E,[1]Comparação!$AP$2,[1]Input!$F:$F,[1]Comparação!AP21) -> #VALUE! | AR21: =SUMIFS([1]Input!$M:$M,[1]Input!$A:$A,[1]Comparação!$AP$1,[1]Input!$E:$E,[1]Comparação!$AP$2,[1]Input!$F:$F,[1]Comparação!AP21) -> #VALUE! | AS21: =IF(AR21=0,"",AR21/AQ21) -> #VALUE! | AT21: Oceaneering | AU21: =SUMIFS([1]Input!$AC:$AC,[1]Input!$A:$A,[1]Comparação!$AT$1,[1]Input!$E:$E,[1]Comparação!$AT$2,[1]Input!$F:$F,[1]Comparação!AT21) -> #VALUE! | AV21: =SUMIFS([1]Input!$M:$M,[1]Input!$A:$A,[1]Comparação!$AT$1,[1]Input!$E:$E,[1]Comparação!$AT$2,[1]Input!$F:$F,[1]Comparação!AT21) -> #VALUE! | AW21: =IF(AV21=0,"",AV21/AU21) -> #VALUE! | AY21: Oceaneering
B22: Fugro | C22: =SUMIFS(Input!$AA:$AA,Input!$A:$A,Comparação!$B$1,Input!$E:$E,Comparação!$B$2,Input!$F:$F,Comparação!B22) -> 0 | D22: =SUMIFS(Input!$K:$K,Input!$A:$A,Comparação!$B$1,Input!$E:$E,Comparação!$B$2,Input!$F:$F,Comparação!B22) -> 0 | F22: Fugro | G22: =SUMIFS(Input!$AA:$AA,Input!$A:$A,$F$1,Input!$E:$E,Comparação!$F$2,Input!$F:$F,Comparação!F22) -> 0 | H22: =SUMIFS(Input!$K:$K,Input!$A:$A,$F$1,Input!$E:$E,$F$2,Input!$F:$F,Comparação!F22) -> 0 | J22: Fugro | K22: =SUMIFS(Input!$AA:$AA,Input!$A:$A,$J$1,Input!$E:$E,Comparação!$J$2,Input!$F:$F,Comparação!J22) -> 0 | L22: =SUMIFS(Input!$K:$K,Input!$A:$A,$J$1,Input!$E:$E,$J$2,Input!$F:$F,Comparação!J22) -> 0 | M22: =IF(L22=0,"",L22/K22) | N22: Fugro | O22: =SUMIFS(Input!$AA:$AA,Input!$A:$A,$N$1,Input!$E:$E,Comparação!$N$2,Input!$F:$F,Comparação!N22) -> 0 | P22: =SUMIFS(Input!$K:$K,Input!$A:$A,$N$1,Input!$E:$E,$N$2,Input!$F:$F,Comparação!N22) -> 0 | Q22: =IF(P22=0,"",P22/O22) | R22: Fugro | S22: =SUMIFS(Input!$AA:$AA,Input!$A:$A,$R$1,Input!$E:$E,Comparação!$R$2,Input!$F:$F,Comparação!R22) -> 0 | T22: =SUMIFS(Input!$K:$K,Input!$A:$A,$R$1,Input!$E:$E,$R$2,Input!$F:$F,Comparação!R22) -> 0 | U22: =IF(T22=0,"",T22/S22) | V22: Fugro | W22: =SUMIFS([1]Input!$AC:$AC,[1]Input!$A:$A,[1]Comparação!$V$1,[1]Input!$E:$E,[1]Comparação!$V$2,[1]Input!$F:$F,[1]Comparação!V22) -> #VALUE! | X22: =SUMIFS([1]Input!$M:$M,[1]Input!$A:$A,[1]Comparação!$V$1,[1]Input!$E:$E,[1]Comparação!$V$2,[1]Input!$F:$F,[1]Comparação!V22) -> #VALUE! | Y22: =IF(X22=0,"",X22/W22) -> #VALUE! | Z22: Fugro | AA22: =SUMIFS([1]Input!$AC:$AC,[1]Input!$A:$A,[1]Comparação!$Z$1,[1]Input!$E:$E,[1]Comparação!$Z$2,[1]Input!$F:$F,[1]Comparação!Z22) -> #VALUE! | AB22: =SUMIFS([1]Input!$M:$M,[1]Input!$A:$A,[1]Comparação!$Z$1,[1]Input!$E:$E,[1]Comparação!$Z$2,[1]Input!$F:$F,[1]Comparação!Z22) -> #VALUE! | AC22: =IF(AB22=0,"",AB22/AA22) -> #VALUE! | AD22: Fugro | AE22: =SUMIFS([1]Input!$AC:$AC,[1]Input!$A:$A,[1]Comparação!$AD$1,[1]Input!$E:$E,[1]Comparação!$AD$2,[1]Input!$F:$F,[1]Comparação!AD22) -> #VALUE! | AF22: =SUMIFS([1]Input!$M:$M,[1]Input!$A:$A,[1]Comparação!$AD$1,[1]Input!$E:$E,[1]Comparação!$AD$2,[1]Input!$F:$F,[1]Comparação!AD22) -> #VALUE! | AG22: =IF(AF22=0,"",AF22/AE22) -> #VALUE! | AH22: Fugro | AI22: =SUMIFS([1]Input!$AC:$AC,[1]Input!$A:$A,[1]Comparação!$AH$1,[1]Input!$E:$E,[1]Comparação!$AH$2,[1]Input!$F:$F,[1]Comparação!AH22) -> #VALUE! | AJ22: =SUMIFS([1]Input!$M:$M,[1]Input!$A:$A,[1]Comparação!$AH$1,[1]Input!$E:$E,[1]Comparação!$AH$2,[1]Input!$F:$F,[1]Comparação!AH22) -> #VALUE! | AK22: =IF(AJ22=0,"",AJ22/AI22) -> #VALUE! | AL22: Fugro | AM22: =SUMIFS([1]Input!$AC:$AC,[1]Input!$A:$A,[1]Comparação!$AL$1,[1]Input!$E:$E,[1]Comparação!$AL$2,[1]Input!$F:$F,[1]Comparação!AL22) -> #VALUE! | AN22: =SUMIFS([1]Input!$M:$M,[1]Input!$A:$A,[1]Comparação!$AL$1,[1]Input!$E:$E,[1]Comparação!$AL$2,[1]Input!$F:$F,[1]Comparação!AL22) -> #VALUE! | AO22: =IF(AN22=0,"",AN22/AM22) -> #VALUE! | AP22: Fugro | AQ22: =SUMIFS([1]Input!$AC:$AC,[1]Input!$A:$A,[1]Comparação!$AP$1,[1]Input!$E:$E,[1]Comparação!$AP$2,[1]Input!$F:$F,[1]Comparação!AP22) -> #VALUE! | AR22: =SUMIFS([1]Input!$M:$M,[1]Input!$A:$A,[1]Comparação!$AP$1,[1]Input!$E:$E,[1]Comparação!$AP$2,[1]Input!$F:$F,[1]Comparação!AP22) -> #VALUE! | AS22: =IF(AR22=0,"",AR22/AQ22) -> #VALUE! | AT22: Fugro | AU22: =SUMIFS([1]Input!$AC:$AC,[1]Input!$A:$A,[1]Comparação!$AT$1,[1]Input!$E:$E,[1]Comparação!$AT$2,[1]Input!$F:$F,[1]Comparação!AT22) -> #VALUE! | AV22: =SUMIFS([1]Input!$M:$M,[1]Input!$A:$A,[1]Comparação!$AT$1,[1]Input!$E:$E,[1]Comparação!$AT$2,[1]Input!$F:$F,[1]Comparação!AT22) -> #VALUE! | AW22: =IF(AV22=0,"",AV22/AU22) -> #VALUE! | AY22: Fugro
B23: Qualitech USA | C23: =SUMIFS(Input!$AA:$AA,Input!$A:$A,Comparação!$B$1,Input!$E:$E,Comparação!$B$2,Input!$F:$F,Comparação!B23) -> 0 | D23: =SUMIFS(Input!$K:$K,Input!$A:$A,Comparação!$B$1,Input!$E:$E,Comparação!$B$2,Input!$F:$F,Comparação!B23) -> 0 | F23: Qualitech USA | G23: =SUMIFS(Input!$AA:$AA,Input!$A:$A,$F$1,Input!$E:$E,Comparação!$F$2,Input!$F:$F,Comparação!F23) -> 0 | H23: =SUMIFS(Input!$K:$K,Input!$A:$A,$F$1,Input!$E:$E,$F$2,Input!$F:$F,Comparação!F23) -> 0 | J23: Qualitech USA | K23: =SUMIFS(Input!$AA:$AA,Input!$A:$A,$J$1,Input!$E:$E,Comparação!$J$2,Input!$F:$F,Comparação!J23) -> 0 | L23: =SUMIFS(Input!$K:$K,Input!$A:$A,$J$1,Input!$E:$E,$J$2,Input!$F:$F,Comparação!J23) -> 0 | M23: =IF(L23=0,"",L23/K23) | N23: Qualitech USA | O23: =SUMIFS(Input!$AA:$AA,Input!$A:$A,$N$1,Input!$E:$E,Comparação!$N$2,Input!$F:$F,Comparação!N23) -> 0 | P23: =SUMIFS(Input!$K:$K,Input!$A:$A,$N$1,Input!$E:$E,$N$2,Input!$F:$F,Comparação!N23) -> 0 | Q23: =IF(P23=0,"",P23/O23) | R23: Qualitech USA | S23: =SUMIFS(Input!$AA:$AA,Input!$A:$A,$R$1,Input!$E:$E,Comparação!$R$2,Input!$F:$F,Comparação!R23) -> 0 | T23: =SUMIFS(Input!$K:$K,Input!$A:$A,$R$1,Input!$E:$E,$R$2,Input!$F:$F,Comparação!R23) -> 0 | U23: =IF(T23=0,"",T23/S23) | V23: Qualitech USA | W23: =SUMIFS([1]Input!$AC:$AC,[1]Input!$A:$A,[1]Comparação!$V$1,[1]Input!$E:$E,[1]Comparação!$V$2,[1]Input!$F:$F,[1]Comparação!V23) -> #VALUE! | X23: =SUMIFS([1]Input!$M:$M,[1]Input!$A:$A,[1]Comparação!$V$1,[1]Input!$E:$E,[1]Comparação!$V$2,[1]Input!$F:$F,[1]Comparação!V23) -> #VALUE! | Y23: =IF(X23=0,"",X23/W23) -> #VALUE! | Z23: Qualitech USA | AA23: =SUMIFS([1]Input!$AC:$AC,[1]Input!$A:$A,[1]Comparação!$Z$1,[1]Input!$E:$E,[1]Comparação!$Z$2,[1]Input!$F:$F,[1]Comparação!Z23) -> #VALUE! | AB23: =SUMIFS([1]Input!$M:$M,[1]Input!$A:$A,[1]Comparação!$Z$1,[1]Input!$E:$E,[1]Comparação!$Z$2,[1]Input!$F:$F,[1]Comparação!Z23) -> #VALUE! | AC23: =IF(AB23=0,"",AB23/AA23) -> #VALUE! | AD23: Qualitech USA | AE23: =SUMIFS([1]Input!$AC:$AC,[1]Input!$A:$A,[1]Comparação!$AD$1,[1]Input!$E:$E,[1]Comparação!$AD$2,[1]Input!$F:$F,[1]Comparação!AD23) -> #VALUE! | AF23: =SUMIFS([1]Input!$M:$M,[1]Input!$A:$A,[1]Comparação!$AD$1,[1]Input!$E:$E,[1]Comparação!$AD$2,[1]Input!$F:$F,[1]Comparação!AD23) -> #VALUE! | AG23: =IF(AF23=0,"",AF23/AE23) -> #VALUE! | AH23: Qualitech USA | AI23: =SUMIFS([1]Input!$AC:$AC,[1]Input!$A:$A,[1]Comparação!$AH$1,[1]Input!$E:$E,[1]Comparação!$AH$2,[1]Input!$F:$F,[1]Comparação!AH23) -> #VALUE! | AJ23: =SUMIFS([1]Input!$M:$M,[1]Input!$A:$A,[1]Comparação!$AH$1,[1]Input!$E:$E,[1]Comparação!$AH$2,[1]Input!$F:$F,[1]Comparação!AH23) -> #VALUE! | AK23: =IF(AJ23=0,"",AJ23/AI23) -> #VALUE! | AL23: Qualitech USA | AM23: =SUMIFS([1]Input!$AC:$AC,[1]Input!$A:$A,[1]Comparação!$AL$1,[1]Input!$E:$E,[1]Comparação!$AL$2,[1]Input!$F:$F,[1]Comparação!AL23) -> #VALUE! | AN23: =SUMIFS([1]Input!$M:$M,[1]Input!$A:$A,[1]Comparação!$AL$1,[1]Input!$E:$E,[1]Comparação!$AL$2,[1]Input!$F:$F,[1]Comparação!AL23) -> #VALUE! | AO23: =IF(AN23=0,"",AN23/AM23) -> #VALUE! | AP23: Qualitech USA | AQ23: =SUMIFS([1]Input!$AC:$AC,[1]Input!$A:$A,[1]Comparação!$AP$1,[1]Input!$E:$E,[1]Comparação!$AP$2,[1]Input!$F:$F,[1]Comparação!AP23) -> #VALUE! | AR23: =SUMIFS([1]Input!$M:$M,[1]Input!$A:$A,[1]Comparação!$AP$1,[1]Input!$E:$E,[1]Comparação!$AP$2,[1]Input!$F:$F,[1]Comparação!AP23) -> #VALUE! | AS23: =IF(AR23=0,"",AR23/AQ23) -> #VALUE! | AT23: Qualitech USA | AU23: =SUMIFS([1]Input!$AC:$AC,[1]Input!$A:$A,[1]Comparação!$AT$1,[1]Input!$E:$E,[1]Comparação!$AT$2,[1]Input!$F:$F,[1]Comparação!AT23) -> #VALUE! | AV23: =SUMIFS([1]Input!$M:$M,[1]Input!$A:$A,[1]Comparação!$AT$1,[1]Input!$E:$E,[1]Comparação!$AT$2,[1]Input!$F:$F,[1]Comparação!AT23) -> #VALUE! | AW23: =IF(AV23=0,"",AV23/AU23) -> #VALUE! | AY23: Qualitech USA
B24: Subsea7 | C24: =SUMIFS(Input!$AA:$AA,Input!$A:$A,Comparação!$B$1,Input!$E:$E,Comparação!$B$2,Input!$F:$F,Comparação!B24) -> 0 | D24: =SUMIFS(Input!$K:$K,Input!$A:$A,Comparação!$B$1,Input!$E:$E,Comparação!$B$2,Input!$F:$F,Comparação!B24) -> 0 | F24: Subsea7 | G24: =SUMIFS(Input!$AA:$AA,Input!$A:$A,$F$1,Input!$E:$E,Comparação!$F$2,Input!$F:$F,Comparação!F24) -> 0 | H24: =SUMIFS(Input!$K:$K,Input!$A:$A,$F$1,Input!$E:$E,$F$2,Input!$F:$F,Comparação!F24) -> 0 | J24: Subsea7 | K24: =SUMIFS(Input!$AA:$AA,Input!$A:$A,$J$1,Input!$E:$E,Comparação!$J$2,Input!$F:$F,Comparação!J24) -> 0 | L24: =SUMIFS(Input!$K:$K,Input!$A:$A,$J$1,Input!$E:$E,$J$2,Input!$F:$F,Comparação!J24) -> 0 | M24: =IF(L24=0,"",L24/K24) | N24: Subsea7 | O24: =SUMIFS(Input!$AA:$AA,Input!$A:$A,$N$1,Input!$E:$E,Comparação!$N$2,Input!$F:$F,Comparação!N24) -> 0 | P24: =SUMIFS(Input!$K:$K,Input!$A:$A,$N$1,Input!$E:$E,$N$2,Input!$F:$F,Comparação!N24) -> 0 | Q24: =IF(P24=0,"",P24/O24) | R24: Subsea7 | S24: =SUMIFS(Input!$AA:$AA,Input!$A:$A,$R$1,Input!$E:$E,Comparação!$R$2,Input!$F:$F,Comparação!R24) -> 0 | T24: =SUMIFS(Input!$K:$K,Input!$A:$A,$R$1,Input!$E:$E,$R$2,Input!$F:$F,Comparação!R24) -> 0 | U24: =IF(T24=0,"",T24/S24) | V24: Subsea7 | W24: =SUMIFS([1]Input!$AC:$AC,[1]Input!$A:$A,[1]Comparação!$V$1,[1]Input!$E:$E,[1]Comparação!$V$2,[1]Input!$F:$F,[1]Comparação!V24) -> #VALUE! | X24: =SUMIFS([1]Input!$M:$M,[1]Input!$A:$A,[1]Comparação!$V$1,[1]Input!$E:$E,[1]Comparação!$V$2,[1]Input!$F:$F,[1]Comparação!V24) -> #VALUE! | Y24: =IF(X24=0,"",X24/W24) -> #VALUE! | Z24: Subsea7 | AA24: =SUMIFS([1]Input!$AC:$AC,[1]Input!$A:$A,[1]Comparação!$Z$1,[1]Input!$E:$E,[1]Comparação!$Z$2,[1]Input!$F:$F,[1]Comparação!Z24) -> #VALUE! | AB24: =SUMIFS([1]Input!$M:$M,[1]Input!$A:$A,[1]Comparação!$Z$1,[1]Input!$E:$E,[1]Comparação!$Z$2,[1]Input!$F:$F,[1]Comparação!Z24) -> #VALUE! | AC24: =IF(AB24=0,"",AB24/AA24) -> #VALUE! | AD24: Subsea7 | AE24: =SUMIFS([1]Input!$AC:$AC,[1]Input!$A:$A,[1]Comparação!$AD$1,[1]Input!$E:$E,[1]Comparação!$AD$2,[1]Input!$F:$F,[1]Comparação!AD24) -> #VALUE! | AF24: =SUMIFS([1]Input!$M:$M,[1]Input!$A:$A,[1]Comparação!$AD$1,[1]Input!$E:$E,[1]Comparação!$AD$2,[1]Input!$F:$F,[1]Comparação!AD24) -> #VALUE! | AG24: =IF(AF24=0,"",AF24/AE24) -> #VALUE! | AH24: Subsea7 | AI24: =SUMIFS([1]Input!$AC:$AC,[1]Input!$A:$A,[1]Comparação!$AH$1,[1]Input!$E:$E,[1]Comparação!$AH$2,[1]Input!$F:$F,[1]Comparação!AH24) -> #VALUE! | AJ24: =SUMIFS([1]Input!$M:$M,[1]Input!$A:$A,[1]Comparação!$AH$1,[1]Input!$E:$E,[1]Comparação!$AH$2,[1]Input!$F:$F,[1]Comparação!AH24) -> #VALUE! | AK24: =IF(AJ24=0,"",AJ24/AI24) -> #VALUE! | AL24: Subsea7 | AM24: =SUMIFS([1]Input!$AC:$AC,[1]Input!$A:$A,[1]Comparação!$AL$1,[1]Input!$E:$E,[1]Comparação!$AL$2,[1]Input!$F:$F,[1]Comparação!AL24) -> #VALUE! | AN24: =SUMIFS([1]Input!$M:$M,[1]Input!$A:$A,[1]Comparação!$AL$1,[1]Input!$E:$E,[1]Comparação!$AL$2,[1]Input!$F:$F,[1]Comparação!AL24) -> #VALUE! | AO24: =IF(AN24=0,"",AN24/AM24) -> #VALUE! | AP24: Subsea7 | AQ24: =SUMIFS([1]Input!$AC:$AC,[1]Input!$A:$A,[1]Comparação!$AP$1,[1]Input!$E:$E,[1]Comparação!$AP$2,[1]Input!$F:$F,[1]Comparação!AP24) -> #VALUE! | AR24: =SUMIFS([1]Input!$M:$M,[1]Input!$A:$A,[1]Comparação!$AP$1,[1]Input!$E:$E,[1]Comparação!$AP$2,[1]Input!$F:$F,[1]Comparação!AP24) -> #VALUE! | AS24: =IF(AR24=0,"",AR24/AQ24) -> #VALUE! | AT24: Subsea7 | AU24: =SUMIFS([1]Input!$AC:$AC,[1]Input!$A:$A,[1]Comparação!$AT$1,[1]Input!$E:$E,[1]Comparação!$AT$2,[1]Input!$F:$F,[1]Comparação!AT24) -> #VALUE! | AV24: =SUMIFS([1]Input!$M:$M,[1]Input!$A:$A,[1]Comparação!$AT$1,[1]Input!$E:$E,[1]Comparação!$AT$2,[1]Input!$F:$F,[1]Comparação!AT24) -> #VALUE! | AW24: =IF(AV24=0,"",AV24/AU24) -> #VALUE! | AY24: Subsea7
B25: SEA1 | C25: =SUMIFS(Input!$AA:$AA,Input!$A:$A,Comparação!$B$1,Input!$E:$E,Comparação!$B$2,Input!$F:$F,Comparação!B25) -> 0 | D25: =SUMIFS(Input!$K:$K,Input!$A:$A,Comparação!$B$1,Input!$E:$E,Comparação!$B$2,Input!$F:$F,Comparação!B25) -> 0 | F25: SEA1 | G25: =SUMIFS(Input!$AA:$AA,Input!$A:$A,$F$1,Input!$E:$E,Comparação!$F$2,Input!$F:$F,Comparação!F25) -> 0 | H25: =SUMIFS(Input!$K:$K,Input!$A:$A,$F$1,Input!$E:$E,$F$2,Input!$F:$F,Comparação!F25) -> 0 | J25: SEA1 | K25: =SUMIFS(Input!$AA:$AA,Input!$A:$A,$J$1,Input!$E:$E,Comparação!$J$2,Input!$F:$F,Comparação!J25) -> 0 | L25: =SUMIFS(Input!$K:$K,Input!$A:$A,$J$1,Input!$E:$E,$J$2,Input!$F:$F,Comparação!J25) -> 0 | M25: =IF(L25=0,"",L25/K25) | N25: SEA1 | O25: =SUMIFS(Input!$AA:$AA,Input!$A:$A,$N$1,Input!$E:$E,Comparação!$N$2,Input!$F:$F,Comparação!N25) -> 0 | P25: =SUMIFS(Input!$K:$K,Input!$A:$A,$N$1,Input!$E:$E,$N$2,Input!$F:$F,Comparação!N25) -> 0 | Q25: =IF(P25=0,"",P25/O25) | R25: SEA1 | S25: =SUMIFS(Input!$AA:$AA,Input!$A:$A,$R$1,Input!$E:$E,Comparação!$R$2,Input!$F:$F,Comparação!R25) -> 0 | T25: =SUMIFS(Input!$K:$K,Input!$A:$A,$R$1,Input!$E:$E,$R$2,Input!$F:$F,Comparação!R25) -> 0 | U25: =IF(T25=0,"",T25/S25) | V25: SEA1 | W25: =SUMIFS([1]Input!$AC:$AC,[1]Input!$A:$A,[1]Comparação!$V$1,[1]Input!$E:$E,[1]Comparação!$V$2,[1]Input!$F:$F,[1]Comparação!V25) -> #VALUE! | X25: =SUMIFS([1]Input!$M:$M,[1]Input!$A:$A,[1]Comparação!$V$1,[1]Input!$E:$E,[1]Comparação!$V$2,[1]Input!$F:$F,[1]Comparação!V25) -> #VALUE! | Y25: =IF(X25=0,"",X25/W25) -> #VALUE! | Z25: SEA1 | AA25: =SUMIFS([1]Input!$AC:$AC,[1]Input!$A:$A,[1]Comparação!$Z$1,[1]Input!$E:$E,[1]Comparação!$Z$2,[1]Input!$F:$F,[1]Comparação!Z25) -> #VALUE! | AB25: =SUMIFS([1]Input!$M:$M,[1]Input!$A:$A,[1]Comparação!$Z$1,[1]Input!$E:$E,[1]Comparação!$Z$2,[1]Input!$F:$F,[1]Comparação!Z25) -> #VALUE! | AC25: =IF(AB25=0,"",AB25/AA25) -> #VALUE! | AD25: SEA1 | AE25: =SUMIFS([1]Input!$AC:$AC,[1]Input!$A:$A,[1]Comparação!$AD$1,[1]Input!$E:$E,[1]Comparação!$AD$2,[1]Input!$F:$F,[1]Comparação!AD25) -> #VALUE! | AF25: =SUMIFS([1]Input!$M:$M,[1]Input!$A:$A,[1]Comparação!$AD$1,[1]Input!$E:$E,[1]Comparação!$AD$2,[1]Input!$F:$F,[1]Comparação!AD25) -> #VALUE! | AG25: =IF(AF25=0,"",AF25/AE25) -> #VALUE! | AH25: SEA1 | AI25: =SUMIFS([1]Input!$AC:$AC,[1]Input!$A:$A,[1]Comparação!$AH$1,[1]Input!$E:$E,[1]Comparação!$AH$2,[1]Input!$F:$F,[1]Comparação!AH25) -> #VALUE! | AJ25: =SUMIFS([1]Input!$M:$M,[1]Input!$A:$A,[1]Comparação!$AH$1,[1]Input!$E:$E,[1]Comparação!$AH$2,[1]Input!$F:$F,[1]Comparação!AH25) -> #VALUE! | AK25: =IF(AJ25=0,"",AJ25/AI25) -> #VALUE! | AL25: SEA1 | AM25: =SUMIFS([1]Input!$AC:$AC,[1]Input!$A:$A,[1]Comparação!$AL$1,[1]Input!$E:$E,[1]Comparação!$AL$2,[1]Input!$F:$F,[1]Comparação!AL25) -> #VALUE! | AN25: =SUMIFS([1]Input!$M:$M,[1]Input!$A:$A,[1]Comparação!$AL$1,[1]Input!$E:$E,[1]Comparação!$AL$2,[1]Input!$F:$F,[1]Comparação!AL25) -> #VALUE! | AO25: =IF(AN25=0,"",AN25/AM25) -> #VALUE! | AP25: SEA1 | AQ25: =SUMIFS([1]Input!$AC:$AC,[1]Input!$A:$A,[1]Comparação!$AP$1,[1]Input!$E:$E,[1]Comparação!$AP$2,[1]Input!$F:$F,[1]Comparação!AP25) -> #VALUE! | AR25: =SUMIFS([1]Input!$M:$M,[1]Input!$A:$A,[1]Comparação!$AP$1,[1]Input!$E:$E,[1]Comparação!$AP$2,[1]Input!$F:$F,[1]Comparação!AP25) -> #VALUE! | AS25: =IF(AR25=0,"",AR25/AQ25) -> #VALUE! | AT25: SEA1 | AU25: =SUMIFS([1]Input!$AC:$AC,[1]Input!$A:$A,[1]Comparação!$AT$1,[1]Input!$E:$E,[1]Comparação!$AT$2,[1]Input!$F:$F,[1]Comparação!AT25) -> #VALUE! | AV25: =SUMIFS([1]Input!$M:$M,[1]Input!$A:$A,[1]Comparação!$AT$1,[1]Input!$E:$E,[1]Comparação!$AT$2,[1]Input!$F:$F,[1]Comparação!AT25) -> #VALUE! | AW25: =IF(AV25=0,"",AV25/AU25) -> #VALUE! | AY25: SEA1
B26: PRIO | C26: =SUMIFS(Input!$AA:$AA,Input!$A:$A,Comparação!$B$1,Input!$E:$E,Comparação!$B$2,Input!$F:$F,Comparação!B26) -> 0 | D26: =SUMIFS(Input!$K:$K,Input!$A:$A,Comparação!$B$1,Input!$E:$E,Comparação!$B$2,Input!$F:$F,Comparação!B26) -> 0 | F26: PRIO | G26: =SUMIFS(Input!$AA:$AA,Input!$A:$A,$F$1,Input!$E:$E,Comparação!$F$2,Input!$F:$F,Comparação!F26) -> 0 | H26: =SUMIFS(Input!$K:$K,Input!$A:$A,$F$1,Input!$E:$E,$F$2,Input!$F:$F,Comparação!F26) -> 0 | J26: PRIO | K26: =SUMIFS(Input!$AA:$AA,Input!$A:$A,$J$1,Input!$E:$E,Comparação!$J$2,Input!$F:$F,Comparação!J26) -> 0 | L26: =SUMIFS(Input!$K:$K,Input!$A:$A,$J$1,Input!$E:$E,$J$2,Input!$F:$F,Comparação!J26) -> 0 | M26: =IF(L26=0,"",L26/K26) | N26: PRIO | O26: =SUMIFS(Input!$AA:$AA,Input!$A:$A,$N$1,Input!$E:$E,Comparação!$N$2,Input!$F:$F,Comparação!N26) -> 0 | P26: =SUMIFS(Input!$K:$K,Input!$A:$A,$N$1,Input!$E:$E,$N$2,Input!$F:$F,Comparação!N26) -> 0 | Q26: =IF(P26=0,"",P26/O26) | R26: PRIO | S26: =SUMIFS(Input!$AA:$AA,Input!$A:$A,$R$1,Input!$E:$E,Comparação!$R$2,Input!$F:$F,Comparação!R26) -> 0 | T26: =SUMIFS(Input!$K:$K,Input!$A:$A,$R$1,Input!$E:$E,$R$2,Input!$F:$F,Comparação!R26) -> 0 | U26: =IF(T26=0,"",T26/S26) | V26: PRIO | W26: =SUMIFS([1]Input!$AC:$AC,[1]Input!$A:$A,[1]Comparação!$V$1,[1]Input!$E:$E,[1]Comparação!$V$2,[1]Input!$F:$F,[1]Comparação!V26) -> #VALUE! | X26: =SUMIFS([1]Input!$M:$M,[1]Input!$A:$A,[1]Comparação!$V$1,[1]Input!$E:$E,[1]Comparação!$V$2,[1]Input!$F:$F,[1]Comparação!V26) -> #VALUE! | Y26: =IF(X26=0,"",X26/W26) -> #VALUE! | Z26: PRIO | AA26: =SUMIFS([1]Input!$AC:$AC,[1]Input!$A:$A,[1]Comparação!$Z$1,[1]Input!$E:$E,[1]Comparação!$Z$2,[1]Input!$F:$F,[1]Comparação!Z26) -> #VALUE! | AB26: =SUMIFS([1]Input!$M:$M,[1]Input!$A:$A,[1]Comparação!$Z$1,[1]Input!$E:$E,[1]Comparação!$Z$2,[1]Input!$F:$F,[1]Comparação!Z26) -> #VALUE! | AC26: =IF(AB26=0,"",AB26/AA26) -> #VALUE! | AD26: PRIO | AE26: =SUMIFS([1]Input!$AC:$AC,[1]Input!$A:$A,[1]Comparação!$AD$1,[1]Input!$E:$E,[1]Comparação!$AD$2,[1]Input!$F:$F,[1]Comparação!AD26) -> #VALUE! | AF26: =SUMIFS([1]Input!$M:$M,[1]Input!$A:$A,[1]Comparação!$AD$1,[1]Input!$E:$E,[1]Comparação!$AD$2,[1]Input!$F:$F,[1]Comparação!AD26) -> #VALUE! | AG26: =IF(AF26=0,"",AF26/AE26) -> #VALUE! | AH26: PRIO | AI26: =SUMIFS([1]Input!$AC:$AC,[1]Input!$A:$A,[1]Comparação!$AH$1,[1]Input!$E:$E,[1]Comparação!$AH$2,[1]Input!$F:$F,[1]Comparação!AH26) -> #VALUE! | AJ26: =SUMIFS([1]Input!$M:$M,[1]Input!$A:$A,[1]Comparação!$AH$1,[1]Input!$E:$E,[1]Comparação!$AH$2,[1]Input!$F:$F,[1]Comparação!AH26) -> #VALUE! | AK26: =IF(AJ26=0,"",AJ26/AI26) -> #VALUE! | AL26: PRIO | AM26: =SUMIFS([1]Input!$AC:$AC,[1]Input!$A:$A,[1]Comparação!$AL$1,[1]Input!$E:$E,[1]Comparação!$AL$2,[1]Input!$F:$F,[1]Comparação!AL26) -> #VALUE! | AN26: =SUMIFS([1]Input!$M:$M,[1]Input!$A:$A,[1]Comparação!$AL$1,[1]Input!$E:$E,[1]Comparação!$AL$2,[1]Input!$F:$F,[1]Comparação!AL26) -> #VALUE! | AO26: =IF(AN26=0,"",AN26/AM26) -> #VALUE! | AP26: PRIO | AQ26: =SUMIFS([1]Input!$AC:$AC,[1]Input!$A:$A,[1]Comparação!$AP$1,[1]Input!$E:$E,[1]Comparação!$AP$2,[1]Input!$F:$F,[1]Comparação!AP26) -> #VALUE! | AR26: =SUMIFS([1]Input!$M:$M,[1]Input!$A:$A,[1]Comparação!$AP$1,[1]Input!$E:$E,[1]Comparação!$AP$2,[1]Input!$F:$F,[1]Comparação!AP26) -> #VALUE! | AS26: =IF(AR26=0,"",AR26/AQ26) -> #VALUE! | AT26: PRIO | AU26: =SUMIFS([1]Input!$AC:$AC,[1]Input!$A:$A,[1]Comparação!$AT$1,[1]Input!$E:$E,[1]Comparação!$AT$2,[1]Input!$F:$F,[1]Comparação!AT26) -> #VALUE! | AV26: =SUMIFS([1]Input!$M:$M,[1]Input!$A:$A,[1]Comparação!$AT$1,[1]Input!$E:$E,[1]Comparação!$AT$2,[1]Input!$F:$F,[1]Comparação!AT26) -> #VALUE! | AW26: =IF(AV26=0,"",AV26/AU26) -> #VALUE! | AY26: PRIO
